Workbook

Sheet Backup-Correos
A1: Servidor | B1: Carpeta | C1: Carpeta 1 | D1: Carpeta 2 | E1: Carpeta 3 | F1: Archivo | G1: CLOUD | H1: FECHA CARGA | I1: TamPST | J1: Tam OneDrive | K1: Columna1
A2: Docking | B2: Disco Duro D | C2: ORGANIZADO6 | D2: ATP | E2: Backup Karen Tovar | F2: Backup KarenTovar.pst | G2: Onedrive | H2: 45995 | I2: 20 GB
A3: Docking | B3: Disco Duro D | C3: ORGANIZADO6 | D3: ATP | E3: Backup Jeinson Montenegro | F3: BackupJeinsonMontenegro.pst | G3: Onedrive | H3: 45995 | I3: 8 GB | J3: 2 GB
A4: Docking | B4: Disco Duro D | C4: ORGANIZADO6 | D4: ATP | E4: Backup Jhonatan Rodriguez | F4: BackupJhonatanRodriguez.pst | G4: Onedrive | H4: 46000 | I4: 0.9 GB
A5: Docking | B5: Disco Duro D | C5: ORGANIZADO6 | D5: ATP | E5: Backup Sandro Zabaleta | F5: BackupSandroZabaleta.pst | G5: Onedrive | H5: 46001 | I5: 21 GB | J5: 2.5 GB
A6: Docking | B6: Disco Duro D | C6: ORGANIZADO6 | D6: ATP | E6: Backup Jairo Munoz | F6: BackupJairoMunoz.pst | G6: Onedrive | H6: 46007 | I6: 24 GB | J6: 16 GB
A7: Docking | B7: Disco Duro D | C7: ORGANIZADO6 | D7: ATP | E7: Backup David Lopez | F7: BackupDavidLopez.pst | G7: Onedrive | H7: 46007 | I7: 17 GB | J7: 0
A8: Docking | B8: Disco Duro D | C8: ORGANIZADO6 | D8: ATP | E8: Backup Cristian Cely | F8: BackupCristianCely.pst | G8: Onedrive | H8: 46036 | I8: 12 GB | J8: 30 GB
A9: Docking | B9: Disco Duro D | C9: ORGANIZADO6 | D9: ATP | E9: PST Diana Lopez | F9: diana.lopez.b@grupoconectar.co | G9: PST | H9: 46126 | I9: 6,34 GB | J9: 6,49 GB
A10: Docking | B10: Disco Duro D | C10: ORGANIZADO6 | D10: ATP | E10: PST Gestion de Permisos | F10: gestiondepermisosadmon@grupoconectar.co | G10: PST | H10: 46126 | I10: 6,13 GB | J10: 67,7 MB
A11: Docking | B11: Disco Duro D | C11: ORGANIZADO6 | D11: AZTECA | E11: BackUp Jhon Moreno | F11: jhon.moreno@grupoconectar.co | G11: PST | H11: 46197 | I11: 52 GB
A12: Docking | B12: Disco Duro D | C12: ORGANIZADO6 | D12: AZTECA | E12: BackUp Marolyn Muñoz | F12: marolyn.munoz@grupoconectar.co | G12: PST | H12: 46198 | I12: 4.9GB | J12: 0.2 GB
A13: Docking | B13: Disco Duro D | C13: ORGANIZADO6 | D13: AZTECA | E13: BackUp Edwin Soto | F13: edwin.soto@grupoconectar.co | G13: Onedrive | H13: 46204 | I13: 29.1GB | J13: 32.1GB
A14: Docking | B14: Disco Duro D | C14: ORGANIZADO6 | D14: AZTECA | E14: Backup Conectar Azteca | F14: conectar.azteca@grupoconectar.co | G14: OneDrive | H14: 46217 | I14: 1.4 GB | J14: 1.3 GB
A15: Docking | B15: Disco Duro D | C15: ORGANIZADO6 | D15: AZTECA | E15: Backup Miguel Ricardo | F15: backupMiguelRicardo | G15: OneDrive | H15: 46226 | I15: 50,5 GB | J15: 32.4GB
A16: Docking | B16: Disco Duro D | C16: ORGANIZADO6 | D16: CLARO R3 | E16: Backup Luis Agudelo | F16: BackupLuisAgudelo.pst | G16: EO | H16: 45662 | I16: 11 GB | J16: 0
A17: Docking | B17: Disco Duro D | C17: ORGANIZADO6 | D17: CLARO R3 | E17: Backup Yerli Romero | F17: BackupYerliRomero.pst | G17: EO | H17: 45664 | I17: 12 GB | J17: 2.13 GB
A18: Docking | B18: Disco Duro D | C18: ORGANIZADO6 | D18: CLARO R3 | E18: Backup Jonierth Velasquez | F18: BackupJonierthVelasquez.pst | G18: OneDrive | H18: 45666 | I18: 50 GB | J18: 1 GB
A19: Docking | B19: Disco Duro D | C19: ORGANIZADO6 | D19: CLARO R3 | E19: Backup Jeferson Bedoya | F19: BackupJefersonBedoya.pst | G19: Onedrive | H19: 45996 | I19: 3.5 GB | J19: 10 MB
A20: Docking | B20: Disco Duro D | C20: ORGANIZADO6 | D20: CLARO R3 | E20: Backup Paula Marulanda | F20: BackupPaulaMarulanda.pst | G20: Onedrive | H20: 45996 | I20: 9.7 GB | J20: 6 GB
A21: Docking | B21: Disco Duro D | C21: ORGANIZADO6 | D21: CLARO R3 | E21: Backup Maria Medellin | F21: BackupMariaMedellin.pst | G21: Onedrive | H21: 46000 | I21: 9.7 GB | J21: 3 GB
A22: Docking | B22: Disco Duro D | C22: ORGANIZADO6 | D22: CLARO R3 | E22: Backup Proyectos Palmira | F22: BackupProyectosPalmira.pst | G22: Onedrive | H22: 46000 | I22: 18.2 GB | J22: 280 MB
A23: Docking | B23: Disco Duro D | C23: ORGANIZADO6 | D23: CLARO R3 | E23: Backup Jimmy Ballen | F23: BackupJimmyBallen.pst | G23: solo pst | H23: 46002 | I23: 4.3 GB
A24: Docking | B24: Disco Duro D | C24: ORGANIZADO6 | D24: CLARO R3 | E24: Backup Eric Orjuela | F24: BackupEricOrjuela.pst | G24: solo pst | H24: 46003 | I24: 7.1 GB
A25: Docking | B25: Disco Duro D | C25: ORGANIZADO6 | D25: CLARO R3 | E25: Backup Ivan Arias | F25: BackupIvanArias.pst | G25: Onedrive | H25: 46007 | I25: 63 GB | J25: 6 GB
A26: Docking | B26: Disco Duro D | C26: ORGANIZADO6 | D26: CLARO R3 | E26: Backup Ruben Solano | F26: BackupRubenSolano.pst | G26: Onedrive | H26: 46008 | I26: 20 GB | J26: 6 GB
A27: Docking | B27: Disco Duro D | C27: ORGANIZADO6 | D27: CLARO R3 | E27: Backup Andrea Corredor | F27: BackupAndreaCorredor.pst | G27: Onedrive | H27: 46009 | I27: 48.5 GB | J27: 24.2 GB
A28: Docking | B28: Disco Duro D | C28: ORGANIZADO6 | D28: CLARO R3 | E28: Backup Diego Rozo | F28: BackupDiegoRozo.pst | G28: EO | H28: 46009 | I28: 13GB
A29: Docking | B29: Disco Duro D | C29: ORGANIZADO6 | D29: CLARO R3 | E29: Backup Steven Cedano | F29: BackupStevenCedano.pst | G29: OneDrive | H29: 46009 | I29: 6.1 GB | J29: 28 GB
A30: Docking | B30: Disco Duro D | C30: ORGANIZADO6 | D30: CLARO R3 | E30: Backup Ana Infante | F30: BackupAnaInfante.pst | G30: OneDrive | H30: 46010 | I30: 1.5 GB | J30: 20 GB
A31: Docking | B31: Disco Duro D | C31: ORGANIZADO6 | D31: CLARO R3 | E31: Backup Angelica Ramirez | F31: BackupAngelicaRamirez.pst | G31: EO | H31: 46010 | I31: 12.5 GB
A32: Docking | B32: Disco Duro D | C32: ORGANIZADO6 | D32: CLARO R3 | E32: Backup Miguel Alonso | F32: BackupMiguelAlonso.pst | G32: OneDrive | H32: 46014 | I32: 49 GB | J32: 2 GB
A33: Docking | B33: Disco Duro D | C33: ORGANIZADO6 | D33: CLARO R3 | E33: Backup Walter Burbano | F33: BackupWalterBurbano.pst | G33: OneDrive | H33: 46014 | I33: 51 GB | J33: 2.4 GB
A34: Docking | B34: Disco Duro D | C34: ORGANIZADO6 | D34: CLARO R3 | E34: Backup Supervisores Cali | F34: BackupSupervisoresCali.pst | G34: EO | H34: 46017 | I34: 2 GB
A35: Docking | B35: Disco Duro D | C35: ORGANIZADO6 | D35: CLARO R3 | E35: Backup German Molano | F35: BackupGermanMolano.pst | G35: OneDrive | H35: 46017 | I35: 47 GB | J35: 200 MB
A36: Docking | B36: Disco Duro D | C36: ORGANIZADO6 | D36: CLARO R3 | E36: Backup Jonathan Correa | F36: BackupJonathanCorrea.pst | G36: solo pst | H36: 46036 | I36: 3 GB | J36: 0
A37: Docking | B37: Disco Duro D | C37: ORGANIZADO6 | D37: CLARO R3 | E37: Backup Jhoan Ortiz | F37: BackupJhoanOrtiz.pst | G37: OneDrive | H37: 46037 | I37: 12 GB | J37: 8 GB
A38: Docking | B38: Disco Duro D | C38: ORGANIZADO6 | D38: CLARO R3 | E38: Backup Maria Sierra | F38: BackupMariaSierra.pst | G38: OneDrive | H38: 46041 | I38: 18 GB | J38: 25.8 GB
A39: Docking | B39: Disco Duro D | C39: ORGANIZADO6 | D39: CLARO R3 | E39: Backup Derly Quintero | F39: BackupderlyQuintero.pst | G39: OneDrive | H39: 46055 | I39: 13 GB | J39: 5 GB
A40: Docking | B40: Disco Duro D | C40: ORGANIZADO6 | D40: CLARO R3 | E40: Backup Jose Maestre | F40: BackupJoseMaestre.pst | G40: OneDrive | H40: 46057 | I40: 48 GB | J40: 100 MB
A41: Docking | B41: Disco Duro D | C41: ORGANIZADO6 | D41: CLARO R3 | E41: Backup Johan Sanchez | F41: BackupJohanSanchez.pst | G41: Onedrive | H41: 46059 | I41: 10.6 GB | J41: 41 GB
A42: Docking | B42: Disco Duro D | C42: ORGANIZADO6 | D42: CLARO R3 | E42: Backup Omar Quinonez | F42: BackupOmarQuinonez.pst | G42: Onedrive | H42: 46063 | I42: 14 GB | J42: 600 MB
A43: Docking | B43: Disco Duro D | C43: ORGANIZADO6 | D43: CLARO R3 | E43: Backup Heydi Barvo | F43: BackupHeydiBravo.pst | G43: Onedrive | H43: 46070 | I43: 14 GB | J43: 39.9 GB
A44: Docking | B44: Disco Duro D | C44: ORGANIZADO6 | D44: CLARO R3 | E44: Backup Laura Ramirez | F44: BackupLauraRamirez.pst | G44: Onedrive | H44: 46072 | I44: 800 MB | J44: 7.61 GB
A45: Docking | B45: Disco Duro D | C45: ORGANIZADO6 | D45: CLARO R3 | E45: Backup Nicoll Robles | F45: BackupNicol.robles@grupoconectar.co FEB 2026.pst | G45: PST | H45: 46078 | I45: 47 GB
A46: Docking | B46: Disco Duro D | C46: ORGANIZADO6 | D46: CLARO R3 | E46: Backup Carlos Giraldo | F46: BackupCarlosGiraldo.pst | G46: OneDrive | H46: 46085 | I46: 11 GB | J46: 3,42 GB
A47: Docking | B47: Disco Duro D | C47: ORGANIZADO6 | D47: CLARO R3 | E47: PST Claudia Muñoz | F47: claudia.munoz@grupoconectar.co | G47: PST | H47: 46128 | I47: 1,32 GB | J47: 491, MB
A48: Docking | B48: Disco Duro D | C48: ORGANIZADO6 | D48: CLARO R3 | E48: PST Documentacionzona1 | F48: documentacionzona1@grupoconectar.co | G48: PST | H48: 46140 | I48: 15,7GB | J48: 40,O KB
A49: Docking | B49: Disco Duro D | C49: ORGANIZADO6 | D49: CLARO R3 | E49: PST liderzona1@grupoconectar.co | F49: liderzona1@grupoconectar.co | G49: PST | H49: 46140 | I49: 7,07 GB | J49: 0
A50: Docking | B50: Disco Duro D | C50: ORGANIZADO6 | D50: CLARO R3 | E50: PST Juan Lopez | F50: juan.lopez@grupoconectar.co | G50: PST | H50: 46149 | I50: 3,31 GB | J50: 390 MB
A51: Docking | B51: Disco Duro D | C51: ORGANIZADO6 | D51: CLARO R3 | E51: PST Samuel Marin | F51: samuel.marin@grupoconectar.co | G51: PST | H51: 46175 | I51: 2,93 GB | J51: 20,1 GB
A52: Docking | B52: Disco Duro D | C52: ORGANIZADO6 | D52: CLARO R3 | E52: PST William Oliveros | F52: william.oliveros@grupoconectar.co | G52: PST | H52: 46178 | I52: 867,MB | J52: 0
A53: Docking | B53: Disco Duro D | C53: ORGANIZADO6 | D53: CLARO R3 | E53: PST Luisa Florero | F53: luisa.forero@grupoconectar.co | G53: PST | H53: 46178 | I53: 94,2 MB | J53: 0
A54: Docking | B54: Disco Duro D | C54: ORGANIZADO6 | D54: CLARO R3 | E54: PST Tatiana Grisales | F54: tatiana.grisales@grupoconectar.co | G54: PST | H54: 46197 | I54: 36.9 GB | J54: 0
A55: Docking | B55: Disco Duro D | C55: ORGANIZADO6 | D55: CLARO R3 | E55: Backup AuxTalentoHumano palmira | F55: auxiliartalentohumano.palmira@grupoconectar.co | G55: Onedrive | H55: 46205 | I55: 0.1GB | J55: 0
A56: Docking | B56: Disco Duro D | C56: ORGANIZADO6 | D56: CLARO R3 | E56: Backup Almacen Log Florencia | F56: Almacenlogisticaflorencia@grupoconectar.co | G56: Onedrive | H56: 46211 | I56: 7.2GB | J56: 1GB
A57: Docking | B57: Disco Duro D | C57: ORGANIZADO6 | D57: CLARO R3 | E57: Backup Miguel Castro | F57: miguel.castro@grupoconectar.co | G57: Onedrive | H57: 46231 | I57: 16.7GB | J57: 50MB
A58: Docking | B58: Disco Duro D | C58: ORGANIZADO6 | D58: COMERCIAL | E58: Backup JorgeSanchezGmail | F58: jorgealberto.sanchez@conectartv.com | G58: Drive | H58: 46205 | I58: 13.2GB | J58: 0.12GB
A59: Docking | B59: Disco Duro D | C59: ORGANIZADO6 | D59: COMERCIAL | E59: Backup Gerenciacontel | F59: gerenciacontel@grupoconectar.co | G59: OneDrive | H59: 46206 | I59: 5.6 GB | J59: 0
A60: Docking | B60: Disco Duro D | C60: ORGANIZADO6 | D60: HUAWEI | E60: Backup Julian Atehortua | F60: BackupJulianAtehortua.pst | G60: solo pst | H60: 46002 | I60: 13.1 GB
A61: Docking | B61: Disco Duro D | C61: ORGANIZADO6 | D61: HUAWEI | E61: Backup Diana Cardona | F61: BackupDianaCardona.pst | G61: Onedrive | H61: 46079 | I61: 1,7 GB | J61: 7 GB
A62: Docking | B62: Disco Duro D | C62: ORGANIZADO6 | D62: HUAWEI | E62: Backup Jorge Hurtado | F62: BackupJorgeHurtado.pst | G62: Onedrive | H62: 46083 | I62: 5 GB | J62: 700 MB
A63: Docking | B63: Disco Duro D | C63: ORGANIZADO6 | D63: HUAWEI | E63: Backup Alvaro Cruz Febrero | F63: BackupAlvaroCruzFebrero2026.pst | G63: PST | H63: 46093 | I63: 49 GB
A64: Docking | B64: Disco Duro D | C64: ORGANIZADO6 | D64: ISP | E64: PST Recaudo ISP | F64: recaudosisp@buum.com.co | G64: PST | H64: 46168 | I64: 396 MB | J64: 0
A65: Docking | B65: Disco Duro D | C65: ORGANIZADO6 | D65: ISP | E65: PST Juliana Sastre | F65: juliana.sastre@grupoconectar.co | G65: PST | H65: 46175 | I65: 9,44 GB | J65: 15,2 GB
A66: Docking | B66: Disco Duro D | C66: ORGANIZADO6 | D66: ISP | E66: Backup ServicioTecnico Buum | F66: serviciotecnicobuum@conectartv.com | G66: Drive | H66: 46231 | I66: 45.4KB | J66: 3KB
A67: Docking | B67: Disco Duro D | C67: ORGANIZADO6 | D67: PERU | E67: PST Alexander Matysek | F67: alexander.matysek@grupoconectar.co | G67: PST | H67: 46135 | I67: 631, MB | J67: 0
A68: Docking | B68: Disco Duro D | C68: ORGANIZADO6 | D68: PERU | E68: PST Alexis Quispe | F68: alexis.quispe@grupoconectar.co | G68: PST | H68: 46135 | I68: 8,10 MB | J68: 0
A69: Docking | B69: Disco Duro D | C69: ORGANIZADO6 | D69: PERU | E69: PST Alvaro Campos | F69: alvaro.campos@grupoconectar.co | G69: PST | H69: 46135 | I69: 710 MB | J69: 0
A70: Docking | B70: Disco Duro D | C70: ORGANIZADO6 | D70: PERU | E70: PST Angel Flores | F70: angel.flores@grupoconectar.co | G70: PST | H70: 46135 | I70: 651 MB | J70: 0
A71: Docking | B71: Disco Duro D | C71: ORGANIZADO6 | D71: PERU | E71: PST Brandon Flores | F71: brandon.flores@grupoconectar.co | G71: PST | H71: 46135 | I71: 3,95 GB | J71: 0
A72: Docking | B72: Disco Duro D | C72: ORGANIZADO6 | D72: PERU | E72: PST Bruce Gamonal | F72: bruce.gamonal@grupoconectar.co | G72: PST | H72: 46135 | I72: 4,36 GB | J72: 0
A73: Docking | B73: Disco Duro D | C73: ORGANIZADO6 | D73: PERU | E73: PST Bryan Murillo | F73: bryan.murillo@grupoconectar.co | G73: PST | H73: 46135 | I73: 3,91 GB | J73: 0
A74: Docking | B74: Disco Duro D | C74: ORGANIZADO6 | D74: PERU | E74: PST Caleb Alburqueque | F74: caleb.alburqueque@grupoconectar.co | G74: PST | H74: 46135 | I74: 1,86 GB | J74: 0
A75: Docking | B75: Disco Duro D | C75: ORGANIZADO6 | D75: PERU | E75: PST Eloy Alvarez | F75: eloy.alvarez@grupoconectar.co | G75: PST | H75: 46135 | I75: 1,79 GB | J75: 0
A76: Docking | B76: Disco Duro D | C76: ORGANIZADO6 | D76: PERU | E76: PST Erwinson Azuaje | F76: Erwinson.azuaje@grupoconectar.co | G76: PST | H76: 46135 | I76: 703,66 MB | J76: 0
A77: Docking | B77: Disco Duro D | C77: ORGANIZADO6 | D77: PERU | E77: PST Francisco Virguez | F77: francisco.virguez@grupoconectar.co | G77: PST | H77: 46135 | I77: 729,97 MB | J77: 0
A78: Docking | B78: Disco Duro D | C78: ORGANIZADO6 | D78: PERU | E78: PST Geronimo Cayampi | F78: geronimo.cayampi@grupoconectar.co | G78: PST | H78: 46135 | I78: 2,61 GB | J78: 0
... A97: Docking | B97: Disco Duro D | C97: ORGANIZADO6 | D97: PERU | E97: PST Cesar Tineo | F97: cesar.tineo@grupoconectar.co | G97: PST | H97: 46149 | I97: 5,25 GB | J97: 0
A98: Docking | B98: Disco Duro D | C98: ORGANIZADO6 | D98: PERU | E98: PST Yasmin Tarazona | F98: yasmin.tarazona@grupoconectar.co | G98: PST | H98: 46156 | I98: 11,6 GB | J98: 854 MB
A99: Docking | B99: Disco Duro D | C99: ORGANIZADO6 | D99: PERU | E99: PST Reporte Fografico | F99: reporte.fotografico@grupoconectar.co | G99: PST | H99: 46156 | I99: 2,89 GB | J99: 39,8 MB
A100: Docking | B100: Disco Duro D | C100: ORGANIZADO6 | D100: PERU | E100: PST Mirtha Yacolca | F100: mirtha.yacolca@grupoconectar.co | G100: PST | H100: 46156 | I100: 3,9 GB | J100: 161 MB
A101: Docking | B101: Disco Duro D | C101: ORGANIZADO6 | D101: PERU | E101: PST Franco Huarcaya | F101: franco.huarcaya@grupoconectar.co | G101: PST | H101: 46167 | I101: 4.90 GB | J101: 0
A102: Docking | B102: Disco Duro D | C102: ORGANIZADO6 | D102: PERU | E102: PST Marlene Solis | F102: marlenne.solis@grupoconectar.co | G102: PST | H102: 46167 | I102: 6,15 GB | J102: 421 MB
A103: Docking | B103: Disco Duro D | C103: ORGANIZADO6 | D103: PERU | E103: PST Samantha Lind | F103: Samantha.lind@grupoconectar.co | G103: PST | H103: 46167 | I103: 5,54 GB | J103: 0
A104: Docking | B104: Disco Duro D | C104: ORGANIZADO6 | D104: PERU | E104: PST Sait Diestra | F104: sait.diestra@grupoconectar.co | G104: PST | H104: 46167 | I104: 1,40 GB | J104: 0
A105: Docking | B105: Disco Duro D | C105: ORGANIZADO6 | D105: PERU | E105: PST Adrian Villar | F105: adrian.villar@grupoconectar.co | G105: PST | H105: 46167 | I105: 4,65 GB | J105: 0
A106: Docking | B106: Disco Duro D | C106: ORGANIZADO6 | D106: PERU | E106: PST Javier Cercado | F106: javier.cercado@grupoconectar.co | G106: PST | H106: 46167 | I106: 8,90 GB | J106: 8,52 GB
A107: Docking | B107: Disco Duro D | C107: ORGANIZADO6 | D107: PERU | E107: PST Luis Huaraca | F107: luis.huaraca@grupoconectar.co | G107: PST | H107: 46168 | I107: 17,2 GB | J107: 0
A108: Docking | B108: Disco Duro D | C108: ORGANIZADO6 | D108: PERU | E108: PST Javier Sifuentes | F108: javier.sifuentes@grupoconectar.co | G108: PST | H108: 46170 | I108: 17,1 GB | J108: 0
A109: Docking | B109: Disco Duro D | C109: ORGANIZADO6 | D109: PERU | E109: PST Adicionales Peru | F109: adicionales.peru@grupoconectar.co | G109: PST | H109: 46170 | I109: 808 MB | J109: 0
A110: Docking | B110: Disco Duro D | C110: ORGANIZADO6 | D110: PERU | E110: PST Marketing Telecomunicaciones | F110: marketing.telecomunicacionessac@grupoconectar.co | G110: PST | H110: 46170 | I110: 788 MB | J110: 0
A111: Docking | B111: Disco Duro D | C111: ORGANIZADO6 | D111: PERU | E111: PST Hoover Cordova | F111: hoover.cordova@grupoconectar.co | G111: PST | H111: 46175 | I111: 20,5 GB | J111: 16,7 GB
A112: Docking | B112: Disco Duro D | C112: ORGANIZADO6 | D112: PERU | E112: PST Alexander Zambrano | F112: alexander.zambrano@grupoconectar.co | G112: PST | H112: 46175 | I112: 1,42 GB | J112: 0
A113: Docking | B113: Disco Duro D | C113: ORGANIZADO6 | D113: PERU | E113: PST Raul Villanueva | F113: raul.villanueva@grupoconectar.co | G113: PST | H113: 46175 | I113: 10,3 GB | J113: 0
A114: Docking | B114: Disco Duro D | C114: ORGANIZADO6 | D114: PERU | E114: PST Cristhus Segura | F114: cristhus.segura@grupoconectar.co | G114: PST | H114: 46175 | I114: 1,45 GB | J114: 0
A115: Docking | B115: Disco Duro D | C115: ORGANIZADO6 | D115: PERU | E115: Backup William Muñoz | F115: william.munoz@grupoconectar.co | G115: OneDrive | H115: 46199 | I115: 26GB | J115: 0.7GB
A116: Docking | B116: Disco Duro D | C116: ORGANIZADO6 | D116: PERU | E116: Backup Winny Espinoza | F116: winny.espinoza@grupoconectar.co | G116: 44.5GB | H116: 46209 | I116: 44.5GB
A117: Docking | B117: Disco Duro D | C117: ORGANIZADO6 | D117: PERU | E117: BackUp Equipo Gabinete | F117: equipogabinete@conectartelecomunicaciones.com | G117: Drive | H117: 46212 | I117: 2.2GB | J117: 1.3GB
A118: Docking | B118: Disco Duro D | C118: ORGANIZADO6 | D118: PERU | E118: Backup Junior Rivera Peru | F118: junior.rivera@grupoconectar.co | G118: EO | H118: 46219 | I118: 1.1GB | J118: 0
...

Sheet CORREOS-PERÚ
A1: FECHA_CREACION | B1: CIUDAD LABOR | C1: PRECIO USD | D1: DOMINIO | E1: PLAN | F1: NUM_DOCUMENTO | G1: NOMBRE_USUARIO | H1: OBSERVACIÓN (Solicitante) | I1: APELLIDO NOMBRE | J1: CARGO | K1: CU1 | L1: CU1-PROCESO | M1: CU1-REGIONAL | N1: CU1-CIUDAD | O1: CU3 | P1: CU3-CLIENTE | Q1: CU3-LINEA DE NEGOCIO | R1: CU3-PROYECTO | S1: GRUPO | T1: EMPRESA | U1: PROCESO GEN | V1: % PROYECTO | W1: Baja Correo
A2: 43710 | B2: LIMA | C2: 7.56 | D2: (G) .TELECOM | E2: Google Workspace Business Starter | F2: 46151732 | G2: compras@conectartelecomunicaciones.com | H2: Wendy Lopez (Consulta) | I2: =VLOOKUP(F2,'PLANTA PERU'!A:AL,2,0) -> LOPEZ UCHUYA KATHERINE WENDY | J2: =VLOOKUP(F2,'PLANTA PERU'!A:AL,10,0) -> JEFE DE ADMINISTRACION Y SCS | K2: IGUL | L2: =VLOOKUP(F2,'PLANTA PERU'!A:AD,7,0) -> 0 | M2: NA | N2: =VLOOKUP(F2,'PLANTA PERU'!A:AD,12,0) -> TERMINO FIJO | O2: CSOM | P2: CLARO PERU | Q2: NA | R2: NA | S2: NA | T2: TELECOMUNICACIONES SAC | U2: NA | V2: NA
A3: 43866 | B3: LIMA | C3: 7.56 | D3: (G) .TELECOM | E3: Google Workspace Business Starter | F3: 73445684 | G3: Katherin.Maldonado@conectartelecomunicaciones.com | H3: LIMA | I3: =VLOOKUP(F3,'PLANTA PERU'!A:AL,2,0) -> #N/A | J3: =VLOOKUP(F3,'PLANTA PERU'!A:AL,10,0) -> #N/A | K3: IGUL | L3: =VLOOKUP(F3,'PLANTA PERU'!A:AD,7,0) -> #N/A | M3: NA | N3: =VLOOKUP(F3,'PLANTA PERU'!A:AD,12,0) -> #N/A | O3: CSOM | P3: CLARO PERU | Q3: NA | R3: NA | S3: NA | T3: TELECOMUNICACIONES SAC | U3: NA | V3: NA
A4: 44070 | B4: LIMA | C4: 7.56 | D4: (G) .TELECOM | E4: Google Workspace Business Starter | G4: actasdigitales@conectartelecomunicaciones.com | H4: LIMA | I4: =VLOOKUP(F4,'PLANTA PERU'!A:AL,2,0) -> #N/A | J4: =VLOOKUP(F4,'PLANTA PERU'!A:AL,10,0) -> #N/A | K4: IGUL | L4: =VLOOKUP(F4,'PLANTA PERU'!A:AD,7,0) -> #N/A | M4: NA | N4: =VLOOKUP(F4,'PLANTA PERU'!A:AD,12,0) -> #N/A | O4: CSOM | P4: CLARO PERU | Q4: NA | R4: NA | S4: NA | T4: TELECOMUNICACIONES SAC | U4: NA | V4: NA
A5: 44364 | B5: LIMA | C5: 12.6 | D5: (M) .CO | E5: Microsoft 365 Empresa Estándar | F5: 4718074 | G5: carlos.porras@grupoconectar.co | H5: LIMA | I5: =VLOOKUP(F5,'PLANTA PERU'!A:AL,2,0) -> PORRAS TIBATA CARLOS MAURICIO | J5: =VLOOKUP(F5,'PLANTA PERU'!A:AL,10,0) -> GERENTE GENERAL & REGIONAL MANAGER | K5: IGUL | L5: =VLOOKUP(F5,'PLANTA PERU'!A:AD,7,0) -> 0 | M5: NA | N5: =VLOOKUP(F5,'PLANTA PERU'!A:AD,12,0) -> TERMINO FIJO | O5: MSIM | P5: CLARO PERU | Q5: NA | R5: NA | S5: NA | T5: TELECOMUNICACIONES SAC | U5: NA | V5: NA
A6: 45174 | B6: LIMA | C6: 6.3 | D6: (M) .CO | E6: Microsoft 365 Empresa Básico | F6: 74214133 | G6: winny.espinoza@grupoconectar.co | H6: WINNY KRISSEL ESPINOZA ARGANDOÑA | I6: =VLOOKUP(F6,'PLANTA PERU'!A:AL,2,0) -> ESPINOZA ARGANDO?A WINNY KRISSEL | J6: =VLOOKUP(F6,'PLANTA PERU'!A:AL,10,0) -> GERENTE DE OPERACIONES | K6: IGUL | L6: =VLOOKUP(F6,'PLANTA PERU'!A:AD,7,0) -> 0 | M6: NA | N6: =VLOOKUP(F6,'PLANTA PERU'!A:AD,12,0) -> 0 | O6: MSIM | P6: HUAWEI PERU | Q6: NA | R6: NA | S6: NA | T6: TELECOMUNICACIONES SAC | U6: NA | V6: NA
A7: 45029 | B7: LIMA | C7: 4.53 | D7: (M) .CO | E7: Exchange Online (Plan 1) | F7: 70390056 | G7: jeancarlos.alfaro@grupoconectar.co | H7: LIMA (Técnico Especialista) | I7: =VLOOKUP(F7,'PLANTA PERU'!A:AL,2,0) -> ALFARO RODRIGUEZ JEANCARLOS DAVID EDEY | J7: =VLOOKUP(F7,'PLANTA PERU'!A:AL,10,0) -> TECNICO ESPECIALISTA | K7: IGUL | L7: =VLOOKUP(F7,'PLANTA PERU'!A:AD,7,0) -> 0 | M7: NA | N7: =VLOOKUP(F7,'PLANTA PERU'!A:AD,12,0) -> INDEFINIDO | O7: HNFM | P7: HUAWEI PERU | Q7: NA | R7: NA | S7: NA | T7: TELECOMUNICACIONES SAC | U7: NA | V7: NA
A8: 45296 | B8: LIMA | C8: 6.3 | D8: (M) .CO | E8: Microsoft 365 Empresa Básico | F8: 48685035 | G8: elizabeth.salazar@grupoconectar.co | H8: LIMA elizabeth Salazar Nizama | I8: =VLOOKUP(F8,'PLANTA PERU'!A:AL,2,0) -> SALAZAR NIZAMA ELIZABETH MARLENE | J8: =VLOOKUP(F8,'PLANTA PERU'!A:AL,10,0) -> BACK OFFICE DE LIQUIDACION | K8: IGUL | L8: =VLOOKUP(F8,'PLANTA PERU'!A:AD,7,0) -> 0 | M8: NA | N8: =VLOOKUP(F8,'PLANTA PERU'!A:AD,12,0) -> TERMINO FIJO | O8: MSIM | P8: CLARO PERU | Q8: NA | R8: NA | S8: NA | T8: TELECOMUNICACIONES SAC | U8: NA | V8: NA
A9: 45238 | B9: LIMA | C9: 4.53 | D9: (M) .CO | E9: Exchange Online (Plan 1) | F9: 46461207 | G9: richard.espinoza@grupoconectar.co | H9: Richard Sebastianni Espinoza Mendoza (Raul Villanueva) | I9: =VLOOKUP(F9,'PLANTA PERU'!A:AL,2,0) -> ESPINOZA MENDOZA RICHARD SEBASTIANNI | J9: =VLOOKUP(F9,'PLANTA PERU'!A:AL,10,0) -> TECNICO JUNIOR TDP | K9: IGUL | L9: =VLOOKUP(F9,'PLANTA PERU'!A:AD,7,0) -> 0 | M9: NA | N9: =VLOOKUP(F9,'PLANTA PERU'!A:AD,12,0) -> TERMINO FIJO | O9: HNFM | P9: HUAWEI PERU | Q9: NA | R9: NA | S9: NA | T9: TELECOMUNICACIONES SAC | U9: NA | V9: NA
A10: 45140 | B10: LIMA | C10: 4.53 | D10: (M) .CO | E10: Exchange Online (Plan 1) | F10: 74988593 | G10: victor.baldeon@grupoconectar.co | H10: VICTOR ALBERTO BALDEON LOMA | I10: =VLOOKUP(F10,'PLANTA PERU'!A:AL,2,0) -> BALDEON LOMA VICTOR ALBERTO | J10: =VLOOKUP(F10,'PLANTA PERU'!A:AL,10,0) -> ANALISTA DE LIQUIDACION | K10: IGUL | L10: =VLOOKUP(F10,'PLANTA PERU'!A:AD,7,0) -> 0 | M10: NA | N10: =VLOOKUP(F10,'PLANTA PERU'!A:AD,12,0) -> 0 | O10: HNFM | P10: HUAWEI PERU | Q10: NA | R10: NA | S10: NA | T10: TELECOMUNICACIONES SAC | U10: NA | V10: NA
A11: 45140 | B11: LIMA | C11: 4.53 | D11: (M) .CO | E11: Exchange Online (Plan 1) | F11: 61106340 | G11: jairzinho.uribe@grupoconectar.co | H11: URIBE QUILCA JAIRZINHO SAMIR | I11: =VLOOKUP(F11,'PLANTA PERU'!A:AL,2,0) -> URIBE QUILCA JAIRZINHO SAMIR | J11: =VLOOKUP(F11,'PLANTA PERU'!A:AL,10,0) -> TECNICO JUNIOR TDP | K11: IGUL | L11: =VLOOKUP(F11,'PLANTA PERU'!A:AD,7,0) -> 0 | M11: NA | N11: =VLOOKUP(F11,'PLANTA PERU'!A:AD,12,0) -> TERMINO FIJO | O11: HNFM | P11: HUAWEI PERU | Q11: NA | R11: NA | S11: NA | T11: TELECOMUNICACIONES SAC | U11: NA | V11: NA
A12: 45140 | B12: LIMA | C12: 4.53 | D12: (M) .CO | E12: Exchange Online (Plan 1) | F12: 2013590 | G12: armando.esteves@grupoconectar.co | H12: Maikers Armando Esteves Hernandez (Raul Villanueva) | I12: =VLOOKUP(F12,'PLANTA PERU'!A:AL,2,0) -> ESTEVES HERNANDEZ MAIKERS ARMANDO | J12: =VLOOKUP(F12,'PLANTA PERU'!A:AL,10,0) -> TECNICO JUNIOR TDP | K12: IGUL | L12: =VLOOKUP(F12,'PLANTA PERU'!A:AD,7,0) -> 0 | M12: NA | N12: =VLOOKUP(F12,'PLANTA PERU'!A:AD,12,0) -> TERMINO FIJO | O12: HNFM | P12: HUAWEI PERU | Q12: NA | R12: NA | S12: NA | T12: TELECOMUNICACIONES SAC | U12: NA | V12: NA
A13: 45140 | B13: LIMA | C13: 6.3 | D13: (M) .CO | E13: Microsoft 365 Empresa Básico | F13: 40418047 | G13: rita.canales@grupoconectar.co | H13: LIMA, RITA CANALES | I13: =VLOOKUP(F13,'PLANTA PERU'!A:AL,2,0) -> CANALES QUI?E RITA GRACIELA | J13: =VLOOKUP(F13,'PLANTA PERU'!A:AL,10,0) -> BACKOFFICE N2 | K13: IGUL | L13: =VLOOKUP(F13,'PLANTA PERU'!A:AD,7,0) -> 0 | M13: NA | N13: =VLOOKUP(F13,'PLANTA PERU'!A:AD,12,0) -> 0 | O13: HNFM | P13: HUAWEI PERU | Q13: NA | R13: NA | S13: NA | T13: TELECOMUNICACIONES SAC | U13: NA | V13: NA
A14: 45140 | B14: LIMA | C14: 4.53 | D14: (M) .CO | E14: Exchange Online (Plan 1) | F14: 71028231 | G14: darwin.tiburcio@grupoconectar.co | H14: TIBURCIO NEIRA DARWIN LEANDRO | I14: =VLOOKUP(F14,'PLANTA PERU'!A:AL,2,0) -> TIBURCIO NEIRA DARWIN LEANDRO | J14: =VLOOKUP(F14,'PLANTA PERU'!A:AL,10,0) -> TECNICO ESPECIALISTA | K14: IGUL | L14: =VLOOKUP(F14,'PLANTA PERU'!A:AD,7,0) -> 0 | M14: NA | N14: =VLOOKUP(F14,'PLANTA PERU'!A:AD,12,0) -> TERMINO FIJO | O14: HNFM | P14: HUAWEI PERU | Q14: NA | R14: NA | S14: NA | T14: TELECOMUNICACIONES SAC | U14: NA | V14: NA
A15: 45140 | B15: LIMA | C15: 4.53 | D15: (M) .CO | E15: Exchange Online (Plan 1) | F15: 3105416 | G15: dennys.huerta@grupoconectar.co | H15: HUERTA ZAMBRANO DENNYS KEN | I15: =VLOOKUP(F15,'PLANTA PERU'!A:AL,2,0) -> HUERTA ZAMBRANO DENNYS KEN | J15: =VLOOKUP(F15,'PLANTA PERU'!A:AL,10,0) -> SUPERVISOR FLM | K15: IGUL | L15: =VLOOKUP(F15,'PLANTA PERU'!A:AD,7,0) -> 0 | M15: NA | N15: =VLOOKUP(F15,'PLANTA PERU'!A:AD,12,0) -> 0 | O15: HNFM | P15: HUAWEI PERU | Q15: NA | R15: NA | S15: NA | T15: TELECOMUNICACIONES SAC | U15: NA | V15: NA
A16: 45140 | B16: LIMA | C16: 4.53 | D16: (M) .CO | E16: Exchange Online (Plan 1) | F16: 70158066 | G16: Daniton.Huaman@grupoconectar.co | H16: LIMA | I16: =VLOOKUP(F16,'PLANTA PERU'!A:AL,2,0) -> HUAMAN HUAMAN DANITON | J16: =VLOOKUP(F16,'PLANTA PERU'!A:AL,10,0) -> TECNICO ESPECIALISTA | K16: IGUL | L16: =VLOOKUP(F16,'PLANTA PERU'!A:AD,7,0) -> 0 | M16: NA | N16: =VLOOKUP(F16,'PLANTA PERU'!A:AD,12,0) -> TERMINO FIJO | O16: HNFM | P16: HUAWEI PERU | Q16: NA | R16: NA | S16: NA | T16: TELECOMUNICACIONES SAC | U16: NA | V16: NA
... A33: 45050 | B33: LIMA | C33: 6.3 | D33: (M) .CO | E33: Microsoft 365 Empresa Básico | F33: 43630508 | G33: andrea.leon@grupoconectar.co | H33: Andrea Leon Serquin (William Muñoz) | I33: =VLOOKUP(F33,'PLANTA PERU'!A:AL,2,0) -> LEON SERQUIN ANDREA | J33: =VLOOKUP(F33,'PLANTA PERU'!A:AL,10,0) -> ANALISTA DE NOMINAS | K33: IGUL | L33: =VLOOKUP(F33,'PLANTA PERU'!A:AD,7,0) -> 0 | M33: NA | N33: =VLOOKUP(F33,'PLANTA PERU'!A:AD,12,0) -> TERMINO FIJO | O33: MSIM | P33: CLARO PERU | Q33: NA | R33: NA | S33: NA | T33: TELECOMUNICACIONES SAC | U33: NA | V33: NA
A34: 45229 | B34: LIMA | C34: 6.3 | D34: (M) .CO | E34: Microsoft 365 Empresa Básico | F34: 74870938 | G34: bruno.alaluna@grupoconectar.co | H34: ALALUNA GOMEZ BRUNO ORLANDO | I34: =VLOOKUP(F34,'PLANTA PERU'!A:AL,2,0) -> ALALUNA GOMEZ BRUNO ORLANDO | J34: =VLOOKUP(F34,'PLANTA PERU'!A:AL,10,0) -> COORDINADOR LOGISTICO | K34: IGUL | L34: =VLOOKUP(F34,'PLANTA PERU'!A:AD,7,0) -> 0 | M34: NA | N34: =VLOOKUP(F34,'PLANTA PERU'!A:AD,12,0) -> 0 | O34: MSIM | P34: CLARO PERU | Q34: NA | R34: NA | S34: NA | T34: TELECOMUNICACIONES SAC | U34: NA | V34: NA | W34: REASIGNAR A: BERROSPI CHAUPIS IVAN RODRIGO DNI: 76297793
A35: 45106 | B35: LIMA | C35: 4.53 | D35: (M) .CO | E35: Exchange Online (Plan 1) | F35: 8890271 | G35: ivan.morales@grupoconectar.co | H35: LIMA IVÁN L MORALES S | I35: =VLOOKUP(F35,'PLANTA PERU'!A:AL,2,0) -> MORALES SOTELO IVAN LUIS | J35: =VLOOKUP(F35,'PLANTA PERU'!A:AL,10,0) -> SUPERVISOR DE INSTALACIONES | K35: IGUL | L35: =VLOOKUP(F35,'PLANTA PERU'!A:AD,7,0) -> 0 | M35: NA | N35: =VLOOKUP(F35,'PLANTA PERU'!A:AD,12,0) -> TERMINO FIJO | O35: MSIM | P35: CLARO PERU | Q35: NA | R35: NA | S35: NA | T35: TELECOMUNICACIONES SAC | U35: NA | V35: NA
A36: 45106 | B36: LIMA | C36: 6.3 | D36: (M) .CO | E36: Microsoft 365 Empresa Básico | F36: 9302925 | G36: edwin.molina@grupoconectar.co | H36: LIMA EDWIN M MOLINA V | I36: =VLOOKUP(F36,'PLANTA PERU'!A:AL,2,0) -> MOLINA VILA EDWIN MANUEL | J36: =VLOOKUP(F36,'PLANTA PERU'!A:AL,10,0) -> COORDINADOR DE SST | K36: IGUL | L36: =VLOOKUP(F36,'PLANTA PERU'!A:AD,7,0) -> 0 | M36: NA | N36: =VLOOKUP(F36,'PLANTA PERU'!A:AD,12,0) -> TERMINO FIJO | O36: MSIM | P36: CLARO PERU | Q36: NA | R36: NA | S36: NA | T36: TELECOMUNICACIONES SAC | U36: NA | V36: NA
A37: 45113 | B37: LIMA | C37: 6.3 | D37: (M) .CO | E37: Microsoft 365 Empresa Básico | F37: 46143644 | G37: meri.albornoz@grupoconectar.co | H37: MERI YENI ALBORNOZ VIGURIA | I37: =VLOOKUP(F37,'PLANTA PERU'!A:AL,2,0) -> ALBORNOZ VIGURIA MERI YENI | J37: =VLOOKUP(F37,'PLANTA PERU'!A:AL,10,0) -> AUXILIAR CONTABLE | K37: IGUL | L37: =VLOOKUP(F37,'PLANTA PERU'!A:AD,7,0) -> 0 | M37: NA | N37: =VLOOKUP(F37,'PLANTA PERU'!A:AD,12,0) -> 0 | O37: MSIM | P37: CLARO PERU | Q37: NA | R37: NA | S37: NA | T37: TELECOMUNICACIONES SAC | U37: NA | V37: NA
A38: 45113 | B38: LIMA | C38: 6.3 | D38: (M) .CO | E38: Microsoft 365 Empresa Básico | F38: 44156080 | G38: lucia.tello@grupoconectar.co | H38: Lucia Luz Tello Cabeza (William Muñoz) | I38: =VLOOKUP(F38,'PLANTA PERU'!A:AL,2,0) -> TELLO CABEZA LUCIA LUZ | J38: =VLOOKUP(F38,'PLANTA PERU'!A:AL,10,0) -> TESORERA | K38: IGUL | L38: =VLOOKUP(F38,'PLANTA PERU'!A:AD,7,0) -> 0 | M38: NA | N38: =VLOOKUP(F38,'PLANTA PERU'!A:AD,12,0) -> 0 | O38: MSIM | P38: CLARO PERU | Q38: NA | R38: NA | S38: NA | T38: TELECOMUNICACIONES SAC | U38: NA | V38: NA
A39: 45113 | B39: LIMA | C39: 6.3 | D39: (M) .CO | E39: Microsoft 365 Empresa Básico | F39: 44285911 | G39: almacen.sur@grupoconectar.co | H39: LIMA ALMACEN BASE SUR | I39: =VLOOKUP(F39,'PLANTA PERU'!A:AL,2,0) -> CAYCHO PACHECO MARIO MIGUEL | J39: =VLOOKUP(F39,'PLANTA PERU'!A:AL,10,0) -> SUPERVISOR LOGISTICO | K39: IGUL | L39: =VLOOKUP(F39,'PLANTA PERU'!A:AD,7,0) -> 0 | M39: NA | N39: =VLOOKUP(F39,'PLANTA PERU'!A:AD,12,0) -> TERMINO FIJO | O39: MSIM | P39: CLARO PERU | Q39: NA | R39: NA | S39: NA | T39: TELECOMUNICACIONES SAC | U39: NA | V39: NA
A40: 45119 | B40: LIMA | C40: 6.3 | D40: (M) .CO | E40: Microsoft 365 Empresa Básico | F40: 76297793 | G40: ivan.berrospi@grupoconectar.co | H40: Ivan Rodrigo Berrospi Chaupis (William Muñoz) | I40: =VLOOKUP(F40,'PLANTA PERU'!A:AL,2,0) -> BERROSPI CHAUPIS IVAN RODRIGO | J40: =VLOOKUP(F40,'PLANTA PERU'!A:AL,10,0) -> ANALISTA FINANCIERO | K40: IGUL | L40: =VLOOKUP(F40,'PLANTA PERU'!A:AD,7,0) -> 0 | M40: NA | N40: =VLOOKUP(F40,'PLANTA PERU'!A:AD,12,0) -> INDEFINIDO | O40: MSIM | P40: CLARO PERU | Q40: NA | R40: NA | S40: NA | T40: TELECOMUNICACIONES SAC | U40: NA | V40: NA
A41: 45119 | B41: LIMA | C41: 6.3 | D41: (M) .CO | E41: Microsoft 365 Empresa Básico | F41: 44277521 | G41: jean.melendez@grupoconectar.co | H41: JEAN PIERRE MELENDEZ ALCAZAR | I41: =VLOOKUP(F41,'PLANTA PERU'!A:AL,2,0) -> MELENDEZ ALCAZAR | J41: =VLOOKUP(F41,'PLANTA PERU'!A:AL,10,0) -> SUPERVISOR FLM ENTEL | K41: IGUL | L41: =VLOOKUP(F41,'PLANTA PERU'!A:AD,7,0) -> 0 | M41: NA | N41: =VLOOKUP(F41,'PLANTA PERU'!A:AD,12,0) -> 0 | O41: MSIM | P41: CLARO PERU | Q41: NA | R41: NA | S41: NA | T41: TELECOMUNICACIONES SAC | U41: NA | V41: NA
A42: 45140 | B42: LIMA | C42: 4.53 | D42: (M) .CO | E42: Exchange Online (Plan 1) | F42: 74941839 | G42: Segundo.Torrejon@grupoconectar.co | H42: SEGUNDO J TORREJÓN P | I42: =VLOOKUP(F42,'PLANTA PERU'!A:AL,2,0) -> TORREJON PULCE SEGUNDO JHONATAN | J42: =VLOOKUP(F42,'PLANTA PERU'!A:AL,10,0) -> TECNICO ESPECIALISTA | K42: IGUL | L42: =VLOOKUP(F42,'PLANTA PERU'!A:AD,7,0) -> 0 | M42: NA | N42: =VLOOKUP(F42,'PLANTA PERU'!A:AD,12,0) -> TERMINO FIJO | O42: HNFM | P42: HUAWEI PERU | Q42: NA | R42: NA | S42: NA | T42: TELECOMUNICACIONES SAC | U42: NA | V42: NA
A43: 45216 | B43: LIMA | C43: 6.3 | D43: (M) .CO | E43: Microsoft 365 Empresa Básico | F43: 70566879 | G43: caleb.alburqueque@grupoconectar.co | H43: ALBURQUEQUE RUEDA CALEB MIGUEL | I43: =VLOOKUP(F43,'PLANTA PERU'!A:AL,2,0) -> ALBURQUEQUE RUEDA CALEB MIGUEL | J43: =VLOOKUP(F43,'PLANTA PERU'!A:AL,10,0) -> AUXILIAR DE LIQUIDACI?N | K43: IGUL | L43: =VLOOKUP(F43,'PLANTA PERU'!A:AD,7,0) -> 0 | M43: NA | N43: =VLOOKUP(F43,'PLANTA PERU'!A:AD,12,0) -> 0 | O43: MSIM | P43: CLARO PERU | Q43: NA | R43: NA | S43: NA | T43: TELECOMUNICACIONES SAC | U43: NA | V43: NA
A44: 45163 | B44: LIMA | C44: 6.3 | D44: (M) .CO | E44: Microsoft 365 Empresa Básico | F44: 71490074 | G44: eliot.chavez@grupoconectar.co | H44: ELIOT MARTÍN CHAVEZ P | I44: =VLOOKUP(F44,'PLANTA PERU'!A:AL,2,0) -> CHAVEZ PALOMINO ELIOT MARTIN | J44: =VLOOKUP(F44,'PLANTA PERU'!A:AL,10,0) -> ANALISTA ADMINISTRATIVO | K44: IGUL | L44: =VLOOKUP(F44,'PLANTA PERU'!A:AD,7,0) -> 0 | M44: NA | N44: =VLOOKUP(F44,'PLANTA PERU'!A:AD,12,0) -> TERMINO FIJO | O44: MSIM | P44: CLARO PERU | Q44: NA | R44: NA | S44: NA | T44: TELECOMUNICACIONES SAC | U44: NA | V44: NA
A45: 45226 | B45: LIMA | C45: 6.3 | D45: (M) .CO | E45: Microsoft 365 Empresa Básico | F45: 76516783 | G45: kevin.herrera@grupoconectar.co | H45: HERRERA U KEVIN S | I45: =VLOOKUP(F45,'PLANTA PERU'!A:AL,2,0) -> HERRERA UCHUYA KEVIN STEVEN | J45: =VLOOKUP(F45,'PLANTA PERU'!A:AL,10,0) -> ANALISTA SSOMA | K45: IGUL | L45: =VLOOKUP(F45,'PLANTA PERU'!A:AD,7,0) -> 0 | M45: NA | N45: =VLOOKUP(F45,'PLANTA PERU'!A:AD,12,0) -> TERMINO FIJO | O45: HNFM | P45: HUAWEI PERU | Q45: NA | R45: NA | S45: NA | T45: TELECOMUNICACIONES SAC | U45: NA | V45: NA
A46: 45245 | B46: LIMA | C46: 4.53 | D46: (M) .CO | E46: Exchange Online (Plan 1) | F46: 5054577 | G46: ana.salazar@grupoconectar.co | H46: ANA ROSA SALAZAR RODRIGUEZ | I46: =VLOOKUP(F46,'PLANTA PERU'!A:AL,2,0) -> SALAZAR RODRIGUEZ ANA ROSA | J46: =VLOOKUP(F46,'PLANTA PERU'!A:AL,10,0) -> TECNICO JUNIOR | K46: IGUL | L46: =VLOOKUP(F46,'PLANTA PERU'!A:AD,7,0) -> 0 | M46: NA | N46: =VLOOKUP(F46,'PLANTA PERU'!A:AD,12,0) -> TERMINO FIJO | O46: MSIM | P46: CLARO PERU | Q46: NA | R46: NA | S46: NA | T46: TELECOMUNICACIONES SAC | U46: NA | V46: NA
... A62: 45343 | B62: LIMA | C62: 4.53 | D62: (M) .CO | E62: Exchange Online (Plan 1) | F62: 76765238 | G62: piero.solier@grupoconectar.co | H62: Piero Rodrigo Solier Galvez (Raul Villanueva) | I62: =VLOOKUP(F62,'PLANTA PERU'!A:AL,2,0) -> SOLIER GALVEZ PIERO RODRIGO | J62: =VLOOKUP(F62,'PLANTA PERU'!A:AL,10,0) -> BACK OFFICE | K62: IGUL | L62: =VLOOKUP(F62,'PLANTA PERU'!A:AD,7,0) -> 0 | M62: NA | N62: =VLOOKUP(F62,'PLANTA PERU'!A:AD,12,0) -> TERMINO FIJO | O62: HNFM | P62: HUAWEI PERU | Q62: NA | R62: NA | S62: NA | T62: TELECOMUNICACIONES SAC | U62: NA | V62: NA
A63: 45343 | B63: LIMA | C63: 4.53 | D63: (M) .CO | E63: Exchange Online (Plan 1) | F63: 75224735 | G63: cesar.curro@grupoconectar.co | H63: Cesar Antonio Curro Mendoza (William Muñoz) | I63: =VLOOKUP(F63,'PLANTA PERU'!A:AL,2,0) -> CURRO MENDOZA CESAR ANTONIO | J63: =VLOOKUP(F63,'PLANTA PERU'!A:AL,10,0) -> TECNICO ESPECIALISTA | K63: IGUL | L63: =VLOOKUP(F63,'PLANTA PERU'!A:AD,7,0) -> 0 | M63: NA | N63: =VLOOKUP(F63,'PLANTA PERU'!A:AD,12,0) -> TERMINO FIJO | O63: HNFM | P63: HUAWEI PERU | Q63: NA | R63: NA | S63: NA | T63: TELECOMUNICACIONES SAC | U63: NA | V63: NA | W63: SU APOYO PARA RECUPERAR EL ACCESO, TIENE REGISTRADO UN NUMERO EL CUAL NO TENEMOS PARA RECUPERAR SU CONTRASEÑA
A64: 45343 | B64: LIMA | C64: 4.53 | D64: (M) .CO | E64: Exchange Online (Plan 1) | F64: 73046819 | G64: eduardo.paredes@grupoconectar.co | H64: Christian Eduardo Paredes Marroquin (William Muñoz) | I64: =VLOOKUP(F64,'PLANTA PERU'!A:AL,2,0) -> PAREDES MARROQUIN CHRISTIAN EDUARDO | J64: =VLOOKUP(F64,'PLANTA PERU'!A:AL,10,0) -> TECNICO ESPECIALISTA | K64: IGUL | L64: =VLOOKUP(F64,'PLANTA PERU'!A:AD,7,0) -> 0 | M64: NA | N64: =VLOOKUP(F64,'PLANTA PERU'!A:AD,12,0) -> TERMINO FIJO | O64: MSIM | P64: CLARO PERU | Q64: NA | R64: NA | S64: NA | T64: TELECOMUNICACIONES SAC | U64: NA | V64: NA
A65: 45343 | B65: LIMA | C65: 4.53 | D65: (M) .CO | E65: Exchange Online (Plan 1) | F65: 72533709 | G65: joseph.garcia@grupoconectar.co | H65: Joseph Ronald Garcia Moscoso (Raul Villanueva) | I65: =VLOOKUP(F65,'PLANTA PERU'!A:AL,2,0) -> GARCIA MOSCOSO JOSEPH RONALD | J65: =VLOOKUP(F65,'PLANTA PERU'!A:AL,10,0) -> BACK OFFICE | K65: IGUL | L65: =VLOOKUP(F65,'PLANTA PERU'!A:AD,7,0) -> 0 | M65: NA | N65: =VLOOKUP(F65,'PLANTA PERU'!A:AD,12,0) -> TERMINO FIJO | O65: HNFM | P65: HUAWEI PERU | Q65: NA | R65: NA | S65: NA | T65: TELECOMUNICACIONES SAC | U65: NA | V65: NA
A66: 45343 | B66: LIMA | C66: 4.53 | D66: (M) .CO | E66: Exchange Online (Plan 1) | F66: 73046819 | G66: christian.paredes@grupoconectar.co | H66: PAREDES MARROQUIN CHRISTIAN EDUARDO | I66: =VLOOKUP(F66,'PLANTA PERU'!A:AL,2,0) -> PAREDES MARROQUIN CHRISTIAN EDUARDO | J66: =VLOOKUP(F66,'PLANTA PERU'!A:AL,10,0) -> TECNICO ESPECIALISTA | K66: IGUL | L66: =VLOOKUP(F66,'PLANTA PERU'!A:AD,7,0) -> 0 | M66: NA | N66: =VLOOKUP(F66,'PLANTA PERU'!A:AD,12,0) -> TERMINO FIJO | O66: HNFM | P66: HUAWEI PERU | Q66: NA | R66: NA | S66: NA | T66: TELECOMUNICACIONES SAC | U66: NA | V66: NA
A67: 45343 | B67: LIMA | C67: 4.53 | D67: (M) .CO | E67: Exchange Online (Plan 1) | F67: 72530565 | G67: hugo.pineda@grupoconectar.co | H67: Hugo Antolin Pineda Rachumi (Raul Villanueva) | I67: =VLOOKUP(F67,'PLANTA PERU'!A:AL,2,0) -> PINEDA RACHUMI HUGO ANTOLIN | J67: =VLOOKUP(F67,'PLANTA PERU'!A:AL,10,0) -> BACK OFFICE | K67: IGUL | L67: =VLOOKUP(F67,'PLANTA PERU'!A:AD,7,0) -> 0 | M67: NA | N67: =VLOOKUP(F67,'PLANTA PERU'!A:AD,12,0) -> TERMINO FIJO | O67: HNFM | P67: HUAWEI PERU | Q67: NA | R67: NA | S67: NA | T67: TELECOMUNICACIONES SAC | U67: NA | V67: NA
A68: 45343 | B68: LIMA | C68: 4.53 | D68: (M) .CO | E68: Exchange Online (Plan 1) | F68: 75544027 | G68: jose.escobedo@grupoconectar.co | H68: Jose Escobedo Cardenas (Raul Villanueva) | I68: =VLOOKUP(F68,'PLANTA PERU'!A:AL,2,0) -> ESCOBEDO CARDENAS JOSE HUMBERTO | J68: =VLOOKUP(F68,'PLANTA PERU'!A:AL,10,0) -> BACK OFFICE | K68: IGUL | L68: =VLOOKUP(F68,'PLANTA PERU'!A:AD,7,0) -> 0 | M68: NA | N68: =VLOOKUP(F68,'PLANTA PERU'!A:AD,12,0) -> TERMINO FIJO | O68: HNFM | P68: HUAWEI PERU | Q68: NA | R68: NA | S68: NA | T68: TELECOMUNICACIONES SAC | U68: NA | V68: NA
A69: 45119 | B69: LIMA | C69: 4.53 | D69: (M) .CO | E69: Exchange Online (Plan 1) | F69: 46933538 | G69: edson.campos@grupoconectar.co | H69: EDSON MANUEL CAMPOS CHERO | I69: =VLOOKUP(F69,'PLANTA PERU'!A:AL,2,0) -> CAMPOS CHERO EDSON MANUEL | J69: =VLOOKUP(F69,'PLANTA PERU'!A:AL,10,0) -> SUPERVISOR FLM ENTEL | K69: IGUL | L69: =VLOOKUP(F69,'PLANTA PERU'!A:AD,7,0) -> 0 | M69: NA | N69: =VLOOKUP(F69,'PLANTA PERU'!A:AD,12,0) -> 0 | O69: MSIM | P69: CLARO PERU | Q69: NA | R69: NA | S69: NA | T69: TELECOMUNICACIONES SAC | U69: NA | V69: NA
A70: 45348 | B70: LIMA | C70: 4.53 | D70: (M) .CO | E70: Exchange Online (Plan 1) | F70: 73013315 | G70: Cristhian.palomino@grupoconectar.co | H70: CRISTHIAN SMITH MARIO PALOMINO UNZUETA | I70: =VLOOKUP(F70,'PLANTA PERU'!A:AL,2,0) -> PALOMINO UNZUETA CRISTHIAN SMITH MARIO | J70: =VLOOKUP(F70,'PLANTA PERU'!A:AL,10,0) -> TECNICO JUNIOR | K70: IGUL | L70: =VLOOKUP(F70,'PLANTA PERU'!A:AD,7,0) -> 0 | M70: NA | N70: =VLOOKUP(F70,'PLANTA PERU'!A:AD,12,0) -> TERMINO FIJO | O70: HNFM | P70: HUAWEI PERU | Q70: NA | R70: NA | S70: NA | T70: TELECOMUNICACIONES SAC | U70: NA | V70: NA
A71: 45352 | B71: LIMA | C71: 4.53 | D71: (M) .CO | E71: Exchange Online (Plan 1) | F71: 71267193 | G71: anderson.alvis@grupoconectar.co | H71: Anderson Alvis Abisrror | I71: =VLOOKUP(F71,'PLANTA PERU'!A:AL,2,0) -> ALVIS ABISRROR ANDERSON | J71: =VLOOKUP(F71,'PLANTA PERU'!A:AL,10,0) -> TECNICO JUNIOR MOTORIZADO TDP | K71: IGUL | L71: =VLOOKUP(F71,'PLANTA PERU'!A:AD,7,0) -> 0 | M71: NA | N71: =VLOOKUP(F71,'PLANTA PERU'!A:AD,12,0) -> INDEFINIDO | O71: HNFM | P71: HUAWEI PERU | Q71: NA | R71: NA | S71: NA | T71: TELECOMUNICACIONES SAC | U71: NA | V71: NA
A72: 45352 | B72: LIMA | C72: 4.53 | D72: (M) .CO | E72: Exchange Online (Plan 1) | F72: 48457074 | G72: residencia.lurin@grupoconectar.co | H72: SERNAQUE ORDINOLA BORIS MARTIN | I72: =VLOOKUP(F72,'PLANTA PERU'!A:AL,2,0) -> SERNAQUE ORDINOLA BORIS MARTIN | J72: =VLOOKUP(F72,'PLANTA PERU'!A:AL,10,0) -> TECNICO RESIDENTE TDP | K72: IGUL | L72: =VLOOKUP(F72,'PLANTA PERU'!A:AD,7,0) -> 0 | M72: NA | N72: =VLOOKUP(F72,'PLANTA PERU'!A:AD,12,0) -> TERMINO FIJO | O72: HNFM | P72: HUAWEI PERU | Q72: NA | R72: NA | S72: NA | T72: TELECOMUNICACIONES SAC | U72: NA | V72: NA
A73: 45352 | B73: LIMA | C73: 4.53 | D73: (M) .CO | E73: Exchange Online (Plan 1) | F73: 46151732 | G73: residencia.sanisidro@grupoconectar.co | H73: SAENZ GARCIA VICTOR ANDRES | I73: =VLOOKUP(F73,'PLANTA PERU'!A:AL,2,0) -> LOPEZ UCHUYA KATHERINE WENDY | J73: =VLOOKUP(F73,'PLANTA PERU'!A:AL,10,0) -> JEFE DE ADMINISTRACION Y SCS | K73: IGUL | L73: =VLOOKUP(F73,'PLANTA PERU'!A:AD,7,0) -> 0 | M73: NA | N73: =VLOOKUP(F73,'PLANTA PERU'!A:AD,12,0) -> TERMINO FIJO | O73: HNFM | P73: HUAWEI PERU | Q73: NA | R73: NA | S73: NA | T73: TELECOMUNICACIONES SAC | U73: NA | V73: NA
A74: 45352 | B74: LIMA | C74: 4.53 | D74: (M) .CO | E74: Exchange Online (Plan 1) | F74: 41846774 | G74: jorge.willyams@grupoconectar.co | H74: Jorge Aparicio Pedro Willyams (Raul Villanueva) | I74: =VLOOKUP(F74,'PLANTA PERU'!A:AL,2,0) -> JORGE APARICIO PEDRO | J74: =VLOOKUP(F74,'PLANTA PERU'!A:AL,10,0) -> BACK OFFICE | K74: IGUL | L74: =VLOOKUP(F74,'PLANTA PERU'!A:AD,7,0) -> 0 | M74: NA | N74: =VLOOKUP(F74,'PLANTA PERU'!A:AD,12,0) -> TERMINO FIJO | O74: HNFM | P74: HUAWEI PERU | Q74: NA | R74: NA | S74: NA | T74: TELECOMUNICACIONES SAC | U74: NA | V74: NA
A75: 45352 | B75: LIMA | C75: 4.53 | D75: (M) .CO | E75: Exchange Online (Plan 1) | F75: 72907788 | G75: francis.velasques@grupoconectar.co | H75: VELASQUES QUIROZ FRANCIS DANIEL | I75: =VLOOKUP(F75,'PLANTA PERU'!A:AL,2,0) -> VELASQUEZ QUIROZ FRANCIS DANIEL | J75: =VLOOKUP(F75,'PLANTA PERU'!A:AL,10,0) -> TECNICO JUNIOR TDP | K75: IGUL | L75: =VLOOKUP(F75,'PLANTA PERU'!A:AD,7,0) -> 0 | M75: NA | N75: =VLOOKUP(F75,'PLANTA PERU'!A:AD,12,0) -> TERMINO FIJO | O75: HNFM | P75: HUAWEI PERU | Q75: NA | R75: NA | S75: NA | T75: TELECOMUNICACIONES SAC | U75: NA | V75: NA
A76: 45352 | B76: LIMA | C76: 4.53 | D76: (M) .CO | E76: Exchange Online (Plan 1) | F76: 46151732 | G76: residencia.polo1@grupoconectar.co | H76: PAIRAZAMAN TORRE ALBERTO JAVIER (residencia Polo1) | I76: =VLOOKUP(F76,'PLANTA PERU'!A:AL,2,0) -> LOPEZ UCHUYA KATHERINE WENDY | J76: =VLOOKUP(F76,'PLANTA PERU'!A:AL,10,0) -> JEFE DE ADMINISTRACION Y SCS | K76: IGUL | L76: =VLOOKUP(F76,'PLANTA PERU'!A:AD,7,0) -> 0 | M76: NA | N76: =VLOOKUP(F76,'PLANTA PERU'!A:AD,12,0) -> TERMINO FIJO | O76: HNFM | P76: HUAWEI PERU | Q76: NA | R76: NA | S76: NA | T76: TELECOMUNICACIONES SAC | U76: NA | V76: NA
A77: 45352 | B77: LIMA | C77: 4.53 | D77: (M) .CO | E77: Exchange Online (Plan 1) | F77: 45990537 | G77: residencia.miraflores@grupoconectar.co | I77: =VLOOKUP(F77,'PLANTA PERU'!A:AL,2,0) -> BECERRA SOTO SANDRO JOHAN | J77: =VLOOKUP(F77,'PLANTA PERU'!A:AL,10,0) -> TECNICO RESIDENTE TDP | K77: IGUL | L77: =VLOOKUP(F77,'PLANTA PERU'!A:AD,7,0) -> 0 | M77: NA | N77: =VLOOKUP(F77,'PLANTA PERU'!A:AD,12,0) -> TERMINO FIJO | O77: HNFM | P77: HUAWEI PERU | Q77: NA | R77: NA | S77: NA | T77: TELECOMUNICACIONES SAC | U77: NA | V77: NA
A78: 45352 | B78: LIMA | C78: 4.53 | D78: (M) .CO | E78: Exchange Online (Plan 1) | F78: 46151732 | G78: telepuerto@grupoconectar.co | H78: DENIS ALMANZA SEMINARIO (telepuerto) | I78: =VLOOKUP(F78,'PLANTA PERU'!A:AL,2,0) -> LOPEZ UCHUYA KATHERINE WENDY | J78: =VLOOKUP(F78,'PLANTA PERU'!A:AL,10,0) -> JEFE DE ADMINISTRACION Y SCS | K78: IGUL | L78: =VLOOKUP(F78,'PLANTA PERU'!A:AD,7,0) -> 0 | M78: NA | N78: =VLOOKUP(F78,'PLANTA PERU'!A:AD,12,0) -> TERMINO FIJO | O78: HNFM | P78: HUAWEI PERU | Q78: NA | R78: NA | S78: NA | T78: TELECOMUNICACIONES SAC | U78: NA | V78: NA
A79: 45352 | B79: LIMA | C79: 4.53 | D79: (M) .CO | E79: Exchange Online (Plan 1) | F79: 77666191 | G79: jeferson.janampa@grupoconectar.co | I79: =VLOOKUP(F79,'PLANTA PERU'!A:AL,2,0) -> JANAMPA REYMUNDO JEFERSON FRANCO | J79: =VLOOKUP(F79,'PLANTA PERU'!A:AL,10,0) -> TECNICO JUNIOR | K79: IGUL | L79: =VLOOKUP(F79,'PLANTA PERU'!A:AD,7,0) -> 0 | M79: NA | N79: =VLOOKUP(F79,'PLANTA PERU'!A:AD,12,0) -> TERMINO FIJO | O79: HNFM | P79: HUAWEI PERU | Q79: NA | R79: NA | S79: NA | T79: TELECOMUNICACIONES SAC | U79: NA | V79: NA
A80: 45352 | B80: LIMA | C80: 12.6 | D80: (M) .CO | E80: Microsoft 365 Empresa Estándar | F80: 71320287 | G80: pamela.garcia@grupoconectar.co | H80: Pamela Nicol Garcia Robles (William Muñoz) | I80: =VLOOKUP(F80,'PLANTA PERU'!A:AL,2,0) -> GARCIA ROBLES PAMELA NICOL | J80: =VLOOKUP(F80,'PLANTA PERU'!A:AL,10,0) -> ASISTENTE CONTABLE | K80: IGUL | L80: =VLOOKUP(F80,'PLANTA PERU'!A:AD,7,0) -> 0 | M80: NA | N80: =VLOOKUP(F80,'PLANTA PERU'!A:AD,12,0) -> 0 | O80: HNFM | P80: HUAWEI PERU | Q80: NA | R80: NA | S80: NA | T80: TELECOMUNICACIONES SAC | U80: NA | V80: NA
A81: 45352 | B81: LIMA | C81: 4.53 | D81: (M) .CO | E81: Exchange Online (Plan 1) | F81: 31936274 | G81: residencia.washintong@grupoconectar.co | I81: =VLOOKUP(F81,'PLANTA PERU'!A:AL,2,0) -> JAIMES ENRRIQUEZ GENNER ALFONSO | J81: =VLOOKUP(F81,'PLANTA PERU'!A:AL,10,0) -> TECNICO RESIDENTE TDP | K81: IGUL | L81: =VLOOKUP(F81,'PLANTA PERU'!A:AD,7,0) -> 0 | M81: NA | N81: =VLOOKUP(F81,'PLANTA PERU'!A:AD,12,0) -> TERMINO FIJO | O81: HNFM | P81: HUAWEI PERU | Q81: NA | R81: NA | S81: NA | T81: TELECOMUNICACIONES SAC | U81: NA | V81: NA
A82: 45352 | B82: LIMA | C82: 4.53 | D82: (M) .CO | E82: Exchange Online (Plan 1) | F82: 42174120 | G82: carlos.vizcarra@grupoconectar.co | I82: =VLOOKUP(F82,'PLANTA PERU'!A:AL,2,0) -> VIZCARRA JOAQUIN CARLOS ALBERTO | J82: =VLOOKUP(F82,'PLANTA PERU'!A:AL,10,0) -> TECNICO ESPECIALISTA TDP | K82: IGUL | L82: =VLOOKUP(F82,'PLANTA PERU'!A:AD,7,0) -> 0 | M82: NA | N82: =VLOOKUP(F82,'PLANTA PERU'!A:AD,12,0) -> TERMINO FIJO | O82: HNFM | P82: HUAWEI PERU | Q82: NA | R82: NA | S82: NA | T82: TELECOMUNICACIONES SAC | U82: NA | V82: NA
A83: 45352 | B83: LIMA | C83: 4.53 | D83: (M) .CO | E83: Exchange Online (Plan 1) | F83: 47991206 | G83: jose.chuima@grupoconectar.co | H83: Jose Luis Chuima Sauñe (Raul Villanueva) | I83: =VLOOKUP(F83,'PLANTA PERU'!A:AL,2,0) -> CHUIMA SAU?E JOSE LUIS | J83: =VLOOKUP(F83,'PLANTA PERU'!A:AL,10,0) -> BACK OFFICE | K83: IGUL | L83: =VLOOKUP(F83,'PLANTA PERU'!A:AD,7,0) -> 0 | M83: NA | N83: =VLOOKUP(F83,'PLANTA PERU'!A:AD,12,0) -> TERMINO FIJO | O83: HNFM | P83: HUAWEI PERU | Q83: NA | R83: NA | S83: NA | T83: TELECOMUNICACIONES SAC | U83: NA | V83: NA
A84: 45352 | B84: LIMA | C84: 4.53 | D84: (M) .CO | E84: Exchange Online (Plan 1) | F84: 7495834 | G84: michael.chavez@grupoconectar.co | I84: =VLOOKUP(F84,'PLANTA PERU'!A:AL,2,0) -> CHAVEZ UNTIVEROS MICHAEL EDWARD | J84: =VLOOKUP(F84,'PLANTA PERU'!A:AL,10,0) -> TECNICO ESPECIALISTA | K84: IGUL | L84: =VLOOKUP(F84,'PLANTA PERU'!A:AD,7,0) -> 0 | M84: NA | N84: =VLOOKUP(F84,'PLANTA PERU'!A:AD,12,0) -> TERMINO FIJO | O84: HNFM | P84: HUAWEI PERU | Q84: NA | R84: NA | S84: NA | T84: TELECOMUNICACIONES SAC | U84: NA | V84: NA
A85: 45352 | B85: LIMA | C85: 4.53 | D85: (M) .CO | E85: Exchange Online (Plan 1) | F85: 75688087 | G85: antony.rojas@grupoconectar.co | I85: =VLOOKUP(F85,'PLANTA PERU'!A:AL,2,0) -> ROJAS HUAMANI ANTONY RAFAEL | J85: =VLOOKUP(F85,'PLANTA PERU'!A:AL,10,0) -> TECNICO ESPECIALISTA TDP | K85: IGUL | L85: =VLOOKUP(F85,'PLANTA PERU'!A:AD,7,0) -> 0 | M85: NA | N85: =VLOOKUP(F85,'PLANTA PERU'!A:AD,12,0) -> TERMINO FIJO | O85: HNFM | P85: HUAWEI PERU | Q85: NA | R85: NA | S85: NA | T85: TELECOMUNICACIONES SAC | U85: NA | V85: NA
A86: 45352 | B86: LIMA | C86: 4.53 | D86: (M) .CO | E86: Exchange Online (Plan 1) | F86: 46944377 | G86: gubber.churata@grupoconectar.co | I86: =VLOOKUP(F86,'PLANTA PERU'!A:AL,2,0) -> CHURATA ZU?IGA GUBBER EDWIN | J86: =VLOOKUP(F86,'PLANTA PERU'!A:AL,10,0) -> TECNICO JUNIOR | K86: IGUL | L86: =VLOOKUP(F86,'PLANTA PERU'!A:AD,7,0) -> 0 | M86: NA | N86: =VLOOKUP(F86,'PLANTA PERU'!A:AD,12,0) -> TERMINO FIJO | O86: HNFM | P86: HUAWEI PERU | Q86: NA | R86: NA | S86: NA | T86: TELECOMUNICACIONES SAC | U86: NA | V86: NA
A87: 45352 | B87: LIMA | C87: 4.53 | D87: (M) .CO | E87: Exchange Online (Plan 1) | F87: 71820008 | G87: gustavo.durand@grupoconectar.co | I87: =VLOOKUP(F87,'PLANTA PERU'!A:AL,2,0) -> DURAND URQUIA GUSTAVO DANIEL | J87: =VLOOKUP(F87,'PLANTA PERU'!A:AL,10,0) -> TECNICO ESPECIALISTA TDP | K87: IGUL | L87: =VLOOKUP(F87,'PLANTA PERU'!A:AD,7,0) -> 0 | M87: NA | N87: =VLOOKUP(F87,'PLANTA PERU'!A:AD,12,0) -> TERMINO FIJO | O87: HNFM | P87: HUAWEI PERU | Q87: NA | R87: NA | S87: NA | T87: TELECOMUNICACIONES SAC | U87: NA | V87: NA
A88: 45352 | B88: LIMA | C88: 4.53 | D88: (M) .CO | E88: Exchange Online (Plan 1) | F88: 76007265 | G88: cesar.urbano@grupoconectar.co | H88: Cesar Aranda Urbano Jhordi (William Muñoz) | I88: =VLOOKUP(F88,'PLANTA PERU'!A:AL,2,0) -> ARANDA URBANO CESAR JORDHI | J88: =VLOOKUP(F88,'PLANTA PERU'!A:AL,10,0) -> TECNICO ESPECIALISTA | K88: IGUL | L88: =VLOOKUP(F88,'PLANTA PERU'!A:AD,7,0) -> 0 | M88: NA | N88: =VLOOKUP(F88,'PLANTA PERU'!A:AD,12,0) -> TERMINO FIJO | O88: HNFM | P88: HUAWEI PERU | Q88: NA | R88: NA | S88: NA | T88: TELECOMUNICACIONES SAC | U88: NA | V88: NA | W88: NO DAR DE BAJA
A89: 45352 | B89: LIMA | C89: 4.53 | D89: (M) .CO | E89: Exchange Online (Plan 1) | F89: 15449605 | G89: martin.hernandez@grupoconectar.co | H89: Martin Hector Hernandez Magallanes (Raul Villanueva) | I89: =VLOOKUP(F89,'PLANTA PERU'!A:AL,2,0) -> HERNANDEZ MAGALLANES MARTIN HECTOR | J89: =VLOOKUP(F89,'PLANTA PERU'!A:AL,10,0) -> BACK OFFICE | K89: IGUL | L89: =VLOOKUP(F89,'PLANTA PERU'!A:AD,7,0) -> 0 | M89: NA | N89: =VLOOKUP(F89,'PLANTA PERU'!A:AD,12,0) -> TERMINO FIJO | O89: HNFM | P89: HUAWEI PERU | Q89: NA | R89: NA | S89: NA | T89: TELECOMUNICACIONES SAC | U89: NA | V89: NA
A90: 45352 | B90: LIMA | C90: 4.53 | D90: (M) .CO | E90: Exchange Online (Plan 1) | F90: 40658303 | G90: carlos.cerron@grupoconectar.co | I90: =VLOOKUP(F90,'PLANTA PERU'!A:AL,2,0) -> CERRON CAMAYO CARLOS PABLO | J90: =VLOOKUP(F90,'PLANTA PERU'!A:AL,10,0) -> TECNICO ESPECIALISTA TDP | K90: IGUL | L90: =VLOOKUP(F90,'PLANTA PERU'!A:AD,7,0) -> 0 | M90: NA | N90: =VLOOKUP(F90,'PLANTA PERU'!A:AD,12,0) -> TERMINO FIJO | O90: MSIM | P90: CLARO PERU | Q90: NA | R90: NA | S90: NA | T90: TELECOMUNICACIONES SAC | U90: NA | V90: NA
A91: 45352 | B91: LIMA | C91: 4.53 | D91: (M) .CO | E91: Exchange Online (Plan 1) | F91: 76523092 | G91: antony.huarcaya@grupoconectar.co | I91: =VLOOKUP(F91,'PLANTA PERU'!A:AL,2,0) -> HUARCAYA HUAMAN ANTONY | J91: =VLOOKUP(F91,'PLANTA PERU'!A:AL,10,0) -> TECNICO JUNIOR | K91: IGUL | L91: =VLOOKUP(F91,'PLANTA PERU'!A:AD,7,0) -> 0 | M91: NA | N91: =VLOOKUP(F91,'PLANTA PERU'!A:AD,12,0) -> TERMINO FIJO | O91: HNFM | P91: HUAWEI PERU | Q91: NA | R91: NA | S91: NA | T91: TELECOMUNICACIONES SAC | U91: NA | V91: NA
A92: 45352 | B92: LIMA | C92: 4.53 | D92: (M) .CO | E92: Exchange Online (Plan 1) | F92: 71279121 | G92: jaime.campos@grupoconectar.co | I92: =VLOOKUP(F92,'PLANTA PERU'!A:AL,2,0) -> CAMPOS PE?A JAIME MANUEL | J92: =VLOOKUP(F92,'PLANTA PERU'!A:AL,10,0) -> TECNICO JUNIOR | K92: IGUL | L92: =VLOOKUP(F92,'PLANTA PERU'!A:AD,7,0) -> 0 | M92: NA | N92: =VLOOKUP(F92,'PLANTA PERU'!A:AD,12,0) -> TERMINO FIJO | O92: HNFM | P92: HUAWEI PERU | Q92: NA | R92: NA | S92: NA | T92: TELECOMUNICACIONES SAC | U92: NA | V92: NA
A93: 45352 | B93: LIMA | C93: 4.53 | D93: (M) .CO | E93: Exchange Online (Plan 1) | F93: 3017373 | G93: cesar.rojas@grupoconectar.co | I93: =VLOOKUP(F93,'PLANTA PERU'!A:AL,2,0) -> ROJAS PADILLA CESAR HUMBERTO | J93: =VLOOKUP(F93,'PLANTA PERU'!A:AL,10,0) -> SUPERVISOR FLM | K93: IGUL | L93: =VLOOKUP(F93,'PLANTA PERU'!A:AD,7,0) -> 0 | M93: NA | N93: =VLOOKUP(F93,'PLANTA PERU'!A:AD,12,0) -> TERMINO FIJO | O93: HNFM | P93: HUAWEI PERU | Q93: NA | R93: NA | S93: NA | T93: TELECOMUNICACIONES SAC | U93: NA | V93: NA
A94: 45352 | B94: LIMA | C94: 4.53 | D94: (M) .CO | E94: Exchange Online (Plan 1) | F94: 75421266 | G94: derek.hernandez@grupoconectar.co | I94: =VLOOKUP(F94,'PLANTA PERU'!A:AL,2,0) -> HERNANDEZ APARCANA DEREK EITAN | J94: =VLOOKUP(F94,'PLANTA PERU'!A:AL,10,0) -> TECNICO JUNIOR MOTORIZADO TDP | K94: IGUL | L94: =VLOOKUP(F94,'PLANTA PERU'!A:AD,7,0) -> 0 | M94: NA | N94: =VLOOKUP(F94,'PLANTA PERU'!A:AD,12,0) -> TERMINO FIJO | O94: HNFM | P94: HUAWEI PERU | Q94: NA | R94: NA | S94: NA | T94: TELECOMUNICACIONES SAC | U94: NA | V94: NA
A95: 45352 | B95: LIMA | C95: 4.53 | D95: (M) .CO | E95: Exchange Online (Plan 1) | F95: 70087717 | G95: carlos.zavala@grupoconectar.co | I95: =VLOOKUP(F95,'PLANTA PERU'!A:AL,2,0) -> ZAVALA BARRON CARLOS JOSSEPH | J95: =VLOOKUP(F95,'PLANTA PERU'!A:AL,10,0) -> TECNICO ESPECIALISTA | K95: IGUL | L95: =VLOOKUP(F95,'PLANTA PERU'!A:AD,7,0) -> 0 | M95: NA | N95: =VLOOKUP(F95,'PLANTA PERU'!A:AD,12,0) -> 0 | O95: HNFM | P95: HUAWEI PERU | Q95: NA | R95: NA | S95: NA | T95: TELECOMUNICACIONES SAC | U95: NA | V95: NA
A96: 45352 | B96: LIMA | C96: 4.53 | D96: (M) .CO | E96: Exchange Online (Plan 1) | F96: 9611762 | G96: juan.hernandez.t@grupoconectar.co | I96: =VLOOKUP(F96,'PLANTA PERU'!A:AL,2,0) -> HERNANDEZ TORRES JUAN ENRIQUE | J96: =VLOOKUP(F96,'PLANTA PERU'!A:AL,10,0) -> TECNICO ESPECIALISTA | K96: IGUL | L96: =VLOOKUP(F96,'PLANTA PERU'!A:AD,7,0) -> 0 | M96: NA | N96: =VLOOKUP(F96,'PLANTA PERU'!A:AD,12,0) -> TERMINO FIJO | O96: HNFM | P96: HUAWEI PERU | Q96: NA | R96: NA | S96: NA | T96: TELECOMUNICACIONES SAC | U96: NA | V96: NA
A97: 45352 | B97: LIMA | C97: 4.53 | D97: (M) .CO | E97: Exchange Online (Plan 1) | F97: 40109481 | G97: servicioalclienteperu@grupoconectar.co | H97: LIMA Supervisora RRHH - Trabajadora Social "Carol Sebastian" (Guido Escobar) | I97: =VLOOKUP(F97,'PLANTA PERU'!A:AL,2,0) -> SEBASTIAN GRAOS CAROL GUISSELA | J97: =VLOOKUP(F97,'PLANTA PERU'!A:AL,10,0) -> SUPERVISOR DE RRHH Y TS | K97: IGUL | L97: =VLOOKUP(F97,'PLANTA PERU'!A:AD,7,0) -> 0 | M97: NA | N97: =VLOOKUP(F97,'PLANTA PERU'!A:AD,12,0) -> TERMINO FIJO | O97: HNFM | P97: HUAWEI PERU | Q97: NA | R97: NA | S97: NA | T97: TELECOMUNICACIONES SAC | U97: NA | V97: NA
A98: 45352 | B98: LIMA | C98: 4.53 | D98: (M) .CO | E98: Exchange Online (Plan 1) | F98: 44931015 | G98: residencia.surquillo@grupoconectar.co | I98: =VLOOKUP(F98,'PLANTA PERU'!A:AL,2,0) -> SOLANO PERALTA JOSUE ARNALDO | J98: =VLOOKUP(F98,'PLANTA PERU'!A:AL,10,0) -> TECNICO RESIDENTE SENIOR | K98: IGUL | L98: =VLOOKUP(F98,'PLANTA PERU'!A:AD,7,0) -> 0 | M98: NA | N98: =VLOOKUP(F98,'PLANTA PERU'!A:AD,12,0) -> TERMINO FIJO | O98: HNFM | P98: HUAWEI PERU | Q98: NA | R98: NA | S98: NA | T98: TELECOMUNICACIONES SAC | U98: NA | V98: NA
A99: 45352 | B99: LIMA | C99: 4.53 | D99: (M) .CO | E99: Exchange Online (Plan 1) | F99: 75344954 | G99: santiago.fernandez@grupoconectar.co | I99: =VLOOKUP(F99,'PLANTA PERU'!A:AL,2,0) -> FERNANDEZ FACUNDO SANTIAGO DUVERLY | J99: =VLOOKUP(F99,'PLANTA PERU'!A:AL,10,0) -> TECNICO ESPECIALISTA JUNIOR | K99: IGUL | L99: =VLOOKUP(F99,'PLANTA PERU'!A:AD,7,0) -> 0 | M99: NA | N99: =VLOOKUP(F99,'PLANTA PERU'!A:AD,12,0) -> TERMINO FIJO | O99: HNFM | P99: HUAWEI PERU | Q99: NA | R99: NA | S99: NA | T99: TELECOMUNICACIONES SAC | U99: NA | V99: NA
A100: 45363 | B100: LIMA | C100: 4.53 | D100: (M) .CO | E100: Exchange Online (Plan 1) | F100: 75607129 | G100: antoni.guzman@grupoconectar.co | I100: =VLOOKUP(F100,'PLANTA PERU'!A:AL,2,0) -> GUZMAN VI?A ANTONI VICTOR | J100: =VLOOKUP(F100,'PLANTA PERU'!A:AL,10,0) -> TECNICO JUNIOR | K100: IGUL | L100: =VLOOKUP(F100,'PLANTA PERU'!A:AD,7,0) -> 0 | M100: NA | N100: =VLOOKUP(F100,'PLANTA PERU'!A:AD,12,0) -> TERMINO FIJO | O100: HNFM | P100: HUAWEI PERU | Q100: NA | R100: NA | S100: NA | T100: TELECOMUNICACIONES SAC | U100: NA | V100: NA
A101: 45352 | B101: LIMA | C101: 12.6 | D101: (M) .CO | E101: Microsoft 365 Empresa Estándar | F101: 43688420 | G101: antenor.miranda@grupoconectar.co | I101: =VLOOKUP(F101,'PLANTA PERU'!A:AL,2,0) -> MIRANDA SUAREZ ANTENOR | J101: =VLOOKUP(F101,'PLANTA PERU'!A:AL,10,0) -> JEFE DE RRHH | K101: IGUL | L101: =VLOOKUP(F101,'PLANTA PERU'!A:AD,7,0) -> 0 | M101: NA | N101: =VLOOKUP(F101,'PLANTA PERU'!A:AD,12,0) -> TERMINO FIJO | O101: HNFM | P101: HUAWEI PERU | Q101: NA | R101: NA | S101: NA | T101: TELECOMUNICACIONES SAC | U101: NA | V101: NA
A102: 45394 | B102: LIMA | C102: 6.3 | D102: (M) .CO | E102: Microsoft 365 Empresa Básico | F102: 43385497 | G102: alvaro.casaretto@grupoconectar.co | H102: ALVARO FRANCISCO CASARETTO IBAÑEZ | I102: =VLOOKUP(F102,'PLANTA PERU'!A:AL,2,0) -> #N/A | J102: =VLOOKUP(F102,'PLANTA PERU'!A:AL,10,0) -> #N/A | K102: IGUL | L102: =VLOOKUP(F102,'PLANTA PERU'!A:AD,7,0) -> #N/A | M102: NA | N102: =VLOOKUP(F102,'PLANTA PERU'!A:AD,12,0) -> #N/A | O102: MSIM | P102: CLARO PERU | Q102: NA | R102: NA | S102: NA | T102: TELECOMUNICACIONES SAC | U102: NA | V102: NA
A103: 45394 | B103: LIMA | C103: 4.53 | D103: (M) .CO | E103: Exchange Online (Plan 1) | F103: 40109481 | G103: carol.sebastian@grupoconectar.co | I103: =VLOOKUP(F103,'PLANTA PERU'!A:AL,2,0) -> SEBASTIAN GRAOS CAROL GUISSELA | J103: =VLOOKUP(F103,'PLANTA PERU'!A:AL,10,0) -> SUPERVISOR DE RRHH Y TS | K103: TGUL | L103: =VLOOKUP(F103,'PLANTA PERU'!A:AD,7,0) -> 0 | M103: NA | N103: =VLOOKUP(F103,'PLANTA PERU'!A:AD,12,0) -> TERMINO FIJO | O103: MSIM | P103: CLARO PERU | Q103: NA | R103: NA | S103: NA | T103: TELECOMUNICACIONES SAC | U103: NA | V103: NA
A104: 45408 | B104: LIMA | C104: 4.53 | D104: (M) .CO | E104: Exchange Online (Plan 1) | F104: 74569469 | G104: juan.carhuajulca@grupoconectar.co | I104: =VLOOKUP(F104,'PLANTA PERU'!A:AL,2,0) -> CARHUAJULCA LEVANO JUAN GABRIEL | J104: =VLOOKUP(F104,'PLANTA PERU'!A:AL,10,0) -> TECNICO ESPECIALISTA TDP | K104: IGUL | L104: =VLOOKUP(F104,'PLANTA PERU'!A:AD,7,0) -> 0 | M104: NA | N104: =VLOOKUP(F104,'PLANTA PERU'!A:AD,12,0) -> TERMINO FIJO | O104: HNFM | P104: HUAWEI PERU | Q104: NA | R104: NA | S104: NA | T104: TELECOMUNICACIONES SAC | U104: NA | V104: NA
A105: 45408 | B105: LIMA | C105: 4.53 | D105: (M) .CO | E105: Exchange Online (Plan 1) | F105: 74622710 | G105: juan.roque@grupoconectar.co | I105: =VLOOKUP(F105,'PLANTA PERU'!A:AL,2,0) -> ROQUE ARREDONDO JUAN ALBERTO | J105: =VLOOKUP(F105,'PLANTA PERU'!A:AL,10,0) -> TECNICO JUNIOR TDP | K105: IGUL | L105: =VLOOKUP(F105,'PLANTA PERU'!A:AD,7,0) -> 0 | M105: NA | N105: =VLOOKUP(F105,'PLANTA PERU'!A:AD,12,0) -> TERMINO FIJO | O105: HNFM | P105: HUAWEI PERU | Q105: NA | R105: NA | S105: NA | T105: TELECOMUNICACIONES SAC | U105: NA | V105: NA
A106: 45408 | B106: LIMA | C106: 4.53 | D106: (M) .CO | E106: Exchange Online (Plan 1) | F106: 9448420 | G106: walter.castro@grupoconectar.co | I106: =VLOOKUP(F106,'PLANTA PERU'!A:AL,2,0) -> CASTRO SALAZAR WALTER ORLANDO | J106: =VLOOKUP(F106,'PLANTA PERU'!A:AL,10,0) -> TECNICO ESPECIALISTA TDP | K106: IGUL | L106: =VLOOKUP(F106,'PLANTA PERU'!A:AD,7,0) -> 0 | M106: NA | N106: =VLOOKUP(F106,'PLANTA PERU'!A:AD,12,0) -> TERMINO FIJO | O106: HNFM | P106: HUAWEI PERU | Q106: NA | R106: NA | S106: NA | T106: TELECOMUNICACIONES SAC | U106: NA | V106: NA
A107: 45408 | B107: LIMA | C107: 4.53 | D107: (M) .CO | E107: Exchange Online (Plan 1) | F107: 4927978 | G107: adonis.charmelo@grupoconectar.co | I107: =VLOOKUP(F107,'PLANTA PERU'!A:AL,2,0) -> CHARMELO HERNANDEZ ADONIS ALDAIR | J107: =VLOOKUP(F107,'PLANTA PERU'!A:AL,10,0) -> TECNICO JUNIOR | K107: IGUL | L107: =VLOOKUP(F107,'PLANTA PERU'!A:AD,7,0) -> 0 | M107: NA | N107: =VLOOKUP(F107,'PLANTA PERU'!A:AD,12,0) -> TERMINO FIJO | O107: HNFM | P107: HUAWEI PERU | Q107: NA | R107: NA | S107: NA | T107: TELECOMUNICACIONES SAC | U107: NA | V107: NA
A108: 45408 | B108: LIMA | C108: 4.53 | D108: (M) .CO | E108: Exchange Online (Plan 1) | F108: 7562873 | G108: david.pereira@grupoconectar.co | I108: =VLOOKUP(F108,'PLANTA PERU'!A:AL,2,0) -> PEREIRA GARCIA DAVID CRISTOBAL JOSE | J108: =VLOOKUP(F108,'PLANTA PERU'!A:AL,10,0) -> TECNICO JUNIOR | K108: IGUL | L108: =VLOOKUP(F108,'PLANTA PERU'!A:AD,7,0) -> 0 | M108: NA | N108: =VLOOKUP(F108,'PLANTA PERU'!A:AD,12,0) -> TERMINO FIJO | O108: HNFM | P108: HUAWEI PERU | Q108: NA | R108: NA | S108: NA | T108: TELECOMUNICACIONES SAC | U108: NA | V108: NA
A109: 45428 | B109: LIMA | C109: 12.6 | D109: (M) .CO | E109: Microsoft 365 Empresa Estándar | F109: 71115880 | G109: erick.pena@grupoconectar.co | H109: CESADO | I109: =VLOOKUP(F109,'PLANTA PERU'!A:AL,2,0) -> PE?A ASENCIO ERICK | J109: =VLOOKUP(F109,'PLANTA PERU'!A:AL,10,0) -> ASISTENTE TI | K109: IGUL | L109: =VLOOKUP(F109,'PLANTA PERU'!A:AD,7,0) -> 0 | M109: NA | N109: =VLOOKUP(F109,'PLANTA PERU'!A:AD,12,0) -> 0 | O109: MSIM | P109: CLARO PERU | Q109: NA | R109: NA | S109: NA | T109: TELECOMUNICACIONES SAC | U109: NA | V109: NA
A110: 45447 | B110: LIMA | C110: 6.3 | D110: (M) .CO | E110: Microsoft 365 Empresa Básico | F110: 4733123 | G110: xiorelys.jimenez@grupoconectar.co | I110: =VLOOKUP(F110,'PLANTA PERU'!A:AL,2,0) -> JIMENEZ RODRIGUEZ XIORELYS NATHALY | J110: =VLOOKUP(F110,'PLANTA PERU'!A:AL,10,0) -> ANALISTA DE COMPRAS | K110: IGUL | L110: =VLOOKUP(F110,'PLANTA PERU'!A:AD,7,0) -> 0 | M110: NA | N110: =VLOOKUP(F110,'PLANTA PERU'!A:AD,12,0) -> TERMINO FIJO | O110: MSIM | P110: CLARO PERU | Q110: NA | R110: NA | S110: NA | T110: TELECOMUNICACIONES SAC | U110: NA | V110: NA
A111: 45750 | B111: LIMA | C111: 4.53 | D111: (M) .CO | E111: Exchange Online (Plan 1) | F111: 71860709 | G111: harry.cuenca@grupoconectar.co | I111: =VLOOKUP(F111,'PLANTA PERU'!A:AL,2,0) -> CUENCA SANCHEZ HARRY JHAN POOL | J111: =VLOOKUP(F111,'PLANTA PERU'!A:AL,10,0) -> TECNICO ESPECIALISTA TDP | K111: IGUL | L111: =VLOOKUP(F111,'PLANTA PERU'!A:AD,7,0) -> 0 | M111: NA | N111: =VLOOKUP(F111,'PLANTA PERU'!A:AD,12,0) -> TERMINO FIJO | O111: MSIM | P111: CLARO PERU | Q111: NA | R111: NA | S111: NA | T111: TELECOMUNICACIONES SAC | U111: NA | V111: NA
A112: 46199 | B112: LIMA | C112: 6.3 | D112: (M) .CO | E112: Microsoft 365 Empresa Básico | F112: 48067632 | G112: evelyn.torres@grupoconectar.co | I112: =VLOOKUP(F112,'PLANTA PERU'!A:AL,2,0) -> TORRES ROJAS EVELYN MILAGROS | J112: =VLOOKUP(F112,'PLANTA PERU'!A:AL,10,0) -> ANALISTA DE RECLUTAMIENTO | K112: IGUL | L112: =VLOOKUP(F112,'PLANTA PERU'!A:AD,7,0) -> 0 | M112: NA | N112: =VLOOKUP(F112,'PLANTA PERU'!A:AD,12,0) -> 0 | O112: MSIM | P112: CLARO PERU | Q112: NA | R112: NA | S112: NA | T112: TELECOMUNICACIONES SAC | U112: NA | V112: NA
A113: 46204 | B113: LIMA | C113: 0.1 | D113: .NET | E113: CPANEL | F113: 42037296 | G113: jguizado@grupoconectar.net | I113: =VLOOKUP(F113,'PLANTA PERU'!A:AL,2,0) -> GUIZADO SOSA JOHN ROGER | J113: =VLOOKUP(F113,'PLANTA PERU'!A:AL,10,0) -> TECNICO ESPECIALISTA | K113: IGUL | L113: =VLOOKUP(F113,'PLANTA PERU'!A:AD,7,0) -> 0 | M113: NA | N113: =VLOOKUP(F113,'PLANTA PERU'!A:AD,12,0) -> 0 | O113: MSIM | P113: CLARO PERU | Q113: NA | R113: NA | S113: NA | T113: TELECOMUNICACIONES SAC | U113: NA | V113: NA
A114: 46204 | B114: LIMA | C114: 0.1 | D114: .NET | E114: CPANEL | F114: 45577771 | G114: jabastidas@grupoconectar.net | I114: =VLOOKUP(F114,'PLANTA PERU'!A:AL,2,0) -> BASTIDAS PAREJA JEREMY ABRAHAM | J114: =VLOOKUP(F114,'PLANTA PERU'!A:AL,10,0) -> TECNICO ESPECIALISTA | K114: IGUL | L114: =VLOOKUP(F114,'PLANTA PERU'!A:AD,7,0) -> 0 | M114: NA | N114: =VLOOKUP(F114,'PLANTA PERU'!A:AD,12,0) -> 0 | O114: MSIM | P114: CLARO PERU | Q114: NA | R114: NA | S114: NA | T114: TELECOMUNICACIONES SAC | U114: NA | V114: NA
A115: 46204 | B115: LIMA | C115: 0.1 | D115: .NET | E115: CPANEL | F115: 10150480 | G115: hlazo@grupoconectar.net | I115: =VLOOKUP(F115,'PLANTA PERU'!A:AL,2,0) -> LAZO GALVAN HECTOR LUIS | J115: =VLOOKUP(F115,'PLANTA PERU'!A:AL,10,0) -> TECNICO ESPECIALISTA | K115: IGUL | L115: =VLOOKUP(F115,'PLANTA PERU'!A:AD,7,0) -> 0 | M115: NA | N115: =VLOOKUP(F115,'PLANTA PERU'!A:AD,12,0) -> 0 | O115: MSIM | P115: CLARO PERU | Q115: NA | R115: NA | S115: NA | T115: TELECOMUNICACIONES SAC | U115: NA | V115: NA
A116: 46204 | B116: LIMA | C116: 0.1 | D116: .NET | E116: CPANEL | F116: 8819288 | G116: vpareja@grupoconectar.net | I116: =VLOOKUP(F116,'PLANTA PERU'!A:AL,2,0) -> PAREJA ALMANZA VICTOR | J116: =VLOOKUP(F116,'PLANTA PERU'!A:AL,10,0) -> TECNICO ESPECIALISTA | K116: IGUL | L116: =VLOOKUP(F116,'PLANTA PERU'!A:AD,7,0) -> 0 | M116: NA | N116: =VLOOKUP(F116,'PLANTA PERU'!A:AD,12,0) -> 0 | O116: MSIM | P116: CLARO PERU | Q116: NA | R116: NA | S116: NA | T116: TELECOMUNICACIONES SAC | U116: NA | V116: NA
A117: 46204 | B117: LIMA | C117: 0.1 | D117: .NET | E117: CPANEL | F117: 77378383 | G117: jbaldeon@grupoconectar.net | I117: =VLOOKUP(F117,'PLANTA PERU'!A:AL,2,0) -> BALDEON PALACIOS JOSE LUIS | J117: =VLOOKUP(F117,'PLANTA PERU'!A:AL,10,0) -> TECNICO JUNIOR | K117: IGUL | L117: =VLOOKUP(F117,'PLANTA PERU'!A:AD,7,0) -> 0 | M117: NA | N117: =VLOOKUP(F117,'PLANTA PERU'!A:AD,12,0) -> 0 | O117: MSIM | P117: CLARO PERU | Q117: NA | R117: NA | S117: NA | T117: TELECOMUNICACIONES SAC | U117: NA | V117: NA
A118: 46204 | B118: LIMA | C118: 0.1 | D118: .NET | E118: CPANEL | F118: 10150480 | G118: rdios@grupoconectar.net | I118: =VLOOKUP(F118,'PLANTA PERU'!A:AL,2,0) -> LAZO GALVAN HECTOR LUIS | J118: =VLOOKUP(F118,'PLANTA PERU'!A:AL,10,0) -> TECNICO ESPECIALISTA | K118: IGUL | L118: =VLOOKUP(F118,'PLANTA PERU'!A:AD,7,0) -> 0 | M118: NA | N118: =VLOOKUP(F118,'PLANTA PERU'!A:AD,12,0) -> 0 | O118: MSIM | P118: CLARO PERU | Q118: NA | R118: NA | S118: NA | T118: TELECOMUNICACIONES SAC | U118: NA | V118: NA
A119: 46204 | B119: LIMA | C119: 0.1 | D119: .NET | E119: CPANEL | F119: 74946090 | G119: jltorres@grupoconectar.net | I119: =VLOOKUP(F119,'PLANTA PERU'!A:AL,2,0) -> TORRES LEON JOSE LUIS | J119: =VLOOKUP(F119,'PLANTA PERU'!A:AL,10,0) -> TECNICO ESPECIALISTA JUNIOR | K119: IGUL | L119: =VLOOKUP(F119,'PLANTA PERU'!A:AD,7,0) -> 0 | M119: NA | N119: =VLOOKUP(F119,'PLANTA PERU'!A:AD,12,0) -> 0 | O119: MSIM | P119: CLARO PERU | Q119: NA | R119: NA | S119: NA | T119: TELECOMUNICACIONES SAC | U119: NA | V119: NA
A120: 46204 | B120: LIMA | C120: 0.1 | D120: .NET | E120: CPANEL | F120: 46880394 | G120: dnlopez@grupoconectar.net | I120: =VLOOKUP(F120,'PLANTA PERU'!A:AL,2,0) -> LOPEZ CARRION DAVID NELSON | J120: =VLOOKUP(F120,'PLANTA PERU'!A:AL,10,0) -> TECNICO ESPECIALISTA | K120: IGUL | L120: =VLOOKUP(F120,'PLANTA PERU'!A:AD,7,0) -> 0 | M120: NA | N120: =VLOOKUP(F120,'PLANTA PERU'!A:AD,12,0) -> 0 | O120: MSIM | P120: CLARO PERU | Q120: NA | R120: NA | S120: NA | T120: TELECOMUNICACIONES SAC | U120: NA | V120: NA
A121: 46204 | B121: LIMA | C121: 0.1 | D121: .NET | E121: CPANEL | F121: 74366523 | G121: oquispe@grupoconectar.net | I121: =VLOOKUP(F121,'PLANTA PERU'!A:AL,2,0) -> QUISPE RAMOS OMAR LUIS | J121: =VLOOKUP(F121,'PLANTA PERU'!A:AL,10,0) -> TECNICO ESPECIALISTA | K121: IGUL | L121: =VLOOKUP(F121,'PLANTA PERU'!A:AD,7,0) -> 0 | M121: NA | N121: =VLOOKUP(F121,'PLANTA PERU'!A:AD,12,0) -> 0 | O121: MSIM | P121: CLARO PERU | Q121: NA | R121: NA | S121: NA | T121: TELECOMUNICACIONES SAC | U121: NA | V121: NA
... A131: 46209 | B131: LIMA | C131: 0.1 | D131: .NET | E131: CPANEL | F131: 71001753 | G131: vimunoz@grupoconectar.net | I131: =VLOOKUP(F131,'PLANTA PERU'!A:AL,2,0) -> MU?OZ MARTINEZ VICTOR HAROL | J131: =VLOOKUP(F131,'PLANTA PERU'!A:AL,10,0) -> TECNICO ESPECIALISTA | K131: IGUL | L131: =VLOOKUP(F131,'PLANTA PERU'!A:AD,7,0) -> 0 | M131: NA | N131: =VLOOKUP(F131,'PLANTA PERU'!A:AD,12,0) -> 0 | O131: MSIM | P131: CLARO PERU | Q131: NA | R131: NA | S131: NA | T131: TELECOMUNICACIONES SAC | U131: NA | V131: NA
A132: 46209 | B132: LIMA | C132: 0.1 | D132: .NET | E132: CPANEL | F132: 41530220 | G132: hchavez@grupoconectar.net | H132: CHAVEZ CHAVEZ HENRY LEANDRO | I132: =VLOOKUP(F132,'PLANTA PERU'!A:AL,2,0) -> CHAVEZ CHAVEZ HENRY LEANDRO | J132: =VLOOKUP(F132,'PLANTA PERU'!A:AL,10,0) -> TECNICO ESPECIALISTA | K132: IGUL | L132: =VLOOKUP(F132,'PLANTA PERU'!A:AD,7,0) -> 0 | M132: NA | N132: =VLOOKUP(F132,'PLANTA PERU'!A:AD,12,0) -> 0 | O132: MSIM | P132: CLARO PERU | Q132: NA | R132: NA | S132: NA | T132: TELECOMUNICACIONES SAC | U132: NA | V132: NA
A133: 46209 | B133: LIMA | C133: 0.1 | D133: .NET | E133: CPANEL | F133: 10074429 | G133: mallcca@grupoconectar.net | I133: =VLOOKUP(F133,'PLANTA PERU'!A:AL,2,0) -> ALLCCA CARRASCO MARCO ANTONIO | J133: =VLOOKUP(F133,'PLANTA PERU'!A:AL,10,0) -> TECNICO ESPECIALISTA BASICO | K133: IGUL | L133: =VLOOKUP(F133,'PLANTA PERU'!A:AD,7,0) -> 0 | M133: NA | N133: =VLOOKUP(F133,'PLANTA PERU'!A:AD,12,0) -> INDEFINIDO | O133: MSIM | P133: CLARO PERU | Q133: NA | R133: NA | S133: NA | T133: TELECOMUNICACIONES SAC | U133: NA | V133: NA
A134: 46209 | B134: LIMA | C134: 0.1 | D134: .NET | E134: CPANEL | F134: 46821377 | G134: jhuarca@grupoconectar.net | I134: =VLOOKUP(F134,'PLANTA PERU'!A:AL,2,0) -> HUARCA HUILLCA JHOEL FELIPE | J134: =VLOOKUP(F134,'PLANTA PERU'!A:AL,10,0) -> TECNICO ESPECIALISTA JUNIOR | K134: IGUL | L134: =VLOOKUP(F134,'PLANTA PERU'!A:AD,7,0) -> 0 | M134: NA | N134: =VLOOKUP(F134,'PLANTA PERU'!A:AD,12,0) -> TERMINO FIJO | O134: MSIM | P134: CLARO PERU | Q134: NA | R134: NA | S134: NA | T134: TELECOMUNICACIONES SAC | U134: NA | V134: NA
A135: 46209 | B135: LIMA | C135: 0.1 | D135: .NET | E135: CPANEL | F135: 42900632 | G135: hlozano@grupoconectar.net | I135: =VLOOKUP(F135,'PLANTA PERU'!A:AL,2,0) -> LOZANO REYES HECTOR HUGO | J135: =VLOOKUP(F135,'PLANTA PERU'!A:AL,10,0) -> TECNICO ESPECIALISTA SENIOR | K135: IGUL | L135: =VLOOKUP(F135,'PLANTA PERU'!A:AD,7,0) -> 0 | M135: NA | N135: =VLOOKUP(F135,'PLANTA PERU'!A:AD,12,0) -> TERMINO FIJO | O135: MSIM | P135: CLARO PERU | Q135: NA | R135: NA | S135: NA | T135: TELECOMUNICACIONES SAC | U135: NA | V135: NA
A136: 46209 | B136: LIMA | C136: 0.1 | D136: .NET | E136: CPANEL | F136: 47199562 | G136: lriveros@grupoconectar.net | I136: =VLOOKUP(F136,'PLANTA PERU'!A:AL,2,0) -> RIVEROS QUISPE LIONEL NAHUN | J136: =VLOOKUP(F136,'PLANTA PERU'!A:AL,10,0) -> TECNICO ESPECIALISTA | K136: IGUL | L136: =VLOOKUP(F136,'PLANTA PERU'!A:AD,7,0) -> 0 | M136: NA | N136: =VLOOKUP(F136,'PLANTA PERU'!A:AD,12,0) -> TERMINO FIJO | O136: MSIM | P136: CLARO PERU | Q136: NA | R136: NA | S136: NA | T136: TELECOMUNICACIONES SAC | U136: NA | V136: NA
A137: 46209 | B137: LIMA | C137: 0.1 | D137: .NET | E137: CPANEL | F137: 72858783 | G137: cysmodes@grupoconectar.net | I137: =VLOOKUP(F137,'PLANTA PERU'!A:AL,2,0) -> YSMODES SANTILLAN CRISTTOPER HAMILTON | J137: =VLOOKUP(F137,'PLANTA PERU'!A:AL,10,0) -> TECNICO ESPECIALISTA SENIOR | K137: IGUL | L137: =VLOOKUP(F137,'PLANTA PERU'!A:AD,7,0) -> 0 | M137: NA | N137: =VLOOKUP(F137,'PLANTA PERU'!A:AD,12,0) -> TERMINO FIJO | O137: MSIM | P137: CLARO PERU | Q137: NA | R137: NA | S137: NA | T137: TELECOMUNICACIONES SAC | U137: NA | V137: NA
A138: 46209 | B138: LIMA | C138: 0.1 | D138: .NET | E138: CPANEL | F138: 46883679 | G138: lzavala@grupoconectar.net | I138: =VLOOKUP(F138,'PLANTA PERU'!A:AL,2,0) -> ZAVALA LEYTH LUIGGY ALESSANDRO | J138: =VLOOKUP(F138,'PLANTA PERU'!A:AL,10,0) -> TECNICO ESPECIALISTA SENIOR | K138: IGUL | L138: =VLOOKUP(F138,'PLANTA PERU'!A:AD,7,0) -> 0 | M138: NA | N138: =VLOOKUP(F138,'PLANTA PERU'!A:AD,12,0) -> 0 | O138: MSIM | P138: CLARO PERU | Q138: NA | R138: NA | S138: NA | T138: TELECOMUNICACIONES SAC | U138: NA | V138: NA
A139: 46209 | B139: LIMA | C139: 0.1 | D139: .NET | E139: CPANEL | F139: 74199665 | G139: jbellido@grupoconectar.net | I139: =VLOOKUP(F139,'PLANTA PERU'!A:AL,2,0) -> BELLIDO PUCHURI JONATHAN ELIAS | J139: =VLOOKUP(F139,'PLANTA PERU'!A:AL,10,0) -> TECNICO ESPECIALISTA SENIOR | K139: IGUL | L139: =VLOOKUP(F139,'PLANTA PERU'!A:AD,7,0) -> 0 | M139: NA | N139: =VLOOKUP(F139,'PLANTA PERU'!A:AD,12,0) -> TERMINO FIJO | O139: MSIM | P139: CLARO PERU | Q139: NA | R139: NA | S139: NA | T139: TELECOMUNICACIONES SAC | U139: NA | V139: NA
A140: 46209 | B140: LIMA | C140: 0.1 | D140: .NET | E140: CPANEL | F140: 47948650 | G140: econdori@grupoconectar.net | I140: =VLOOKUP(F140,'PLANTA PERU'!A:AL,2,0) -> CONDORI CORDOVA EDUARDO ENRIQUE | J140: =VLOOKUP(F140,'PLANTA PERU'!A:AL,10,0) -> TECNICO ESPECIALISTA JUNIOR | K140: IGUL | L140: =VLOOKUP(F140,'PLANTA PERU'!A:AD,7,0) -> 0 | M140: NA | N140: =VLOOKUP(F140,'PLANTA PERU'!A:AD,12,0) -> TERMINO FIJO | O140: MSIM | P140: CLARO PERU | Q140: NA | R140: NA | S140: NA | T140: TELECOMUNICACIONES SAC | U140: NA | V140: NA
...

Sheet PLANTA PERU
A1: CEDULA | B1: APELLIDOS Y NOMBRES | C1: EMP | D1: INGRESO | E1: VENCE | F1: EST | G1: RETIRO | H1: MOTIVO RETIRO | I1: MOTIVO RETIRO - ESPECIFICADO | J1: CARGO | K1: TIPO CARGO | L1: TIPO CONTRATO | M1: SUBPROCESO | N1: PROCESO | O1: CLIENTE | P1: CARPETA | Q1: PROYECTO | R1: LINEA N | S1: CIUDAD OPE | T1: REGIONAL | U1: AUSENT. GEN | V1: AUSENT. DM | W1: DIAS ACCID | X1: ROTACION | Y1: CC SUPERVISOR | Z1: NOMBRE SUPERVISOR | AA1: OBSERVACIONES | AB1: INGENIERIA | AC1: TOTAL VACACIONES ACUMULADOS | AD1: VACACIONES TOMADOS | AE1: VACACIONES PENDIENTES | AF1: TIPO DE CONTRATO | AG1: REEMBOLSO DE ESSALUD | AH1: SALARIO BASICO | AI1: REGIMEN | AJ1: CLASE CARGO | AK1: NIVEL CARGO | AL1: C.COSTO
A2: 46352583 | B2: ALATA DAVILA MICHAEL ALFREDO | C2: CP | D2: 45702 | E2: 46446 | F2: A | J2: TECNICO JUNIOR | K2: ADMTIVO | L2: INDEFINIDO | M2: TALENTO-GENERAL | N2: TALENTO HUMANO | O2: HUAWEI PERU | P2: FLM | Q2: NUEVOS NEG | R2: MOVIL | S2: LIMA | T2: PERU | U2: 0 | V2: 0 | X2: PLANTA | Y2: 43688420 | Z2: MIRANDA SUAREZ ANTENOR | AA2: ACTIVO TRABAJANDO | AB2: CERTIFICADO EN CLARO | AC2: 202.58333 | AD2: 181 | AE2: 21.583333 | AF2: INDEFINIDO | AH2: 2000 | AI2: GENERAL | AJ2: ADMINISTRATIVO | AK2: SUPERVISORES | AL2: HUAWEI FLM CLARO
A3: 70390056 | B3: ALFARO RODRIGUEZ JEANCARLOS DAVID EDEY | C3: CP | D3: 45306 | E3: 46446 | F3: A | J3: TECNICO ESPECIALISTA | K3: OPE UPC | L3: INDEFINIDO | M3: INGENIERIA-GENERAL | N3: INGENIERIA | O3: HUAWEI PERU | P3: FLM | Q3: NUEVOS NEG | R3: MOVIL | S3: LIMA | T3: PERU | U3: 0 | V3: 0 | X3: PLANTA | Y3: 3017373 | Z3: ROJAS PADILLA CESAR HUMBERTO | AA3: ACTIVO TRABAJANDO | AB3: NO APLICA | AC3: 201.83333 | AD3: 190 | AE3: 11.833333 | AF3: INDEFINIDO | AH3: 1300 | AI3: GENERAL | AJ3: OPERATIVO | AK3: TECNICOS | AL3: HUAWEI FLM TDP
A4: 10074429 | B4: ALLCCA CARRASCO MARCO ANTONIO | C4: CP | D4: 45880 | E4: 46446 | F4: A | J4: TECNICO ESPECIALISTA BASICO | K4: ADM OPE | L4: INDEFINIDO | M4: CONTROLLER-LIQUIDACION | N4: INGENIERIA | O4: HUAWEI PERU | P4: FLM | Q4: NUEVOS NEG | R4: MOVIL | S4: LIMA | T4: PERU | U4: 0 | V4: 0 | X4: PLANTA | Y4: 72810172 | Z4: MUÑOZ PIZARRO WILLIAM MARTIN | AA4: ACTIVO TRABAJANDO | AC4: 201.41667 | AD4: 175 | AE4: 26.416667 | AF4: INDEFINIDO | AH4: 1300 | AI4: GENERAL | AJ4: ADMINISTRATIVO | AK4: ANALISTAS | AL4: HUAWEI FLM TDP
A5: 8050213 | B5: ALONSO GARRIAZO HERNAN | C5: CP | D5: 46054 | E5: 46446 | F5: A | J5: TECNICO RESIDENTE | K5: APOYO UPC | L5: INDEFINIDO | M5: INGENIERIA-GENERAL | N5: INGENIERIA | O5: WIN OPERACIONES | P5: OYM | Q5: SOLU FIJAS | R5: MASIVAS | S5: LIMA | T5: PERU | U5: 0 | V5: 0 | X5: PLANTA | Y5: 4718074 | Z5: PORRAS TIBATA CARLOS MAURICIO | AA5: ACTIVO TRABAJANDO | AC5: 191.67123 | AD5: 160 | AE5: 31.671233 | AF5: INDEFINIDO | AH5: 2200 | AI5: GENERAL | AJ5: ADMINISTRATIVO | AK5: COORDINADORES | AL5: WIN OPERACIONES
A6: 40946309 | B6: ALVARADO VARGAS JOSE MANUEL | C6: CP | D6: 46054 | E6: 46446 | F6: A | J6: TECNICO RESIDENTE | K6: PER APOYO | L6: INDEFINIDO | M6: ABASTECIMIENTO-MATERIALES | N6: ABASTECIMIENTO | O6: HUAWEI PERU | P6: FLM | Q6: NUEVOS NEG | R6: MOVIL | S6: LIMA | T6: PERU | U6: 0 | V6: 0 | X6: PLANTA | Y6: 72566559 | Z6: SOTO CASTILLO JOSE ALEJANDRO | AA6: ACTIVO TRABAJANDO | AB6: CERTIFICADO EN CLARO | AC6: 188.71233 | AD6: 168 | AE6: 20.712329 | AF6: INDEFINIDO | AH6: 2000 | AI6: GENERAL | AJ6: CARGO UPC | AK6: SUPERVISORES | AL6: HUAWEI FLM TDP
A7: 71267193 | B7: ALVIS ABISRROR ANDERSON | C7: CP | D7: 46008 | E7: 46446 | F7: A | J7: TECNICO JUNIOR MOTORIZADO TDP | K7: ADM OPE | L7: INDEFINIDO | M7: INGENIERIA-GENERAL | N7: INGENIERIA | O7: WIN OPERACIONES | P7: OYM | Q7: SOLU FIJAS | R7: MASIVAS | S7: LIMA | T7: PERU | U7: 31 | V7: 31 | X7: PLANTA | Y7: 72810172 | Z7: MUÑOZ PIZARRO WILLIAM MARTIN | AA7: ACTIVO TRABAJANDO | AC7: 164.91667 | AD7: 120 | AE7: 44.916667 | AF7: TERMINO FIJO | AH7: 1300 | AI7: GENERAL | AJ7: ADMINISTRATIVO | AK7: SUPERVISORES | AL7: WIN OPERACIONES
A8: 41887361 | B8: ANAMPA GUTIERREZ IVAN WALDO | C8: CP | D8: 45497 | E8: 46446 | F8: A | J8: TECNICO JUNIOR | K8: ADMTIVO | L8: TERMINO FIJO | M8: CONTROLLER-LIQUIDACION | N8: INGENIERIA | O8: HUAWEI PERU | P8: FLM | Q8: NUEVOS NEG | R8: MOVIL | S8: LIMA | T8: PERU | U8: 0 | V8: 0 | X8: PLANTA | Y8: 72810172 | Z8: MUÑOZ PIZARRO WILLIAM MARTIN | AA8: ACTIVO TRABAJANDO | AC8: 89.236301 | AD8: 64 | AE8: 25.236301 | AF8: TERMINO FIJO | AH8: 1300 | AI8: GENERAL | AJ8: ADMINISTRATIVO | AK8: ANALISTAS | AL8: HUAWEI FLM LONG HAUL
A9: 70845087 | B9: ANGULO RAMOS RONALDO ESTHEFANO | C9: CP | D9: 45813 | E9: 46446 | F9: A | J9: AUXILIAR DE LIQUIDACION | K9: ADM UPC | L9: TERMINO FIJO | M9: ADMIN-GENERAL | N9: ADMINISTRACION | O9: MULTICLIENTE | P9: TRANSVERSAL | Q9: TRANSVERSAL | R9: INTEGRAL | S9: LIMA | T9: PERU | U9: 0 | V9: 0 | X9: PLANTA | Y9: 4718074 | Z9: PORRAS TIBATA CARLOS MAURICIO | AA9: ACTIVO TRABAJANDO | AB9: NO APLICA | AC9: 88.041667 | AD9: 47 | AE9: 41.041667 | AF9: TERMINO FIJO | AH9: 4000 | AI9: GENERAL | AJ9: ADMINISTRATIVO | AK9: JEFES | AL9: TRANSVERSAL
A10: 43096607 | B10: AQUINO BRAVO RONALD DIRSEO | C10: CP | D10: 45826 | E10: 46446 | F10: A | J10: SUPERVISOR MBB | K10: OPE UPC | L10: TERMINO FIJO | M10: TALENTO-SSTA | N10: SSTA | O10: HUAWEI PERU | P10: FLM | Q10: NUEVOS NEG | R10: MOVIL | S10: LIMA | T10: PERU | U10: 0 | V10: 0 | X10: PLANTA | Y10: 4718074 | Z10: PORRAS TIBATA CARLOS MAURICIO | AA10: ACTIVO TRABAJANDO | AB10: NO APLICA | AC10: 83.833333 | AD10: 52 | AE10: 31.833333 | AF10: TERMINO FIJO | AH10: 3500 | AI10: GENERAL | AJ10: CARGO UPC | AK10: COORDINADORES | AL10: HUAWEI FLM TDP
A11: 76007265 | B11: ARANDA URBANO CESAR JORDHI | C11: CP | D11: 46090 | E11: 46173 | F11: A | J11: TECNICO ESPECIALISTA | K11: OPE UPC | L11: TERMINO FIJO | M11: INGENIERIA-GENERAL | N11: INGENIERIA | O11: HUAWEI PERU | P11: FLM | Q11: NUEVOS NEG | R11: MOVIL | S11: LIMA | T11: PERU | U11: 11 | V11: 11 | X11: PLANTA | Y11: 10551431 | Z11: ESPINOZA BUSTAMANTE LUIS ABELARDO | AA11: ACTIVO TRABAJANDO | AB11: NO APLICA | AC11: 72 | AD11: 33 | AE11: 39 | AF11: TERMINO FIJO | AH11: 2200 | AI11: GENERAL | AJ11: OPERATIVO | AK11: TECNICOS | AL11: HUAWEI FLM CLARO
A12: 74588571 | B12: AROSEMENA DIAZ MATTHYUS AARON | C12: CP | D12: 46122 | E12: 46356 | F12: A | J12: TECNICO JUNIOR TDP | K12: ADMTIVO | L12: TERMINO FIJO | M12: INGENIERIA-GENERAL | N12: INGENIERIA | O12: HUAWEI PERU | P12: FLM | Q12: NUEVOS NEG | R12: MOVIL | S12: LIMA | T12: PERU | U12: 0 | V12: 0 | X12: PLANTA | Y12: 10551431 | Z12: ESPINOZA BUSTAMANTE LUIS ABELARDO | AA12: ACTIVO TRABAJANDO | AB12: NO APLICA | AC12: 71.416667 | AD12: 68 | AE12: 3.4166667 | AF12: TERMINO FIJO | AH12: 2400 | AI12: GENERAL | AJ12: OPERATIVO | AK12: TECNICOS | AL12: HUAWEI FLM CLARO
A13: 10642561 | B13: AVALOS ALARCON CRISTHIAN DANGELO | C13: CP | D13: 45922 | E13: 46356 | F13: A | J13: TECNICO ESPECIALISTA | K13: OPE UPC | L13: TERMINO FIJO | M13: INGENIERIA-GENERAL | N13: INGENIERIA | O13: HUAWEI PERU | P13: FLM | Q13: NUEVOS NEG | R13: MOVIL | S13: LIMA | T13: PERU | U13: 0 | V13: 0 | X13: PLANTA | Y13: 10551431 | Z13: ESPINOZA BUSTAMANTE LUIS ABELARDO | AA13: ACTIVO TRABAJANDO | AB13: NO APLICA | AC13: 71.416667 | AD13: 22 | AE13: 49.416667 | AF13: TERMINO FIJO | AH13: 2000 | AI13: GENERAL | AJ13: OPERATIVO | AK13: TECNICOS | AL13: HUAWEI FLM CLARO
A14: 45990537 | B14: BECERRA SOTO SANDRO JOHAN | C14: CP | D14: 45352 | E14: 46446 | F14: A | J14: TECNICO RESIDENTE TDP | K14: ADM UPC | L14: TERMINO FIJO | M14: INGENIERIA-GENERAL | N14: INGENIERIA | O14: HUAWEI PERU | P14: OLT | Q14: NUEVOS NEG | R14: INTEGRAL | S14: LIMA | T14: PERU | U14: 0 | V14: 0 | X14: PLANTA | Y14: 46151732 | Z14: LOPEZ UCHUYA KATHERINE WENDY | AA14: ACTIVO TRABAJANDO | AB14: NO APLICA | AC14: 71.25 | AD14: 23 | AE14: 48.25 | AF14: TERMINO FIJO | AH14: 1800 | AI14: GENERAL | AJ14: ADMINISTRATIVO | AK14: ANALISTAS | AL14: PROYECTO OLT
A15: 74199665 | B15: BELLIDO PUCHURI JONATHAN ELIAS | C15: CP | D15: 45337 | E15: 46356 | F15: A | J15: TECNICO ESPECIALISTA SENIOR | K15: ADM UPC | L15: TERMINO FIJO | M15: INGENIERIA-GENERAL | N15: INGENIERIA | O15: HUAWEI PERU | P15: FLM | Q15: NUEVOS NEG | R15: MOVIL | S15: LIMA | T15: PERU | U15: 0 | V15: 0 | X15: PLANTA | Y15: 10551431 | Z15: ESPINOZA BUSTAMANTE LUIS ABELARDO | AA15: ACTIVO TRABAJANDO | AB15: NO APLICA | AC15: 71 | AD15: 24 | AE15: 47 | AF15: TERMINO FIJO | AH15: 2500 | AI15: GENERAL | AJ15: OPERATIVO | AK15: TECNICOS | AL15: HUAWEI FLM CLARO
A16: 41444629 | B16: BENITES DIAZ ELVA MARIA DEL SOCOR | C16: CP | D16: 46037 | E16: 46203 | F16: A | J16: CONTADOR GENERAL | K16: ADMTIVO | L16: TERMINO FIJO | M16: CONTROLLER-LIQUIDACION | N16: CONTROLLER | O16: HUAWEI PERU | P16: FLM | Q16: NUEVOS NEG | R16: MOVIL | S16: LIMA | T16: PERU | U16: 1 | V16: 1 | X16: PLANTA | Y16: 46151732 | Z16: LOPEZ UCHUYA KATHERINE WENDY | AA16: ACTIVO TRABAJANDO | AB16: NO APLICA | AC16: 70.416667 | AD16: 41 | AE16: 29.416667 | AF16: TERMINO FIJO | AH16: 3000 | AI16: GENERAL | AJ16: CARGO UPC | AK16: ANALISTAS | AL16: HUAWEI FLM CLARO
A17: 75373817 | B17: BERNAL CANALES LEONIDAS MITCHEL | C17: CP | D17: 45974 | E17: 46446 | F17: A | J17: TECNICO JUNIOR MOTORIZADO TDP | K17: OPE UPC | L17: TERMINO FIJO | M17: TALENTO-SSTA | N17: SSTA | O17: HUAWEI PERU | P17: FLM | Q17: NUEVOS NEG | R17: MOVIL | S17: LIMA | T17: PERU | U17: 0 | V17: 0 | X17: PLANTA | Y17: 9302925 | Z17: MOLINA VILA EDWIN MANUEL | AA17: ACTIVO TRABAJANDO | AB17: NO APLICA | AC17: 67.833333 | AD17: 26 | AE17: 41.833333 | AF17: TERMINO FIJO | AH17: 2000 | AI17: GENERAL | AJ17: CARGO UPC | AK17: ANALISTAS | AL17: HUAWEI FLM CLARO
A18: 76297793 | B18: BERROSPI CHAUPIS IVAN RODRIGO | C18: CP | D18: 46132 | E18: 46446 | F18: A | J18: ANALISTA FINANCIERO | K18: ADM UPC | L18: INDEFINIDO | M18: CONTEL PE-GENERAL | N18: GERENCIA CONTEL PE | O18: MULTICLIENTE | P18: TRANSVERSAL | Q18: TRANSVERSAL | R18: INTEGRAL | S18: LIMA | T18: PERU | U18: 0 | V18: 0 | X18: PLANTA | AA18: ACTIVO TRABAJANDO | AB18: NO APLICA | AC18: 75.083333 | AD18: 17 | AE18: 58.083333 | AF18: INDEFINIDO | AH18: 15943.2 | AI18: GENERAL | AJ18: ADMINISTRATIVO | AK18: GERENTES | AL18: TRANSVERSAL
A19: 42778138 | B19: BOZA PARIONA JORGE LUIS | C19: CP | D19: 45931 | E19: 46265 | F19: A | J19: TECNICO RESIDENTE TDP | K19: OPE UPC | L19: TERMINO FIJO | M19: INGENIERIA-GENERAL | N19: INGENIERIA | O19: HUAWEI PERU | P19: FLM | Q19: NUEVOS NEG | R19: MOVIL | S19: LIMA | T19: PERU | U19: 0 | V19: 0 | X19: PLANTA | Y19: 10551431 | Z19: ESPINOZA BUSTAMANTE LUIS ABELARDO | AA19: ACTIVO TRABAJANDO | AB19: NO APLICA | AC19: 64.664384 | AD19: 15 | AE19: 49.664384 | AF19: TERMINO FIJO | AH19: 1900 | AI19: GENERAL | AJ19: OPERATIVO | AK19: TECNICOS | AL19: HUAWEI FLM LONG HAUL
A20: 42712391 | B20: BRAVO VIVANCO JUAN CARLOS | C20: CP | D20: 46125 | E20: 46265 | F20: A | J20: BACK OFFICE | K20: OPE UPC | L20: TERMINO FIJO | M20: INGENIERIA-GENERAL | N20: INGENIERIA | O20: HUAWEI PERU | P20: FLM | Q20: NUEVOS NEG | R20: MOVIL | S20: LIMA | T20: PERU | U20: 0 | V20: 0 | X20: PLANTA | Y20: 10551431 | Z20: ESPINOZA BUSTAMANTE LUIS ABELARDO | AA20: ACTIVO TRABAJANDO | AB20: NO APLICA | AC20: 64.178082 | AD20: 34 | AE20: 30.178082 | AF20: TERMINO FIJO | AH20: 2200 | AI20: GENERAL | AJ20: OPERATIVO | AK20: TECNICOS | AL20: HUAWEI FLM CLARO
A21: 80524414 | B21: BRIZUELA CORRALES JORGE ARTURO | C21: CP | D21: 45782 | E21: 46265 | F21: A | J21: AUXILIAR SERVICIOS GENERALES | K21: ADM UPC | L21: TERMINO FIJO | M21: ABASTECIMIENTO-MATERIALES | N21: ABASTECIMIENTO | O21: HUAWEI PERU | P21: OYM | Q21: NUEVOS NEG | R21: MOVIL | S21: LIMA | T21: PERU | U21: 0 | V21: 0 | X21: PLANTA | Y21: 41444629 | Z21: BENITES DIAZ ELVA MARIA DEL SOCORRO | AA21: ACTIVO TRABAJANDO | AB21: NO APLICA | AC21: 63.244863 | AD21: 15 | AE21: 48.244863 | AF21: TERMINO FIJO | AH21: 2200 | AI21: GENERAL | AJ21: CARGO UPC | AK21: ANALISTAS | AL21: HUAWEI FLM CLARO
A22: 71452551 | B22: CABREJOS MONTENEGRO CESAR ABEL | C22: CP | D22: 45352 | E22: 46356 | F22: A | J22: TECNICO RESIDENTE TDP | K22: OPE UPC | L22: TERMINO FIJO | M22: INGENIERIA-GENERAL | N22: INGENIERIA | O22: HUAWEI PERU | P22: FLM | Q22: NUEVOS NEG | R22: MOVIL | S22: LIMA | T22: PERU | U22: 0 | V22: 0 | X22: PLANTA | Y22: 3017373 | Z22: ROJAS PADILLA CESAR HUMBERTO | AA22: ACTIVO TRABAJANDO | AB22: NO APLICA | AC22: 35.21347 | AD22: 43 | AE22: -7.7865297 | AF22: TERMINO FIJO | AH22: 2000 | AI22: GENERAL | AJ22: OPERATIVO | AK22: TECNICOS | AL22: HUAWEI FLM TDP
A23: 40597379 | B23: CABRERA TAPIA EDGAR | C23: CP | D23: 45352 | E23: 46265 | F23: A | J23: TECNICO RESIDENTE TDP | K23: OPE UPC | L23: TERMINO FIJO | M23: INGENIERIA-GENERAL | N23: INGENIERIA | O23: HUAWEI PERU | P23: FLM | Q23: NUEVOS NEG | R23: MOVIL | S23: LIMA | T23: PERU | U23: 0 | V23: 0 | X23: PLANTA | Y23: 43096607 | Z23: AQUINO BRAVO RONALD DIRSEO | AA23: ACTIVO TRABAJANDO | AB23: NO APLICA | AC23: 35.21347 | AD23: 22 | AE23: 13.21347 | AF23: TERMINO FIJO | AH23: 2000 | AI23: GENERAL | AJ23: OPERATIVO | AK23: TECNICOS | AL23: HUAWEI FLM TDP
A24: 71279121 | B24: CAMPOS PE?A JAIME MANUEL | C24: CP | D24: 46017 | E24: 46446 | F24: A | J24: TECNICO JUNIOR | K24: OPE UPC | L24: TERMINO FIJO | M24: CONTROLLER-LIQUIDACION | N24: CONTROLLER | O24: HUAWEI PERU | P24: MBB | Q24: NUEVOS NEG | R24: MOVIL | S24: LIMA | T24: PERU | U24: 2 | V24: 2 | X24: PLANTA | Y24: 46151732 | Z24: LOPEZ UCHUYA KATHERINE WENDY | AA24: ACTIVO TRABAJANDO | AC24: 62.718037 | AD24: 22 | AE24: 40.718037 | AF24: TERMINO FIJO | AH24: 2000 | AI24: GENERAL | AJ24: CARGO UPC | AK24: ANALISTAS | AL24: HUAWEI MBB
A25: 74569469 | B25: CARHUAJULCA LEVANO JUAN GABRIEL | C25: CP | D25: 45384 | E25: 46265 | F25: A | J25: TECNICO ESPECIALISTA TDP | K25: OPE UPC | L25: TERMINO FIJO | M25: INGENIERIA-GENERAL | N25: INGENIERIA | O25: HUAWEI PERU | P25: FLM | Q25: NUEVOS NEG | R25: MOVIL | S25: LIMA | T25: PERU | U25: 11 | V25: 10 | X25: PLANTA | Y25: 3017373 | Z25: ROJAS PADILLA CESAR HUMBERTO | AA25: ACTIVO TRABAJANDO | AB25: NO APLICA | AC25: 34.646119 | AD25: 31 | AE25: 3.6461187 | AF25: TERMINO FIJO | AH25: 2000 | AI25: GENERAL | AJ25: OPERATIVO | AK25: TECNICOS | AL25: HUAWEI FLM TDP
A26: 42785003 | B26: CARRASCO VILCA FRANK | C26: CP | D26: 46054 | E26: 46356 | F26: A | J26: INGENIERO RESIDENTE | K26: OPE UPC | L26: TERMINO FIJO | M26: INGENIERIA-GENERAL | N26: INGENIERIA | O26: HUAWEI PERU | P26: FLM | Q26: NUEVOS NEG | R26: MOVIL | S26: LIMA | T26: PERU | U26: 0 | V26: 0 | X26: PLANTA | Y26: 10551431 | Z26: ESPINOZA BUSTAMANTE LUIS ABELARDO | AA26: ACTIVO TRABAJANDO | AB26: NO APLICA | AC26: 62.312785 | AD26: 38 | AE26: 24.312785 | AF26: TERMINO FIJO | AH26: 1700 | AI26: GENERAL | AJ26: OPERATIVO | AK26: TECNICOS | AL26: HUAWEI FLM CLARO
A27: 75415990 | B27: CASTILLO MARCHENA YELSIN DENILSON | C27: CP | D27: 46056 | E27: 46265 | F27: A | J27: TECNICO ESPECIALISTA JUNIOR | K27: OPE UPC | L27: TERMINO FIJO | M27: INGENIERIA-GENERAL | N27: INGENIERIA | O27: HUAWEI PERU | P27: FLM | Q27: NUEVOS NEG | R27: MOVIL | S27: LIMA | T27: PERU | U27: 0 | V27: 0 | X27: PLANTA | AA27: ACTIVO TRABAJANDO | AB27: NO APLICA | AC27: 34.646119 | AD27: 15 | AE27: 19.646119 | AF27: TERMINO FIJO | AH27: 2000 | AI27: GENERAL | AJ27: OPERATIVO | AK27: TECNICOS | AL27: HUAWEI FLM TDP
A28: 43960188 | B28: CASTILLO MARTINEZ PEDRO | C28: CP | D28: 45719 | E28: 46265 | F28: A | J28: TECNICO ESPECIALISTA | K28: OPE UPC | L28: TERMINO FIJO | M28: INGENIERIA-GENERAL | N28: INGENIERIA | O28: HUAWEI PERU | P28: FLM | Q28: NUEVOS NEG | R28: MOVIL | S28: LIMA | T28: PERU | U28: 0 | V28: 0 | X28: PLANTA | AA28: ACTIVO TRABAJANDO | AB28: NO APLICA | AC28: 34.646119 | AD28: 46 | AE28: -11.353881 | AF28: TERMINO FIJO | AH28: 2000 | AI28: GENERAL | AJ28: OPERATIVO | AK28: TECNICOS | AL28: HUAWEI FLM TDP
A29: 47960741 | B29: CASTRO GOMEZ CESAR ENRIQUE | C29: CP | D29: 46054 | E29: 46265 | F29: A | J29: TECNICO RESIDENTE | K29: OPE UPC | L29: TERMINO FIJO | M29: INGENIERIA-GENERAL | N29: INGENIERIA | O29: HUAWEI PERU | P29: FLM | Q29: NUEVOS NEG | R29: MOVIL | S29: LIMA | T29: PERU | U29: 0 | V29: 0 | X29: PLANTA | AA29: ACTIVO TRABAJANDO | AB29: NO APLICA | AC29: 34.646119 | AD29: 30 | AE29: 4.6461187 | AF29: TERMINO FIJO | AH29: 2000 | AI29: GENERAL | AJ29: OPERATIVO | AK29: TECNICOS | AL29: HUAWEI FLM TDP
A30: 9448420 | B30: CASTRO SALAZAR WALTER ORLANDO | C30: CP | D30: 45428 | E30: 46265 | F30: A | J30: TECNICO ESPECIALISTA TDP | K30: OPE UPC | L30: TERMINO FIJO | M30: INGENIERIA-GENERAL | N30: INGENIERIA | O30: HUAWEI PERU | P30: FLM | Q30: NUEVOS NEG | R30: MOVIL | S30: LIMA | T30: PERU | U30: 0 | V30: 0 | X30: PLANTA | AA30: ACTIVO TRABAJANDO | AB30: NO APLICA | AC30: 34.646119 | AD30: 30 | AE30: 4.6461187 | AF30: TERMINO FIJO | AH30: 2000 | AI30: GENERAL | AJ30: OPERATIVO | AK30: TECNICOS | AL30: HUAWEI FLM TDP
A31: 44285911 | B31: CAYCHO PACHECO MARIO MIGUEL | C31: CP | D31: 43875 | E31: 46265 | F31: A | J31: SUPERVISOR LOGISTICO | K31: OPE UPC | L31: TERMINO FIJO | M31: INGENIERIA-GENERAL | N31: INGENIERIA | O31: HUAWEI PERU | P31: FLM | Q31: NUEVOS NEG | R31: MOVIL | S31: LIMA | T31: PERU | U31: 0 | V31: 0 | X31: PLANTA | AA31: ACTIVO TRABAJANDO | AB31: NO APLICA | AC31: 34.646119 | AD31: 20 | AE31: 14.646119 | AF31: TERMINO FIJO | AH31: 2000 | AI31: GENERAL | AJ31: OPERATIVO | AK31: TECNICOS | AL31: HUAWEI FLM TDP
A32: 40658303 | B32: CERRON CAMAYO CARLOS PABLO | C32: CP | D32: 45364 | E32: 46265 | F32: A | J32: TECNICO ESPECIALISTA TDP | K32: OPE UPC | L32: TERMINO FIJO | M32: INGENIERIA-GENERAL | N32: INGENIERIA | O32: HUAWEI PERU | P32: FLM | Q32: NUEVOS NEG | R32: MOVIL | S32: LIMA | T32: PERU | U32: 0 | V32: 0 | X32: PLANTA | AA32: ACTIVO TRABAJANDO | AB32: NO APLICA | AC32: 34.646119 | AD32: 30 | AE32: 4.6461187 | AF32: TERMINO FIJO | AH32: 2000 | AI32: GENERAL | AJ32: OPERATIVO | AK32: TECNICOS | AL32: HUAWEI FLM TDP
A33: 48453046 | B33: CHAMANA YARLEQUE JULIO | C33: CP | D33: 46128 | E33: 46265 | F33: A | J33: TECNICO JUNIOR | K33: OPE UPC | L33: TERMINO FIJO | M33: INGENIERIA-GENERAL | N33: INGENIERIA | O33: HUAWEI PERU | P33: FLM | Q33: NUEVOS NEG | R33: MOVIL | S33: LIMA | T33: PERU | U33: 0 | V33: 0 | X33: PLANTA | AA33: ACTIVO TRABAJANDO | AB33: NO APLICA | AC33: 34.646119 | AD33: 31 | AE33: 3.6461187 | AF33: TERMINO FIJO | AH33: 2000 | AI33: GENERAL | AJ33: OPERATIVO | AK33: TECNICOS | AL33: HUAWEI FLM TDP
A34: 4927978 | B34: CHARMELO HERNANDEZ ADONIS ALDAIR | C34: CP | D34: 45790 | E34: 46265 | F34: A | J34: TECNICO JUNIOR | K34: OPE UPC | L34: TERMINO FIJO | M34: INGENIERIA-GENERAL | N34: INGENIERIA | O34: HUAWEI PERU | P34: FLM | Q34: NUEVOS NEG | R34: MOVIL | S34: LIMA | T34: PERU | U34: 0 | V34: 0 | X34: PLANTA | AA34: ACTIVO TRABAJANDO | AB34: NO APLICA | AC34: 34.646119 | AD34: 30 | AE34: 4.6461187 | AF34: TERMINO FIJO | AH34: 2000 | AI34: GENERAL | AJ34: OPERATIVO | AK34: TECNICOS | AL34: HUAWEI FLM TDP
A35: 41713199 | B35: CHAVEZ AGUEDO MARCO ANTONIO | C35: CP | D35: 46054 | E35: 46265 | F35: A | J35: TECNICO RESIDENTE | K35: OPE UPC | L35: TERMINO FIJO | M35: INGENIERIA-GENERAL | N35: INGENIERIA | O35: HUAWEI PERU | P35: FLM | Q35: NUEVOS NEG | R35: MOVIL | S35: LIMA | T35: PERU | U35: 0 | V35: 0 | X35: PLANTA | AA35: ACTIVO TRABAJANDO | AB35: NO APLICA | AC35: 34.646119 | AD35: 30 | AE35: 4.6461187 | AF35: TERMINO FIJO | AH35: 2000 | AI35: GENERAL | AJ35: OPERATIVO | AK35: TECNICOS | AL35: HUAWEI FLM TDP
A36: 76661104 | B36: CHAVEZ DELGADO SERGIO ARMANDO | C36: CP | D36: 45843 | E36: 46265 | F36: A | J36: TECNICO JUNIOR | K36: OPE UPC | L36: TERMINO FIJO | M36: INGENIERIA-GENERAL | N36: INGENIERIA | O36: HUAWEI PERU | P36: FLM | Q36: NUEVOS NEG | R36: MOVIL | S36: LIMA | T36: PERU | U36: 0 | V36: 0 | X36: PLANTA | AA36: ACTIVO TRABAJANDO | AB36: NO APLICA | AC36: 34.646119 | AD36: 16 | AE36: 18.646119 | AF36: TERMINO FIJO | AH36: 2700 | AI36: GENERAL | AJ36: OPERATIVO | AK36: TECNICOS | AL36: HUAWEI FLM TDP
A37: 46002701 | B37: CHAVEZ MONTENEGRO JEAN PIERRE | C37: CP | D37: 46087 | E37: 46265 | F37: A | J37: TECNICO 1 | K37: OPE UPC | L37: TERMINO FIJO | M37: INGENIERIA-GENERAL | N37: INGENIERIA | O37: HUAWEI PERU | P37: FLM | Q37: NUEVOS NEG | R37: MOVIL | S37: LIMA | T37: PERU | U37: 0 | V37: 0 | X37: PLANTA | AA37: ACTIVO TRABAJANDO | AB37: NO APLICA | AC37: 34.646119 | AD37: 38 | AE37: -3.3538813 | AF37: TERMINO FIJO | AH37: 2000 | AI37: GENERAL | AJ37: OPERATIVO | AK37: TECNICOS | AL37: HUAWEI FLM TDP
A38: 71490074 | B38: CHAVEZ PALOMINO ELIOT MARTIN | C38: CP | D38: 45141 | E38: 46265 | F38: A | J38: ANALISTA ADMINISTRATIVO | K38: OPE UPC | L38: TERMINO FIJO | M38: INGENIERIA-GENERAL | N38: INGENIERIA | O38: HUAWEI PERU | P38: FLM | Q38: NUEVOS NEG | R38: MOVIL | S38: LIMA | T38: PERU | U38: 0 | V38: 0 | X38: PLANTA | AA38: ACTIVO TRABAJANDO | AB38: NO APLICA | AC38: 34.646119 | AD38: 42 | AE38: -7.3538813 | AF38: TERMINO FIJO | AH38: 2000 | AI38: GENERAL | AJ38: OPERATIVO | AK38: TECNICOS | AL38: HUAWEI FLM TDP
... A40: 9598278 | B40: CHIRINOS SEVILLA LUIS ERNESTO | C40: CP | D40: 46113 | E40: 46265 | F40: A | J40: TECNICO RESIDENTE TDP | K40: OPE UPC | L40: TERMINO FIJO | M40: INGENIERIA-GENERAL | N40: INGENIERIA | O40: HUAWEI PERU | P40: FLM | Q40: NUEVOS NEG | R40: MOVIL | S40: LIMA | T40: PERU | U40: 0 | V40: 0 | X40: PLANTA | AA40: ACTIVO TRABAJANDO | AB40: NO APLICA | AC40: 34.569635 | AD40: 30 | AE40: 4.5696347 | AF40: TERMINO FIJO | AH40: 2000 | AI40: GENERAL | AJ40: OPERATIVO | AK40: TECNICOS | AL40: HUAWEI FLM TDP
A41: 47991206 | B41: CHUIMA SAU?E JOSE LUIS | C41: CP | D41: 46113 | E41: 46356 | F41: A | J41: BACK OFFICE | K41: ADMTIVO | L41: TERMINO FIJO | M41: INGENIERIA-GENERAL | N41: INGENIERIA | O41: HUAWEI PERU | P41: FLM | Q41: NUEVOS NEG | R41: MOVIL | S41: LIMA | T41: PERU | U41: 0 | V41: 0 | X41: PLANTA | Y41: 4718074 | Z41: PORRAS TIBATA CARLOS MAURICIO | AA41: ACTIVO TRABAJANDO | AB41: NO APLICA | AC41: 62.195776 | AD41: 40 | AE41: 22.195776 | AF41: TERMINO FIJO | AH41: 3000 | AI41: GENERAL | AJ41: CARGO UPC | AK41: COORDINADORES | AL41: HUAWEI FLM CLARO
A42: 76339673 | B42: CHUMPITAZ VILLARRUBIA JAIME ERIK | C42: CP | D42: 46097 | E42: 46356 | F42: A | J42: ASISTENTE CONTABLE | K42: OPE UPC | L42: TERMINO FIJO | M42: INGENIERIA-GENERAL | N42: INGENIERIA | O42: HUAWEI PERU | P42: FLM | Q42: NUEVOS NEG | R42: MOVIL | S42: LIMA | T42: PERU | U42: 0 | V42: 0 | X42: PLANTA | Y42: 3017373 | Z42: ROJAS PADILLA CESAR HUMBERTO | AA42: ACTIVO TRABAJANDO | AB42: NO APLICA | AC42: 34.326484 | AD42: 34 | AE42: 0.32648402 | AF42: TERMINO FIJO | AH42: 2200 | AI42: GENERAL | AJ42: OPERATIVO | AK42: TECNICOS | AL42: HUAWEI FLM TDP
A43: 74579283 | B43: CHURATA ZU?IGA CESAR CINDERZ | C43: CP | D43: 45427 | E43: 46356 | F43: A | J43: TECNICO JUNIOR | K43: OPE UPC | L43: TERMINO FIJO | M43: INGENIERIA-GENERAL | N43: INGENIERIA | O43: HUAWEI PERU | P43: FLM | Q43: NUEVOS NEG | R43: MOVIL | S43: LIMA | T43: PERU | U43: 0 | V43: 0 | X43: PLANTA | Y43: 3017373 | Z43: ROJAS PADILLA CESAR HUMBERTO | AA43: ACTIVO TRABAJANDO | AB43: NO APLICA | AC43: 34.123858 | AD43: 41 | AE43: -6.8761416 | AF43: TERMINO FIJO | AH43: 2000 | AI43: GENERAL | AJ43: OPERATIVO | AK43: TECNICOS | AL43: HUAWEI FLM TDP
A44: 46944377 | B44: CHURATA ZU?IGA GUBBER EDWIN | C44: CP | D44: 45839 | E44: 46173 | F44: A | J44: TECNICO JUNIOR | K44: OPE UPC | L44: TERMINO FIJO | M44: INGENIERIA-GENERAL | N44: INGENIERIA | O44: HUAWEI PERU | P44: FLM | Q44: NUEVOS NEG | R44: MOVIL | S44: LIMA | T44: PERU | U44: 0 | V44: 0 | X44: PLANTA | Y44: 3017373 | Z44: ROJAS PADILLA CESAR HUMBERTO | AA44: ACTIVO TRABAJANDO | AB44: NO APLICA | AC44: 34.123858 | AD44: 35 | AE44: -0.87614155 | AF44: TERMINO FIJO | AH44: 1400 | AI44: GENERAL | AJ44: OPERATIVO | AK44: TECNICOS | AL44: HUAWEI FLM TDP
A45: 47948650 | B45: CONDORI CORDOVA EDUARDO ENRIQUE | C45: CP | D45: 46056 | E45: 46356 | F45: A | J45: TECNICO ESPECIALISTA JUNIOR | K45: OPE UPC | L45: TERMINO FIJO | M45: INGENIERIA-GENERAL | N45: INGENIERIA | O45: HUAWEI PERU | P45: FLM | Q45: NUEVOS NEG | R45: MOVIL | S45: LIMA | T45: PERU | U45: 0 | V45: 0 | X45: PLANTA | Y45: 10551431 | Z45: ESPINOZA BUSTAMANTE LUIS ABELARDO | AA45: ACTIVO TRABAJANDO | AB45: NO APLICA | AC45: 61.26484 | AD45: 15 | AE45: 46.26484 | AF45: TERMINO FIJO | AH45: 1300 | AI45: GENERAL | AJ45: OPERATIVO | AK45: TECNICOS | AL45: HUAWEI FLM CLARO
A46: 71515058 | B46: CORDOVA BOBADILLA HOOVER ALEXIS | C46: CP | D46: 46055 | E46: 46356 | F46: A | J46: ANALISTA DE COMPRAS | K46: ADMTIVO | L46: TERMINO FIJO | M46: INGENIERIA-GENERAL | N46: INGENIERIA | O46: HUAWEI PERU | P46: FLM | Q46: NUEVOS NEG | R46: MOVIL | S46: LIMA | T46: PERU | U46: 0 | V46: 0 | X46: PLANTA | Y46: 3017373 | Z46: ROJAS PADILLA CESAR HUMBERTO | AA46: ACTIVO TRABAJANDO | AB46: NO APLICA | AC46: 33.474315 | AD46: 30 | AE46: 3.4743151 | AF46: TERMINO FIJO | AH46: 2000 | AI46: GENERAL | AJ46: OPERATIVO | AK46: TECNICOS | AL46: HUAWEI FLM TDP
A47: 75445639 | B47: CRISOLO ROMERO RODRIGO SALAS | C47: CP | D47: 45294 | E47: 46265 | F47: A | J47: TECNICO ESPECIALISTA | K47: ADMTIVO | L47: TERMINO FIJO | M47: TALENTO-GENERAL | N47: TALENTO HUMANO | O47: HUAWEI PERU | P47: FLM | Q47: NUEVOS NEG | R47: MOVIL | S47: LIMA | T47: PERU | U47: 0 | V47: 0 | X47: PLANTA | Y47: 43688420 | Z47: MIRANDA SUAREZ ANTENOR | AA47: ACTIVO TRABAJANDO | AB47: NO APLICA | AC47: 60.897831 | AD47: 31 | AE47: 29.897831 | AF47: TERMINO FIJO | AH47: 2000 | AI47: GENERAL | AJ47: ADMINISTRATIVO | AK47: SUPERVISORES | AL47: HUAWEI FLM LONG HAUL
A48: 71860709 | B48: CUENCA SANCHEZ HARRY JHAN POOL | C48: CP | D48: 46108 | E48: 46234 | F48: A | J48: TECNICO ESPECIALISTA TDP | K48: OPE UPC | L48: TERMINO FIJO | M48: INGENIERIA-GENERAL | N48: INGENIERIA | O48: HUAWEI PERU | P48: FLM | Q48: NUEVOS NEG | R48: MOVIL | S48: LIMA | T48: PERU | U48: 2 | V48: 0 | X48: PLANTA | Y48: 10551431 | Z48: ESPINOZA BUSTAMANTE LUIS ABELARDO | AA48: ACTIVO TRABAJANDO | AB48: NO APLICA | AC48: 59.398402 | AD48: 15 | AE48: 44.398402 | AF48: TERMINO FIJO | AH48: 1400 | AI48: GENERAL | AJ48: OPERATIVO | AK48: TECNICOS | AL48: HUAWEI FLM CLARO
A49: 75224735 | B49: CURRO MENDOZA CESAR ANTONIO | C49: CP | D49: 46094 | E49: 46356 | F49: A | J49: TECNICO ESPECIALISTA | K49: OPE UPC | L49: TERMINO FIJO | M49: INGENIERIA-GENERAL | N49: INGENIERIA | O49: HUAWEI PERU | P49: FLM | Q49: NUEVOS NEG | R49: MOVIL | S49: LIMA | T49: PERU | U49: 0 | V49: 0 | X49: PLANTA | Y49: 3017373 | Z49: ROJAS PADILLA CESAR HUMBERTO | AA49: ACTIVO TRABAJANDO | AB49: NO APLICA | AC49: 61.232877 | AD49: 15 | AE49: 46.232877 | AF49: TERMINO FIJO | AH49: 2000 | AI49: GENERAL | AJ49: OPERATIVO | AK49: TECNICOS | AL49: HUAWEI FLM TDP
A50: 42144495 | B50: DAZA ROBLES MARCO ANTONIO | C50: CP | D50: 45352 | E50: 46203 | F50: A | J50: TECNICO RESIDENTE TDP | K50: ADMTIVO | L50: TERMINO FIJO | M50: INGENIERIA-GENERAL | N50: INGENIERIA | O50: HUAWEI PERU | P50: FLM | Q50: NUEVOS NEG | R50: MOVIL | S50: LIMA | T50: PERU | U50: 0 | V50: 0 | X50: PLANTA | Y50: 3017373 | Z50: ROJAS PADILLA CESAR HUMBERTO | AA50: ACTIVO TRABAJANDO | AB50: NO APLICA | AC50: 60.328767 | AD50: 28 | AE50: 32.328767 | AF50: TERMINO FIJO | AH50: 1300 | AI50: GENERAL | AJ50: OPERATIVO | AK50: TECNICOS | AL50: HUAWEI FLM TDP
A51: 8151583 | B51: DIAZ SILVA CARLO PAUL | C51: CP | D51: 46085 | E51: 46265 | F51: A | J51: TECNICO RESIDENTE TDP | K51: APOYO UPC | L51: TERMINO FIJO | M51: INGENIERIA-GENERAL | N51: INGENIERIA | O51: HUAWEI PERU | P51: FLM | Q51: NUEVOS NEG | R51: MOVIL | S51: LIMA | T51: PERU | U51: 3 | V51: 3 | X51: PLANTA | Y51: 10551431 | Z51: ESPINOZA BUSTAMANTE LUIS ABELARDO | AA51: ACTIVO TRABAJANDO | AB51: NO APLICA | AC51: 58.375 | AD51: 0 | AE51: 58.375 | AF51: TERMINO FIJO | AH51: 1500 | AI51: GENERAL | AJ51: OPERATIVO | AK51: TECNICOS | AL51: HUAWEI FLM CLARO
A52: 71820008 | B52: DURAND URQUIA GUSTAVO DANIEL | C52: CP | D52: 45663 | E52: 46265 | F52: A | J52: TECNICO ESPECIALISTA TDP | K52: OPE UPC | L52: TERMINO FIJO | M52: ADMIN-GENERAL | N52: ADMINISTRACION | O52: MULTICLIENTE | P52: TRANSVERSAL | Q52: TRANSVERSAL | R52: INTEGRAL | S52: LIMA | T52: PERU | U52: 2 | V52: 0 | X52: PLANTA | Y52: 9302925 | Z52: MOLINA VILA EDWIN MANUEL | AA52: ACTIVO TRABAJANDO | AB52: NO APLICA | AC52: 55.833333 | AD52: 54 | AE52: 1.8333333 | AF52: TERMINO FIJO | AH52: 1130 | AI52: GENERAL | AJ52: ADMINISTRATIVO | AK52: SERVICIOS GRALES | AL52: TRANSVERSAL
... A59: 75344954 | B59: FERNANDEZ FACUNDO SANTIAGO DUVERLY | C59: CP | D59: 45352 | E59: 46265 | F59: A | J59: TECNICO ESPECIALISTA JUNIOR | K59: OPE UPC | L59: TERMINO FIJO | M59: INGENIERIA-GENERAL | N59: INGENIERIA | O59: HUAWEI PERU | P59: FLM | Q59: NUEVOS NEG | R59: MOVIL | S59: LIMA | T59: PERU | U59: 0 | V59: 0 | X59: PLANTA | Y59: 3017373 | Z59: ROJAS PADILLA CESAR HUMBERTO | AA59: ACTIVO TRABAJANDO | AB59: NO APLICA | AC59: 41.917808 | AD59: 25 | AE59: 16.917808 | AF59: TERMINO FIJO | AH59: 2000 | AI59: GENERAL | AJ59: OPERATIVO | AK59: TECNICOS | AL59: HUAWEI FLM TDP
A60: 8386220 | B60: FIGINI BERNAL ANTONI | C60: CP | D60: 46054 | E60: 46265 | F60: A | J60: TECNICO RESIDENTE | K60: OPERATIVO | L60: TERMINO FIJO | M60: INGENIERIA-GENERAL | N60: INGENIERIA | O60: HUAWEI PERU | P60: FLM | Q60: NUEVOS NEG | R60: MOVIL | S60: LIMA | T60: PERU | U60: 0 | V60: 0 | X60: PLANTA | AA60: ACTIVO TRABAJANDO | AB60: NO APLICA | AC60: 41.342466 | AD60: 0 | AE60: 41.342466 | AF60: TERMINO FIJO | AH60: 2000 | AI60: GENERAL | AJ60: OPERATIVO | AK60: TECNICOS | AL60: HUAWEI FLM TDP
A61: 7316718 | B61: FLORES CASTILLO RICARDO GREGORIO | C61: CP | D61: 45352 | E61: 46203 | F61: A | J61: TECNICO RESIDENTE TDP | K61: APOYO UPC | L61: TERMINO FIJO | M61: INGENIERIA-GENERAL | N61: INGENIERIA | O61: WIN OPERACIONES | P61: OYM | Q61: SOLU FIJAS | R61: MASIVAS | S61: LIMA | T61: PERU | U61: 31 | V61: 31 | X61: PLANTA | Y61: 72810172 | Z61: MUÑOZ PIZARRO WILLIAM MARTIN | AA61: ACTIVO TRABAJANDO | AC61: 39.369863 | AD61: 0 | AE61: 39.369863 | AF61: TERMINO FIJO | AH61: 1130 | AI61: GENERAL | AJ61: OPERATIVO | AK61: TECNICOS | AL61: WIN OPERACIONES
A62: 70776667 | B62: FLORES VALERIO BRANDON GIAMPOOL | C62: CP | D62: 45054 | E62: 46265 | F62: A | J62: TECNICO ESPECIALISTA BASICO | K62: OPE UPC | L62: TERMINO FIJO | M62: INGENIERIA-GENERAL | N62: INGENIERIA | O62: HUAWEI PERU | P62: FLM | Q62: NUEVOS NEG | R62: MOVIL | S62: LIMA | T62: PERU | U62: 0 | V62: 0 | X62: PLANTA | Y62: 72810172 | Z62: MUÑOZ PIZARRO WILLIAM MARTIN | AA62: ACTIVO TRABAJANDO | AC62: 39.205479 | AD62: 20 | AE62: 19.205479 | AF62: TERMINO FIJO | AH62: 1200 | AI62: GENERAL | AJ62: OPERATIVO | AK62: TECNICOS | AL62: HUAWEI FLM CLARO
A63: 72013772 | B63: FUSTAMANTE TORRES ASAEL | C63: CP | D63: 44168 | E63: 46265 | F63: A | J63: SUPERVISOR DE INSTALACIONES | K63: ADMTIVO | L63: TERMINO FIJO | M63: INGENIERIA-GENERAL | N63: INGENIERIA | O63: HUAWEI PERU | P63: FLM | Q63: NUEVOS NEG | R63: MOVIL | S63: LIMA | T63: PERU | U63: 0 | V63: 0 | X63: PLANTA | AA63: ACTIVO TRABAJANDO | AC63: 39.041096 | AD63: 0 | AE63: 39.041096 | AF63: TERMINO FIJO | AH63: 2000 | AI63: GENERAL | AJ63: OPERATIVO | AK63: TECNICOS | AL63: HUAWEI FLM TDP
A64: 71251762 | B64: GAMARRA BAUTISTA JOSE DANIEL | C64: CP | D64: 46132 | E64: 46203 | F64: A | J64: BACK OFFICE | K64: OPE UPC | L64: TERMINO FIJO | M64: INGENIERIA-GENERAL | N64: INGENIERIA | O64: HUAWEI PERU | P64: FLM | Q64: NUEVOS NEG | R64: MOVIL | S64: LIMA | T64: PERU | U64: 0 | V64: 0 | X64: PLANTA | Y64: 10551431 | Z64: ESPINOZA BUSTAMANTE LUIS ABELARDO | AA64: ACTIVO TRABAJANDO | AC64: 38.630137 | AD64: 0 | AE64: 38.630137 | AF64: TERMINO FIJO | AH64: 1300 | AI64: GENERAL | AJ64: OPERATIVO | AK64: TECNICOS | AL64: HUAWEI FLM CLARO
A65: 9306707 | B65: GAMARRA POMAR VICTOR HUGO WILLIAM | C65: CP | D65: 45352 | E65: 46265 | F65: A | J65: TECNICO RESIDENTE TDP | K65: APOYO UPC | L65: TERMINO FIJO | M65: INGENIERIA-GENERAL | N65: INGENIERIA | O65: HUAWEI PERU | P65: FLM | Q65: NUEVOS NEG | R65: MOVIL | S65: LIMA | T65: PERU | U65: 0 | V65: 0 | X65: PLANTA | Y65: 10551431 | Z65: ESPINOZA BUSTAMANTE LUIS ABELARDO | AA65: ACTIVO TRABAJANDO | AC65: 37.315068 | AD65: 0 | AE65: 37.315068 | AF65: TERMINO FIJO | AH65: 2000 | AI65: GENERAL | AJ65: OPERATIVO | AK65: TECNICOS | AL65: HUAWEI FLM LONG HAUL
A66: 2704980 | B66: GARCIA BLANCO JORGE LUIS | C66: CP | D66: 45759 | E66: 46265 | F66: A | J66: TECNICO ESPECIALISTA TDP | K66: OPE UPC | L66: TERMINO FIJO | M66: INGENIERIA-GENERAL | N66: INGENIERIA | O66: HUAWEI PERU | P66: FLM | Q66: NUEVOS NEG | R66: MOVIL | S66: LIMA | T66: PERU | U66: 0 | V66: 0 | X66: PLANTA | Y66: 10551431 | Z66: ESPINOZA BUSTAMANTE LUIS ABELARDO | AA66: ACTIVO TRABAJANDO | AC66: 37.150685 | AD66: 0 | AE66: 37.150685 | AF66: TERMINO FIJO | AH66: 1300 | AI66: GENERAL | AJ66: OPERATIVO | AK66: TECNICOS | AL66: HUAWEI FLM CLARO
A67: 72533709 | B67: GARCIA MOSCOSO JOSEPH RONALD | C67: CP | D67: 46094 | E67: 46203 | F67: A | J67: BACK OFFICE | K67: OPE UPC | L67: TERMINO FIJO | M67: INGENIERIA-GENERAL | N67: INGENIERIA | O67: HUAWEI PERU | P67: FLM | Q67: NUEVOS NEG | R67: MOVIL | S67: LIMA | T67: PERU | U67: 0 | V67: 0 | X67: PLANTA | Y67: 10551431 | Z67: ESPINOZA BUSTAMANTE LUIS ABELARDO | AA67: ACTIVO TRABAJANDO | AC67: 36.657534 | AD67: 0 | AE67: 36.657534 | AF67: TERMINO FIJO | AH67: 1600 | AI67: GENERAL | AJ67: OPERATIVO | AK67: TECNICOS | AL67: HUAWEI FLM CLARO
A68: 77567760 | B68: GARCIA SALAS JAVIER LUIS | C68: CP | D68: 46085 | E68: 46173 | F68: A | J68: TECNICO 1 | K68: OPE UPC | L68: TERMINO FIJO | M68: ABASTECIMIENTO-MATERIALES | N68: ABASTECIMIENTO | O68: WIN OPERACIONES | P68: OYM | Q68: SOLU FIJAS | R68: MASIVAS | S68: LIMA | T68: PERU | U68: 0 | V68: 0 | X68: PLANTA | Y68: 72566559 | Z68: SOTO CASTILLO JOSE ALEJANDRO | AA68: ACTIVO TRABAJANDO | AC68: 36.082192 | AD68: 23 | AE68: 13.082192 | AF68: TERMINO FIJO | AH68: 1130 | AI68: GENERAL | AJ68: ADMINISTRATIVO | AK68: ALMACENISTAS | AL68: WIN OPERACIONES
A69: 73885080 | B69: GIRON COBA KAREN BRISSETH | C69: CP | D69: 45859 | E69: 46265 | F69: A | J69: ANALISTA LOGISTICO | K69: OPE UPC | L69: TERMINO FIJO | M69: INGENIERIA-GENERAL | N69: INGENIERIA | O69: HUAWEI PERU | P69: FLM | Q69: NUEVOS NEG | R69: MOVIL | S69: LIMA | T69: PERU | U69: 0 | V69: 0 | X69: PLANTA | Y69: 3017373 | Z69: ROJAS PADILLA CESAR HUMBERTO | AA69: ACTIVO TRABAJANDO | AC69: 34.849315 | AD69: 0 | AE69: 34.849315 | AF69: TERMINO FIJO | AH69: 1300 | AI69: GENERAL | AJ69: OPERATIVO | AK69: TECNICOS | AL69: HUAWEI FLM TDP
A70: 75607129 | B70: GUZMAN VI?A ANTONI VICTOR | C70: CP | D70: 45383 | E70: 46265 | F70: A | J70: TECNICO JUNIOR | K70: OPE UPC | L70: TERMINO FIJO | M70: INGENIERIA-GENERAL | N70: INGENIERIA | O70: HUAWEI PERU | P70: OLT | Q70: NUEVOS NEG | R70: MOVIL | S70: LIMA | T70: PERU | U70: 0 | V70: 0 | X70: PLANTA | Y70: 72810172 | Z70: MUÑOZ PIZARRO WILLIAM MARTIN | AA70: ACTIVO TRABAJANDO | AC70: 34.191781 | AD70: 40 | AE70: -5.8082192 | AF70: TERMINO FIJO | AH70: 1200 | AI70: GENERAL | AJ70: OPERATIVO | AK70: TECNICOS | AL70: PROYECTO OLT
A71: 75421266 | B71: HERNANDEZ APARCANA DEREK EITAN | C71: CP | D71: 45538 | E71: 46265 | F71: A | J71: TECNICO JUNIOR MOTORIZADO TDP | K71: OPE UPC | L71: TERMINO FIJO | M71: ADMIN-GENERAL | N71: ADMINISTRACION | O71: HUAWEI PERU | P71: FLM | Q71: NUEVOS NEG | R71: MOVIL | S71: LIMA | T71: PERU | U71: 0 | V71: 0 | X71: PLANTA | Y71: 9302925 | Z71: MOLINA VILA EDWIN MANUEL | AA71: ACTIVO TRABAJANDO | AC71: 32.136986 | AD71: 0 | AE71: 32.136986 | AF71: TERMINO FIJO | AH71: 1300 | AI71: GENERAL | AJ71: CARGO UPC | AK71: AUXILIARES ADM | AL71: HUAWEI FLM TDP
A72: 15449605 | B72: HERNANDEZ MAGALLANES MARTIN HECTOR | C72: CP | D72: 46113 | E72: 46265 | F72: A | J72: BACK OFFICE | K72: OPE UPC | L72: TERMINO FIJO | M72: INGENIERIA-GENERAL | N72: INGENIERIA | O72: HUAWEI PERU | P72: FLM | Q72: NUEVOS NEG | R72: MOVIL | S72: LIMA | T72: PERU | U72: 0 | V72: 0 | X72: PLANTA | Y72: 3017373 | Z72: ROJAS PADILLA CESAR HUMBERTO | AA72: ACTIVO TRABAJANDO | AC72: 31.479452 | AD72: 0 | AE72: 31.479452 | AF72: TERMINO FIJO | AH72: 1300 | AI72: GENERAL | AJ72: OPERATIVO | AK72: TECNICOS | AL72: HUAWEI FLM TDP
A73: 9611762 | B73: HERNANDEZ TORRES JUAN ENRIQUE | C73: CP | D73: 45536 | E73: 46356 | F73: A | J73: TECNICO ESPECIALISTA | K73: OPE UPC | L73: TERMINO FIJO | M73: ADMIN-GENERAL | N73: TALENTO HUMANO | O73: MULTICLIENTE | P73: TRANSVERSAL | Q73: TRANSVERSAL | R73: INTEGRAL | S73: LIMA | T73: PERU | U73: 0 | V73: 0 | X73: PLANTA | Y73: 4718074 | Z73: PORRAS TIBATA CARLOS MAURICIO | AA73: ACTIVO TRABAJANDO | AC73: 29.916667 | AD73: 10 | AE73: 19.916667 | AF73: TERMINO FIJO | AH73: 3000 | AI73: GENERAL | AJ73: ADMINISTRATIVO | AK73: JEFES | AL73: TRANSVERSAL
A74: 76516783 | B74: HERRERA UCHUYA KEVIN STEVEN | C74: CP | D74: 45224 | E74: 46265 | F74: A | J74: ANALISTA SSOMA | K74: OPE UPC | L74: TERMINO FIJO | M74: INGENIERIA-GENERAL | N74: INGENIERIA | O74: HUAWEI PERU | P74: FLM | Q74: NUEVOS NEG | R74: MOVIL | S74: LIMA | T74: PERU | U74: 0 | V74: 0 | X74: PLANTA | Y74: 46151732 | Z74: LOPEZ UCHUYA KATHERINE WENDY | AA74: ACTIVO TRABAJANDO | AB74: NO APLICA | AC74: 29.75 | AD74: 0 | AE74: 29.75 | AF74: TERMINO FIJO | AH74: 1200 | AI74: GENERAL | AJ74: CARGO UPC | AK74: AUXILIARES ADM | AL74: HUAWEI FLM TDP
A75: 60682057 | B75: HINOJOZA MATEO ANTHONY YONY | C75: CP | D75: 45931 | E75: 46265 | F75: A | J75: TECNICO ESPECIALISTA JUNIOR | K75: APOYO UPC | L75: TERMINO FIJO | M75: INGENIERIA-GENERAL | N75: INGENIERIA | O75: HUAWEI PERU | P75: FLM | Q75: NUEVOS NEG | R75: MOVIL | S75: LIMA | T75: PERU | U75: 0 | V75: 0 | X75: PLANTA | AA75: ACTIVO TRABAJANDO | AC75: 28.75 | AD75: 0 | AE75: 28.75 | AF75: TERMINO FIJO | AH75: 2000 | AI75: GENERAL | AJ75: OPERATIVO | AK75: TECNICOS | AL75: HUAWEI FLM TDP
A76: 46156507 | B76: HUAMAN ARENAS ABIGAIL IRENE | C76: CP | D76: 45744 | E76: 46203 | F76: A | J76: ANALISTA CONTABLE | K76: APOYO UPC | L76: TERMINO FIJO | M76: INGENIERIA-GENERAL | N76: INGENIERIA | O76: HUAWEI PERU | P76: MBB | Q76: NUEVOS NEG | R76: MOVIL | S76: LIMA | T76: PERU | U76: 0 | V76: 0 | X76: PLANTA | Y76: 70032235 | Z76: TACUNAN BARAHONA ELIAS ROMAN JUNIOR | AA76: ACTIVO TRABAJANDO | AC76: 28.666667 | AD76: 0 | AE76: 28.666667 | AF76: TERMINO FIJO | AH76: 2500 | AI76: GENERAL | AJ76: CARGO UPC | AK76: SUPERVISORES | AL76: HUAWEI MBB
A77: 70158066 | B77: HUAMAN HUAMAN DANITON | C77: CP | D77: 45139 | E77: 46203 | F77: A | J77: TECNICO ESPECIALISTA | K77: OPE UPC | L77: TERMINO FIJO | M77: INGENIERIA-GENERAL | N77: INGENIERIA | O77: HUAWEI PERU | P77: FLM | Q77: NUEVOS NEG | R77: MOVIL | S77: LIMA | T77: PERU | U77: 0 | V77: 0 | X77: PLANTA | Y77: 10551431 | Z77: ESPINOZA BUSTAMANTE LUIS ABELARDO | AA77: ACTIVO TRABAJANDO | AC77: 28.083333 | AD77: 0 | AE77: 28.083333 | AF77: TERMINO FIJO | AH77: 1300 | AI77: GENERAL | AJ77: OPERATIVO | AK77: TECNICOS | AL77: HUAWEI FLM CLARO
A78: 46084053 | B78: HUAMAN TOCTO ALEXANDER PAUL | C78: CP | D78: 45985 | E78: 46265 | F78: A | J78: TECNICO ESPECIALISTA SENIOR | K78: OPE UPC | L78: TERMINO FIJO | M78: INGENIERIA-GENERAL | N78: INGENIERIA | O78: HUAWEI PERU | P78: FLM | Q78: NUEVOS NEG | R78: MOVIL | S78: LIMA | T78: PERU | U78: 0 | V78: 0 | X78: PLANTA | Y78: 10551431 | Z78: ESPINOZA BUSTAMANTE LUIS ABELARDO | AA78: ACTIVO TRABAJANDO | AC78: 27.583333 | AD78: 7 | AE78: 20.583333 | AF78: TERMINO FIJO | AH78: 1300 | AI78: GENERAL | AJ78: OPERATIVO | AK78: TECNICOS | AL78: HUAWEI FLM CLARO
A79: 46821377 | B79: HUARCA HUILLCA JHOEL FELIPE | C79: CP | D79: 46042 | E79: 46265 | F79: A | J79: TECNICO ESPECIALISTA JUNIOR | K79: OPE UPC | L79: TERMINO FIJO | M79: INGENIERIA-GENERAL | N79: INGENIERIA | O79: HUAWEI PERU | P79: FLM | Q79: NUEVOS NEG | R79: MOVIL | S79: LIMA | T79: PERU | U79: 1 | V79: 0 | X79: PLANTA | Y79: 10551431 | Z79: ESPINOZA BUSTAMANTE LUIS ABELARDO | AA79: ACTIVO TRABAJANDO | AC79: 27.583333 | AD79: 0 | AE79: 27.583333 | AF79: TERMINO FIJO | AH79: 1300 | AI79: GENERAL | AJ79: OPERATIVO | AK79: TECNICOS | AL79: HUAWEI FLM CLARO
A80: 76523092 | B80: HUARCAYA HUAMAN ANTONY | C80: CP | D80: 45839 | E80: 46203 | F80: A | J80: TECNICO JUNIOR | K80: OPE UPC | L80: TERMINO FIJO | M80: INGENIERIA-GENERAL | N80: INGENIERIA | O80: HUAWEI PERU | P80: FLM | Q80: NUEVOS NEG | R80: MOVIL | S80: LIMA | T80: PERU | U80: 1 | V80: 1 | X80: PLANTA | Y80: 10551431 | Z80: ESPINOZA BUSTAMANTE LUIS ABELARDO | AA80: ACTIVO TRABAJANDO | AC80: 27.583333 | AD80: 0 | AE80: 27.583333 | AF80: TERMINO FIJO | AH80: 1300 | AI80: GENERAL | AJ80: OPERATIVO | AK80: TECNICOS | AL80: HUAWEI FLM CLARO
A81: 42372173 | B81: HUARCAYA PILLACA MARIBETZ | C81: CP | D81: 43723 | E81: 46173 | F81: A | J81: ANALISTA DE VALORIZACION | K81: APOYO UPC | L81: TERMINO FIJO | M81: INGENIERIA-GENERAL | N81: INGENIERIA | O81: HUAWEI PERU | P81: FLM | Q81: NUEVOS NEG | R81: MOVIL | S81: LIMA | T81: PERU | U81: 0 | V81: 0 | X81: PLANTA | Y81: 10551431 | Z81: ESPINOZA BUSTAMANTE LUIS ABELARDO | AA81: ACTIVO TRABAJANDO | AC81: 27.583333 | AD81: 0 | AE81: 27.583333 | AF81: TERMINO FIJO | AH81: 2000 | AI81: GENERAL | AJ81: OPERATIVO | AK81: TECNICOS | AL81: HUAWEI FLM CLARO
A82: 10604373 | B82: JAIMES ENRIQUEZ MANUEL DAVID | C82: CP | D82: 45352 | E82: 46265 | F82: A | J82: TECNICO RESIDENTE TDP | K82: OPE UPC | L82: TERMINO FIJO | M82: INGENIERIA-GENERAL | N82: INGENIERIA | O82: HUAWEI PERU | P82: FLM | Q82: NUEVOS NEG | R82: MOVIL | S82: LIMA | T82: PERU | U82: 0 | V82: 0 | X82: PLANTA | Y82: 10551431 | Z82: ESPINOZA BUSTAMANTE LUIS ABELARDO | AA82: ACTIVO TRABAJANDO | AC82: 27.583333 | AD82: 0 | AE82: 27.583333 | AF82: TERMINO FIJO | AH82: 1300 | AI82: GENERAL | AJ82: OPERATIVO | AK82: TECNICOS | AL82: HUAWEI FLM CLARO
A83: 31936274 | B83: JAIMES ENRRIQUEZ GENNER ALFONSO | C83: CP | D83: 45352 | E83: 46265 | F83: A | J83: TECNICO RESIDENTE TDP | K83: OPE UPC | L83: TERMINO FIJO | M83: INGENIERIA-GENERAL | N83: INGENIERIA | O83: HUAWEI PERU | P83: FLM | Q83: NUEVOS NEG | R83: MOVIL | S83: LIMA | T83: PERU | U83: 0 | V83: 0 | X83: PLANTA | Y83: 10551431 | Z83: ESPINOZA BUSTAMANTE LUIS ABELARDO | AA83: ACTIVO TRABAJANDO | AC83: 27.583333 | AD83: 0 | AE83: 27.583333 | AF83: TERMINO FIJO | AH83: 2000 | AI83: GENERAL | AJ83: OPERATIVO | AK83: TECNICOS | AL83: HUAWEI FLM CLARO
A84: 77666191 | B84: JANAMPA REYMUNDO JEFERSON FRANCO | C84: CP | D84: 45839 | E84: 46203 | F84: A | J84: TECNICO JUNIOR | K84: OPE UPC | L84: TERMINO FIJO | M84: INGENIERIA-GENERAL | N84: INGENIERIA | O84: HUAWEI PERU | P84: FLM | Q84: NUEVOS NEG | R84: MOVIL | S84: LIMA | T84: PERU | U84: 0 | V84: 0 | X84: PLANTA | Y84: 10551431 | Z84: ESPINOZA BUSTAMANTE LUIS ABELARDO | AA84: ACTIVO TRABAJANDO | AC84: 27.583333 | AD84: 0 | AE84: 27.583333 | AF84: TERMINO FIJO | AH84: 1300 | AI84: GENERAL | AJ84: OPERATIVO | AK84: TECNICOS | AL84: HUAWEI FLM CLARO
A85: 76285576 | B85: JIMENEZ CARRASCO PERCY | C85: CP | D85: 46042 | E85: 46265 | F85: A | J85: TECNICO ESPECIALISTA SENIOR | K85: OPE UPC | L85: TERMINO FIJO | M85: INGENIERIA-GENERAL | N85: INGENIERIA | O85: HUAWEI PERU | P85: FLM | Q85: NUEVOS NEG | R85: MOVIL | S85: LIMA | T85: PERU | U85: 0 | V85: 0 | X85: PLANTA | Y85: 10551431 | Z85: ESPINOZA BUSTAMANTE LUIS ABELARDO | AA85: ACTIVO TRABAJANDO | AC85: 27.583333 | AD85: 0 | AE85: 27.583333 | AF85: TERMINO FIJO | AH85: 2000 | AI85: GENERAL | AJ85: OPERATIVO | AK85: TECNICOS | AL85: HUAWEI FLM CLARO
A86: 4733123 | B86: JIMENEZ RODRIGUEZ XIORELYS NATHALY | C86: CP | D86: 45516 | E86: 46203 | F86: A | J86: ANALISTA DE COMPRAS | K86: OPE UPC | L86: TERMINO FIJO | M86: INGENIERIA-GENERAL | N86: INGENIERIA | O86: HUAWEI PERU | P86: FLM | Q86: NUEVOS NEG | R86: MOVIL | S86: LIMA | T86: PERU | U86: 0 | V86: 0 | X86: PLANTA | Y86: 10551431 | Z86: ESPINOZA BUSTAMANTE LUIS ABELARDO | AA86: ACTIVO TRABAJANDO | AC86: 27.5 | AD86: 5 | AE86: 22.5 | AF86: TERMINO FIJO | AH86: 1500 | AI86: GENERAL | AJ86: OPERATIVO | AK86: TECNICOS | AL86: HUAWEI FLM CLARO
A87: 41846774 | B87: JORGE APARICIO PEDRO | C87: CP | D87: 46113 | E87: 46203 | F87: A | J87: BACK OFFICE | K87: OPE UPC | L87: TERMINO FIJO | M87: INGENIERIA-GENERAL | N87: INGENIERIA | O87: HUAWEI PERU | P87: FLM | Q87: NUEVOS NEG | R87: MOVIL | S87: LIMA | T87: PERU | U87: 0 | V87: 0 | X87: PLANTA | Y87: 10551431 | Z87: ESPINOZA BUSTAMANTE LUIS ABELARDO | AA87: ACTIVO TRABAJANDO | AC87: 27.123288 | AD87: 0 | AE87: 27.123288 | AF87: TERMINO FIJO | AH87: 1300 | AI87: GENERAL | AJ87: OPERATIVO | AK87: TECNICOS | AL87: HUAWEI FLM CLARO
A88: 43630508 | B88: LEON SERQUIN ANDREA | C88: CP | D88: 46136 | E88: 46265 | F88: A | J88: ANALISTA DE NOMINAS | K88: OPE UPC | L88: TERMINO FIJO | M88: ABASTECIMIENTO-MATERIALES | N88: ABASTECIMIENTO | O88: HUAWEI PERU | P88: OYM | Q88: NUEVOS NEG | R88: MOVIL | S88: LIMA | T88: PERU | U88: 0 | V88: 0 | X88: PLANTA | Y88: 72566559 | Z88: SOTO CASTILLO JOSE ALEJANDRO | AA88: ACTIVO TRABAJANDO | AC88: 25.916667 | AD88: 5 | AE88: 20.916667 | AF88: TERMINO FIJO | AH88: 1600 | AI88: GENERAL | AJ88: ADMINISTRATIVO | AK88: ANALISTAS | AL88: HUAWEI FLM CLARO
A89: 72169351 | B89: LIMACO VARGAS ERNESTO CARLOS | C89: CP | D89: 46055 | E89: 46265 | F89: A | J89: BACK OFFICE | K89: OPE UPC | L89: TERMINO FIJO | M89: ABASTECIMIENTO-MATERIALES | N89: ABASTECIMIENTO | O89: HUAWEI PERU | P89: OYM | Q89: NUEVOS NEG | R89: MOVIL | S89: LIMA | T89: PERU | U89: 0 | V89: 0 | X89: PLANTA | Y89: 72566559 | Z89: SOTO CASTILLO JOSE ALEJANDRO | AA89: ACTIVO TRABAJANDO | AB89: NO APLICA | AC89: 25.916667 | AD89: 0 | AE89: 25.916667 | AF89: TERMINO FIJO | AH89: 1130 | AI89: GENERAL | AJ89: CARGO UPC | AK89: ALMACENISTAS | AL89: WIN OPERACIONES
A90: 72740881 | B90: LIZARES FIGUEROA PAUL GIANCARLO | C90: CP | D90: 46126 | E90: 46265 | F90: A | J90: BACK OFFICE | K90: OPE UPC | L90: TERMINO FIJO | M90: INGENIERIA-GENERAL | N90: INGENIERIA | O90: HUAWEI PERU | P90: MBB | Q90: NUEVOS NEG | R90: MOVIL | S90: LIMA | T90: PERU | U90: 0 | V90: 0 | X90: PLANTA | Y90: 43096607 | Z90: AQUINO BRAVO RONALD DIRSEO | AA90: ACTIVO TRABAJANDO | AC90: 24.833333 | AD90: 21 | AE90: 3.8333333 | AF90: TERMINO FIJO | AH90: 2200 | AI90: GENERAL | AJ90: OPERATIVO | AK90: TECNICOS | AL90: HUAWEI MBB
A91: 77431568 | B91: LLAMOCCA RAMOS NELSON ALEXANDER | C91: CP | D91: 46135 | E91: 46265 | F91: A | J91: TECNICO JUNIOR | K91: OPE UPC | L91: TERMINO FIJO | M91: INGENIERIA-GENERAL | N91: INGENIERIA | O91: HUAWEI PERU | P91: MBB | Q91: NUEVOS NEG | R91: MOVIL | S91: LIMA | T91: PERU | U91: 0 | V91: 0 | X91: PLANTA | Y91: 43096607 | Z91: AQUINO BRAVO RONALD DIRSEO | AA91: ACTIVO TRABAJANDO | AC91: 24.833333 | AD91: 4 | AE91: 20.833333 | AF91: TERMINO FIJO | AH91: 1800 | AI91: GENERAL | AJ91: OPERATIVO | AK91: TECNICOS | AL91: HUAWEI MBB
A92: 42936413 | B92: LOPEZ PEREZ ANIBAL | C92: CP | D92: 45825 | E92: 46265 | F92: A | J92: TECNICO RESIDENTE TDP | K92: OPE UPC | L92: TERMINO FIJO | M92: INGENIERIA-GENERAL | N92: INGENIERIA | O92: HUAWEI PERU | P92: MBB | Q92: NUEVOS NEG | R92: MOVIL | S92: LIMA | T92: PERU | U92: 0 | V92: 0 | X92: PLANTA | Y92: 43096607 | Z92: AQUINO BRAVO RONALD DIRSEO | AA92: ACTIVO TRABAJANDO | AC92: 24.833333 | AD92: 0 | AE92: 24.833333 | AF92: TERMINO FIJO | AH92: 1500 | AI92: GENERAL | AJ92: OPERATIVO | AK92: TECNICOS | AL92: HUAWEI MBB
A93: 74548107 | B93: LOPEZ PINTADO LUIS FERNANDO | C93: CP | D93: 46055 | E93: 46265 | F93: A | J93: TECNICO AYUDANTE | K93: OPE UPC | L93: TERMINO FIJO | M93: INGENIERIA-GENERAL | N93: INGENIERIA | O93: HUAWEI PERU | P93: FLM | Q93: NUEVOS NEG | R93: MOVIL | S93: LIMA | T93: PERU | U93: 0 | V93: 0 | X93: PLANTA | Y93: 3017373 | Z93: ROJAS PADILLA CESAR HUMBERTO | AA93: ACTIVO TRABAJANDO | AC93: 24.583333 | AD93: 0 | AE93: 24.583333 | AF93: TERMINO FIJO | AH93: 2000 | AI93: GENERAL | AJ93: OPERATIVO | AK93: TECNICOS | AL93: HUAWEI FLM TDP
A94: 46917667 | B94: LOPEZ SERNA ANDERSON JOEL | C94: CP | D94: 45908 | E94: 46203 | F94: A | J94: TECNICO ESPECIALISTA TDP | K94: ADMTIVO | L94: TERMINO FIJO | M94: INGENIERIA-GENERAL | N94: INGENIERIA | O94: HUAWEI PERU | P94: FLM | Q94: NUEVOS NEG | R94: MOVIL | S94: LIMA | T94: PERU | U94: 0 | V94: 0 | X94: PLANTA | Y94: 10551431 | Z94: ESPINOZA BUSTAMANTE LUIS ABELARDO | AA94: ACTIVO TRABAJANDO | AC94: 22.849315 | AD94: 0 | AE94: 22.849315 | AF94: TERMINO FIJO | AH94: 2000 | AI94: GENERAL | AJ94: OPERATIVO | AK94: TECNICOS | AL94: HUAWEI FLM CLARO
A95: 46151732 | B95: LOPEZ UCHUYA KATHERINE WENDY | C95: CP | D95: 44732 | E95: 46265 | F95: A | J95: JEFE DE ADMINISTRACION Y SCS | K95: OPE UPC | L95: TERMINO FIJO | M95: ABASTECIMIENTO-MATERIALES | N95: ABASTECIMIENTO | O95: HUAWEI PERU | P95: MBB | Q95: NUEVOS NEG | R95: MOVIL | S95: LIMA | T95: PERU | U95: 0 | V95: 0 | X95: PLANTA | Y95: 72566559 | Z95: SOTO CASTILLO JOSE ALEJANDRO | AA95: ACTIVO TRABAJANDO | AC95: 22.109589 | AD95: 0 | AE95: 22.109589 | AF95: TERMINO FIJO | AH95: 1130 | AI95: GENERAL | AJ95: CARGO UPC | AK95: ALMACENISTAS | AL95: HUAWEI MBB
A96: 42900632 | B96: LOZANO REYES HECTOR HUGO | C96: CP | D96: 46034 | E96: 46173 | F96: A | J96: TECNICO ESPECIALISTA SENIOR | K96: OPE UPC | L96: TERMINO FIJO | M96: INGENIERIA-GENERAL | N96: INGENIERIA | O96: HUAWEI PERU | P96: FLM | Q96: NUEVOS NEG | R96: MOVIL | S96: LIMA | T96: PERU | U96: 0 | V96: 0 | X96: PLANTA | AA96: RETIRADO | AC96: 21.780822 | AD96: 10 | AE96: 11.780822 | AF96: TERMINO FIJO | AH96: 2000 | AI96: GENERAL | AJ96: OPERATIVO | AK96: TECNICOS | AL96: HUAWEI FLM TDP
A97: 9343166 | B97: LUNA VALDEZ RICARDO BENITO | C97: CP | D97: 45139 | E97: 46203 | F97: A | J97: TECNICO ESPECIALISTA | K97: OPE UPC | L97: TERMINO FIJO | M97: INGENIERIA-GENERAL | N97: INGENIERIA | O97: HUAWEI PERU | P97: FLM | Q97: NUEVOS NEG | R97: MOVIL | S97: LIMA | T97: PERU | U97: 0 | V97: 0 | X97: PLANTA | Y97: 10551431 | Z97: ESPINOZA BUSTAMANTE LUIS ABELARDO | AA97: ACTIVO TRABAJANDO | AC97: 20.630137 | AD97: 0 | AE97: 20.630137 | AF97: TERMINO FIJO | AH97: 2000 | AI97: GENERAL | AJ97: OPERATIVO | AK97: TECNICOS | AL97: HUAWEI FLM CLARO
A98: 43670836 | B98: MANCHEGO RODRIGUEZ CARLOS OSWALDO | C98: CP | D98: 45352 | E98: 46265 | F98: A | J98: TECNICO RESIDENTE TDP | K98: OPE UPC | L98: TERMINO FIJO | M98: INGENIERIA-GENERAL | N98: INGENIERIA | O98: HUAWEI PERU | P98: FLM | Q98: NUEVOS NEG | R98: MOVIL | S98: LIMA | T98: PERU | U98: 0 | V98: 0 | X98: PLANTA | AA98: ACTIVO TRABAJANDO | AC98: 19.890411 | AD98: 0 | AE98: 19.890411 | AF98: TERMINO FIJO | AH98: 2000 | AI98: GENERAL | AJ98: OPERATIVO | AK98: TECNICOS | AL98: HUAWEI FLM TDP
A99: 46721769 | B99: MARTEL CERNA MAICOL JESUS | C99: CP | D99: 45840 | E99: 46265 | F99: A | J99: TECNICO MOTORIZADO | K99: OPE UPC | L99: TERMINO FIJO | M99: INGENIERIA-GENERAL | N99: INGENIERIA | O99: HUAWEI PERU | P99: MBB | Q99: NUEVOS NEG | R99: MOVIL | S99: LIMA | T99: PERU | U99: 1 | V99: 1 | X99: PLANTA | Y99: 43096607 | Z99: AQUINO BRAVO RONALD DIRSEO | AA99: ACTIVO TRABAJANDO | AC99: 19.890411 | AD99: 12 | AE99: 7.890411 | AF99: TERMINO FIJO | AH99: 1800 | AI99: GENERAL | AJ99: OPERATIVO | AK99: TECNICOS | AL99: HUAWEI MBB
A100: 48258909 | B100: MARTINEZ MEDRANO LUZ NATALY | C100: CP | D100: 45161 | E100: 46265 | F100: A | J100: ANALISTA ADMINISTRATIVO SENIOR | K100: OPE UPC | L100: TERMINO FIJO | M100: INGENIERIA-GENERAL | N100: INGENIERIA | O100: HUAWEI PERU | P100: MBB | Q100: NUEVOS NEG | R100: MOVIL | S100: LIMA | T100: PERU | U100: 0 | V100: 0 | X100: PLANTA | Y100: 43096607 | Z100: AQUINO BRAVO RONALD DIRSEO | AA100: ACTIVO TRABAJANDO | AC100: 19.890411 | AD100: 4 | AE100: 15.890411 | AF100: TERMINO FIJO | AH100: 1800 | AI100: GENERAL | AJ100: OPERATIVO | AK100: TECNICOS | AL100: HUAWEI MBB
A101: 72854350 | B101: MARTINEZ POZO CHRISTIAN YORDAN | C101: CP | D101: 45995 | E101: 46265 | F101: A | J101: TECNICO ESPECIALISTA TDP | K101: OPE UPC | L101: TERMINO FIJO | M101: INGENIERIA-GENERAL | N101: INGENIERIA | O101: HUAWEI PERU | P101: FLM | Q101: NUEVOS NEG | R101: MOVIL | S101: LIMA | T101: PERU | U101: 0 | V101: 0 | X101: PLANTA | Y101: 3017373 | Z101: ROJAS PADILLA CESAR HUMBERTO | AA101: ACTIVO TRABAJANDO | AC101: 16.438356 | AD101: 0 | AE101: 16.438356 | AF101: TERMINO FIJO | AH101: 1300 | AI101: GENERAL | AJ101: OPERATIVO | AK101: TECNICOS | AL101: HUAWEI FLM TDP
A102: 41631477 | B102: MEDINA CHUQUISPUMA EDGAR EDUARDO | C102: CP | D102: 45369 | E102: 46265 | F102: A | J102: TECNICO ESPECIALISTA TDP | K102: OPE UPC | L102: TERMINO FIJO | M102: INGENIERIA-GENERAL | N102: INGENIERIA | O102: HUAWEI PERU | P102: FLM | Q102: NUEVOS NEG | R102: MOVIL | S102: LIMA | T102: PERU | U102: 13 | V102: 13 | X102: PLANTA | Y102: 3017373 | Z102: ROJAS PADILLA CESAR HUMBERTO | AA102: ACTIVO TRABAJANDO | AC102: 16.356164 | AD102: 10 | AE102: 6.3561644 | AF102: TERMINO FIJO | AH102: 1500 | AI102: GENERAL | AJ102: OPERATIVO | AK102: TECNICOS | AL102: HUAWEI FLM TDP
A103: 2500840 | B103: MEJIAS MAIZ ERNESTOR ANTONIO | C103: CP | D103: 45670 | E103: 46265 | F103: A | J103: TECNICO RESIDENTE TDP | K103: OPE UPC | L103: TERMINO FIJO | M103: INGENIERIA-GENERAL | N103: INGENIERIA | O103: HUAWEI PERU | P103: MBB | Q103: NUEVOS NEG | R103: MOVIL | S103: LIMA | T103: PERU | U103: 1 | V103: 0 | X103: PLANTA | Y103: 43096607 | Z103: AQUINO BRAVO RONALD DIRSEO | AA103: ACTIVO TRABAJANDO | AC103: 15.452055 | AD103: 0 | AE103: 15.452055 | AF103: TERMINO FIJO | AH103: 2000 | AI103: GENERAL | AJ103: OPERATIVO | AK103: TECNICOS | AL103: HUAWEI MBB
A104: 43417264 | B104: MENDIVIL BALANDRA MAGDELINE FIORELLA | C104: CP | D104: 45341 | E104: 46265 | F104: A | J104: ANALISTA DE LIQUIDACION | K104: OPE UPC | L104: TERMINO FIJO | M104: INGENIERIA-GENERAL | N104: INGENIERIA | O104: HUAWEI PERU | P104: MBB | Q104: NUEVOS NEG | R104: MOVIL | S104: LIMA | T104: PERU | U104: 0 | V104: 0 | X104: PLANTA | Y104: 43096607 | Z104: AQUINO BRAVO RONALD DIRSEO | AA104: ACTIVO TRABAJANDO | AC104: 14.876712 | AD104: 0 | AE104: 14.876712 | AF104: TERMINO FIJO | AH104: 2000 | AI104: GENERAL | AJ104: OPERATIVO | AK104: TECNICOS | AL104: HUAWEI MBB
A105: 43688420 | B105: MIRANDA SUAREZ ANTENOR | C105: CP | D105: 45811 | E105: 46265 | F105: A | J105: JEFE DE RRHH | K105: OPE UPC | L105: TERMINO FIJO | M105: INGENIERIA-GENERAL | N105: INGENIERIA | O105: HUAWEI PERU | P105: FLM | Q105: NUEVOS NEG | R105: MOVIL | S105: LIMA | T105: PERU | U105: 0 | V105: 0 | X105: PLANTA | Y105: 3017373 | Z105: ROJAS PADILLA CESAR HUMBERTO | AA105: ACTIVO TRABAJANDO | AC105: 13.561644 | AD105: 0 | AE105: 13.561644 | AF105: TERMINO FIJO | AH105: 1500 | AI105: GENERAL | AJ105: OPERATIVO | AK105: TECNICOS | AL105: HUAWEI FLM TDP
A106: 9302925 | B106: MOLINA VILA EDWIN MANUEL | C106: CP | D106: 44835 | E106: 46265 | F106: A | J106: COORDINADOR DE SST | K106: OPE UPC | L106: TERMINO FIJO | M106: INGENIERIA-GENERAL | N106: INGENIERIA | O106: HUAWEI PERU | P106: FLM | Q106: NUEVOS NEG | R106: MOVIL | S106: LIMA | T106: PERU | U106: 0 | V106: 0 | X106: PLANTA | Y106: 10551431 | Z106: ESPINOZA BUSTAMANTE LUIS ABELARDO | AA106: ACTIVO TRABAJANDO | AC106: 12.821918 | AD106: 0 | AE106: 12.821918 | AF106: TERMINO FIJO | AH106: 1300 | AI106: GENERAL | AJ106: OPERATIVO | AK106: TECNICOS | AL106: HUAWEI FLM CLARO
A107: 8890271 | B107: MORALES SOTELO IVAN LUIS | C107: CP | D107: 43718 | E107: 46265 | F107: A | J107: SUPERVISOR DE INSTALACIONES | K107: OPE UPC | L107: TERMINO FIJO | M107: INGENIERIA-GENERAL | N107: INGENIERIA | O107: HUAWEI PERU | P107: MBB | Q107: NUEVOS NEG | R107: MOVIL | S107: LIMA | T107: PERU | U107: 0 | V107: 0 | X107: PLANTA | Y107: 43096607 | Z107: AQUINO BRAVO RONALD DIRSEO | AA107: ACTIVO TRABAJANDO | AC107: 11.424658 | AD107: 0 | AE107: 11.424658 | AF107: TERMINO FIJO | AH107: 2000 | AI107: GENERAL | AJ107: OPERATIVO | AK107: TECNICOS | AL107: HUAWEI MBB
...

Sheet NOVEDADES
A1: FECHA_CREACION | B1: CIUDAD LABOR | C1: PRECIO USD | D1: DOMINIO | E1: PLAN | F1: NUM_DOCUMENTO | G1: NOMBRE_USUARIO | H1: OBSERVACIÓN (Solicitante) | I1: APELLIDO NOMBRE | J1: CARGO | K1: CU1 | L1: CU1-PROCESO | M1: CU1-REGIONAL | N1: CU1-CIUDAD | O1: CU3 | P1: CU3-CLIENTE | Q1: CU3-LINEA DE NEGOCIO | R1: CU3-PROYECTO | S1: GRUPO | T1: EMPRESA | U1: PROCESO GEN | V1: % PROYECTO | W1: OBSERVACION | X1: Fecha Modificación
A2: 45630 | B2: BOGOTA | C2: 5.5 | D2: (M) .CO | E2: Microsoft 365 Empresa Básico | F2: 1193218651 | G2: juan.soto@grupoconectar.co | H2: (Yuliana Cardenas) | I2: NA | J2: NA | K2: NA | L2: NA | M2: NA | N2: NA | O2: NA | P2: NA | Q2: NA | R2: NA | S2: NA | T2: NA | U2: NA | V2: NA | W2: Cambio de Asignacion a Angelica Paez | X2: 45967
A3: 45680 | B3: BOGOTA | C3: 11.3 | D3: (M) .CO | E3: Microsoft 365 Empresa Estándar | F3: 1013692183 | G3: santiago.leon@grupoconectar.co | H3: LEON SALAMANCA SANTIAGO FELIPE (ana durán) | I3: NA | J3: NA | K3: NA | L3: NA | M3: NA | N3: NA | O3: NA | P3: NA | Q3: NA | R3: NA | S3: NA | T3: NA | U3: NA | V3: NA | W3: Cambio de Asignacion a Tania Estefany Castro | X3: 45967
A4: 45294 | B4: MEDELLIN | C4: 5.5 | D4: (M) .CO | E4: Microsoft 365 Empresa Básico | F4: 6104831 | G4: rodolfo.tumal@grupoconectar.co | H4: Hernandez Valencia Nelson Andres(Christofer) | I4: TUMAL JURADO RODOLFO | J4: COORDINADOR OPERACION FLM | K4: IGAM | L4: INGENIERIA-GENERAL | M4: REG ANTIO | N4: MEDELLIN | O4: HNAL | P4: HUAWEI | Q4: NUEVOS NEG | R4: FLM ALL IN ONE | S4: CLIENTES | T4: CONECTAR TV | U4: INGENIERIA | V4: OPERATIVO | W4: Cambio de Asignacion a Milton Fabian Pino | X4: 45967
A5: 45296 | B5: BOGOTA | C5: 11.3 | D5: (M) .CO | E5: Microsoft 365 Empresa Estándar | F5: 1000472275 | G5: maria.lozano@grupoconectar.co | H5: Maria Daniela Lozano Garcia(Randy) | I5: LOZANO GARCIA MARIA DANIELA | J5: ANALISTA TALENTO HUMANO | K5: TGCB | L5: TALENTO-GENERAL | M5: REG CENTRO | N5: BOGOTA | O5: ISST | P5: TIGO | Q5: SOLU FIJAS | R5: STRONG | S5: CSC | T5: CONECTAR TV | U5: TALENTO HUMANO | V5: OPERATIVO | W5: Cambio de Asignacion a Danna Valentina Forero Espinosa | X5: 45968
A6: 43931 | B6: BOGOTA | C6: 11.3 | D6: (M) .CO | E6: Microsoft 365 Empresa Estándar | F6: 1005248870 | G6: derly.fandino@grupoconectar.co | I6: FANDINO QUIROGA DERLY YADIANA | J6: ANALISTA RELACIONES LABORALES | K6: TWTN | L6: TALENTO-RELABO | M6: TRANSVERSAL | N6: NACIONAL | O6: TTTR | P6: TRANSV CTV | Q6: TRANSVER | R6: TRANSV UEN | S6: CSC | T6: CONECTAR TV | U6: TALENTO HUMANO | V6: ADMINISTRATIVO | W6: Cambio de Asignacion a Miley Portillo | X6: 45965
A7: 45468 | B7: CALI | C7: 4.53 | D7: (M) .CO | E7: Exchange Online (Plan 1) | F7: 1144107409 | G7: valeria.oliva@grupoconectar.co | H7: R3 (RANDY AGUILAR) | I7: OLIVA SOLARTE VALERIA | J7: BACKOFFICE OPERACION | K7: IGVI | L7: INGENIERIA-GENERAL | M7: REG VALLE | N7: CALI | O7: CSIM | P7: CLARO R3 | Q7: SOLU FIJAS | R7: IMM | S7: CLIENTES | T7: CONECTAR TV | U7: INGENIERIA | V7: PERSONAL APOYO | W7: Cambio a Licencia estándar | X7: 45965
A8: 45343 | B8: IBAGUE | C8: 5.5 | D8: (M) .CO | E8: Microsoft 365 Empresa Básico | F8: 1005815440 | G8: maria.rodriguez@grupoconectar.co | H8: MARIA CAMUA RODRIGUEZ LOZANO (Evelin) | I8: NA | J8: NA | K8: NA | L8: NA | M8: NA | N8: NA | O8: NA | P8: NA | Q8: NA | R8: NA | S8: NA | T8: NA | U8: NA | V8: NA | W8: Cambio de Asignacion a Laura Balaguera | X8: 45968
A9: 45387 | B9: IBAGUE | C9: 11.3 | D9: (M) .CO | E9: Microsoft 365 Empresa Estándar | F9: 93386747 | G9: Ernesto.acosta@grupoconectar.co | H9: Hugo Ernesto Acosta Alvarez (Nicolás Pulgarín CLARO R3) | I9: ACOSTA ALVAREZ HUGO ERNESTO | J9: ANALISTA LOGISTICO | K9: SGVI | L9: DISAN-GENERAL | M9: REG VALLE | N9: CALI | O9: TTTR | P9: TRANSV CTV | Q9: TRANSVER | R9: TRANSV UEN | S9: DISAN | T9: CONECTAR TV | U9: DISAN | V9: OTROS | W9: Cambio de Asignación a María Zuluaga | X9: 45968
A10: 45532 | B10: BOGOTA | C10: 5.5 | D10: (M) .CO | E10: Microsoft 365 Empresa Básico | F10: 79784200 | G10: desarrollo.proyectos@grupoconectar.co | H10: usuario para desarrollo Proyectos | I10: =IFERROR(VLOOKUP($F10,MatrizHDUniclass!$A:$AN,3,0),"NA") -> PENA CLAVIJO LUIS EDUARDO | J10: =IFERROR(VLOOKUP($F10,MatrizHDUniclass!$A:$AN,19,0),"NA") -> GERENTE CONTROLLER | K10: =IFERROR(VLOOKUP($F10,MatrizHDUniclass!$A:$AN,24,0),"NA") -> BGTN | L10: =IFERROR(VLOOKUP($F10,MatrizHDUniclass!$A:$AN,31,0),"NA") -> CONTROLLER-GENERAL | M10: =IFERROR(VLOOKUP($F10,MatrizHDUniclass!$A:$AN,32,0),"NA") -> TRANSVERSAL | N10: =IFERROR(VLOOKUP($F10,MatrizHDUniclass!$A:$AN,33,0),"NA") -> NACIONAL | O10: =IFERROR(VLOOKUP($F10,MatrizHDUniclass!$A:$AN,26,0),"NA") -> LTTR | P10: =IFERROR(VLOOKUP($F10,MatrizHDUniclass!$A:$AN,34,0),"NA") -> CASA MATRIZ | Q10: =IFERROR(VLOOKUP($F10,MatrizHDUniclass!$A:$AN,35,0),"NA") -> TRANSVER | R10: =IFERROR(VLOOKUP($F10,MatrizHDUniclass!$A:$AN,36,0),"NA") -> TRANSV UEN | S10: =IFERROR(VLOOKUP($F10,MatrizHDUniclass!$A:$AN,37,0),"NA") -> CONTROLLER | T10: =IFERROR(VLOOKUP($F10,MatrizHDUniclass!$A:$AN,38,0),"NA") -> INVESTMENT | U10: =IFERROR(VLOOKUP($F10,MatrizHDUniclass!$A:$AN,39,0),"NA") -> CONTROLLER | V10: =IFERROR(VLOOKUP($F10,MatrizHDUniclass!$A:$AN,40,0),"NA") -> ADMINISTRATIVO | W10: Asignación de Licencia a Javier Gaitan | X10: 45972
A11: 44742 | B11: MEDELLIN | C11: 5.5 | D11: (M) .CO | E11: Microsoft 365 Empresa Básico | F11: 1073327029 | G11: cesar.osorio.u@grupoconectar.co | H11: (Crhistofer García) | I11: OSORIO ULLOA CESAR DARIO | J11: COORDINADOR OPERACION FLM | K11: IGAM | L11: INGENIERIA-GENERAL | M11: REG ANTIO | N11: MEDELLIN | O11: HNAL | P11: HUAWEI | Q11: NUEVOS NEG | R11: FLM ALL IN ONE | S11: CLIENTES | T11: CONECTAR TV | U11: INGENIERIA | V11: OPERATIVO | W11: Cambio de Asignación a Wilton Avedaño | X11: 45972
A12: 44008 | B12: MEDELLIN | C12: 5.5 | D12: (M) .CO | E12: Microsoft 365 Empresa Básico | F12: 1152693429 | G12: katerin.ruiz@grupoconectar.co | H12: RUIZ ALVAREZ KATERIN ANDREA | I12: =IFERROR(VLOOKUP($F12,MatrizHDUniclass!$A:$AN,3,0),"NA") -> NA | J12: =IFERROR(VLOOKUP($F12,MatrizHDUniclass!$A:$AN,19,0),"NA") -> NA | K12: =IFERROR(VLOOKUP($F12,MatrizHDUniclass!$A:$AN,24,0),"NA") -> NA | L12: =IFERROR(VLOOKUP($F12,MatrizHDUniclass!$A:$AN,31,0),"NA") -> NA | M12: =IFERROR(VLOOKUP($F12,MatrizHDUniclass!$A:$AN,32,0),"NA") -> NA | N12: =IFERROR(VLOOKUP($F12,MatrizHDUniclass!$A:$AN,33,0),"NA") -> NA | O12: =IFERROR(VLOOKUP($F12,MatrizHDUniclass!$A:$AN,26,0),"NA") -> NA | P12: =IFERROR(VLOOKUP($F12,MatrizHDUniclass!$A:$AN,34,0),"NA") -> NA | Q12: =IFERROR(VLOOKUP($F12,MatrizHDUniclass!$A:$AN,35,0),"NA") -> NA | R12: =IFERROR(VLOOKUP($F12,MatrizHDUniclass!$A:$AN,36,0),"NA") -> NA | S12: =IFERROR(VLOOKUP($F12,MatrizHDUniclass!$A:$AN,37,0),"NA") -> NA | T12: =IFERROR(VLOOKUP($F12,MatrizHDUniclass!$A:$AN,38,0),"NA") -> NA | U12: =IFERROR(VLOOKUP($F12,MatrizHDUniclass!$A:$AN,39,0),"NA") -> NA | V12: =IFERROR(VLOOKUP($F12,MatrizHDUniclass!$A:$AN,40,0),"NA") -> NA | W12: Cambio de Asignación a Cindy Vargas | X12: 45972
A13: 44201 | B13: MEDELLIN | C13: 5.5 | D13: (M) .CO | E13: Microsoft 365 Empresa Básico | F13: 1003069083 | G13: ader.avila@grupoconectar.co | H13: (Juan Guarín) | I13: NA | J13: NA | K13: NA | L13: NA | M13: NA | N13: NA | O13: NA | P13: NA | Q13: NA | R13: NA | S13: NA | T13: NA | U13: NA | V13: NA | W13: Cambio de Asignación a Jose García | X13: 45972
A14: 45241 | B14: CALI | C14: 11.3 | D14: (M) .CO | E14: Microsoft 365 Empresa Estándar | F14: 1144193545 | G14: sebastian.barragan@grupoconectar.co | H14: SEBASTIAN STEVEN BARRAGAN CUERO R3( Eliesid González) | I14: =IFERROR(VLOOKUP($F14,MatrizHDUniclass!$A:$AN,3,0),"NA") -> NA | J14: =IFERROR(VLOOKUP($F14,MatrizHDUniclass!$A:$AN,19,0),"NA") -> NA | K14: =IFERROR(VLOOKUP($F14,MatrizHDUniclass!$A:$AN,24,0),"NA") -> NA | L14: =IFERROR(VLOOKUP($F14,MatrizHDUniclass!$A:$AN,31,0),"NA") -> NA | M14: =IFERROR(VLOOKUP($F14,MatrizHDUniclass!$A:$AN,32,0),"NA") -> NA | N14: =IFERROR(VLOOKUP($F14,MatrizHDUniclass!$A:$AN,33,0),"NA") -> NA | O14: =IFERROR(VLOOKUP($F14,MatrizHDUniclass!$A:$AN,26,0),"NA") -> NA | P14: =IFERROR(VLOOKUP($F14,MatrizHDUniclass!$A:$AN,34,0),"NA") -> NA | Q14: =IFERROR(VLOOKUP($F14,MatrizHDUniclass!$A:$AN,35,0),"NA") -> NA | R14: =IFERROR(VLOOKUP($F14,MatrizHDUniclass!$A:$AN,36,0),"NA") -> NA | S14: =IFERROR(VLOOKUP($F14,MatrizHDUniclass!$A:$AN,37,0),"NA") -> NA | T14: =IFERROR(VLOOKUP($F14,MatrizHDUniclass!$A:$AN,38,0),"NA") -> NA | U14: =IFERROR(VLOOKUP($F14,MatrizHDUniclass!$A:$AN,39,0),"NA") -> NA | V14: =IFERROR(VLOOKUP($F14,MatrizHDUniclass!$A:$AN,40,0),"NA") -> NA | W14: Eliminado con Backup | X14: 45973
A15: 45716 | B15: FLORENCIA | C15: 5.5 | D15: (M) .CO | E15: Microsoft 365 Empresa Básico | F15: 41242450 | G15: maria.medellin@grupoconectar.co | H15: MARIA ANTONIA MEDELLIN FRANCO (Diana Diaz) | I15: =IFERROR(VLOOKUP($F15,MatrizHDUniclass!$A:$AN,3,0),"NA") -> NA | J15: =IFERROR(VLOOKUP($F15,MatrizHDUniclass!$A:$AN,19,0),"NA") -> NA | K15: =IFERROR(VLOOKUP($F15,MatrizHDUniclass!$A:$AN,24,0),"NA") -> NA | L15: =IFERROR(VLOOKUP($F15,MatrizHDUniclass!$A:$AN,31,0),"NA") -> NA | M15: =IFERROR(VLOOKUP($F15,MatrizHDUniclass!$A:$AN,32,0),"NA") -> NA | N15: =IFERROR(VLOOKUP($F15,MatrizHDUniclass!$A:$AN,33,0),"NA") -> NA | O15: =IFERROR(VLOOKUP($F15,MatrizHDUniclass!$A:$AN,26,0),"NA") -> NA | P15: =IFERROR(VLOOKUP($F15,MatrizHDUniclass!$A:$AN,34,0),"NA") -> NA | Q15: =IFERROR(VLOOKUP($F15,MatrizHDUniclass!$A:$AN,35,0),"NA") -> NA | R15: =IFERROR(VLOOKUP($F15,MatrizHDUniclass!$A:$AN,36,0),"NA") -> NA | S15: =IFERROR(VLOOKUP($F15,MatrizHDUniclass!$A:$AN,37,0),"NA") -> NA | T15: =IFERROR(VLOOKUP($F15,MatrizHDUniclass!$A:$AN,38,0),"NA") -> NA | U15: =IFERROR(VLOOKUP($F15,MatrizHDUniclass!$A:$AN,39,0),"NA") -> NA | V15: =IFERROR(VLOOKUP($F15,MatrizHDUniclass!$A:$AN,40,0),"NA") -> NA | W15: Cambio de Asignación a Laura Cruz | X15: 45979
A16: 45596 | B16: BOGOTA | C16: 5.5 | D16: (M) .CO | E16: Microsoft 365 Empresa Básico | F16: 80190584 | G16: harold.cardenas@grupoconectar.co | H16: harol cardenas (Onnet) | I16: NA | J16: NA | K16: NA | L16: NA | M16: NA | N16: NA | O16: NA | P16: NA | Q16: NA | R16: NA | S16: NA | T16: NA | U16: NA | V16: NA | W16: Cambio de Licencia a Microsoft Standard | X16: 45981
A17: 45873 | B17: BOGOTA | C17: 11.3 | D17: (M) .CO | E17: Microsoft 365 Empresa Estándar | F17: 1006822899 | G17: oscar.rocha@grupoconectar.co | H17: Oscar Leonardo Rocha Naveo (Christofer) | I17: =IFERROR(VLOOKUP($F17,MatrizHDUniclass!$A:$AN,3,0),"NA") -> ROCHA NAVEO OSCAR LEONARDO | J17: =IFERROR(VLOOKUP($F17,MatrizHDUniclass!$A:$AN,19,0),"NA") -> ANALISTA ALIADOS | K17: =IFERROR(VLOOKUP($F17,MatrizHDUniclass!$A:$AN,24,0),"NA") -> DLTN | L17: =IFERROR(VLOOKUP($F17,MatrizHDUniclass!$A:$AN,31,0),"NA") -> ADMIN-ALIADOS | M17: =IFERROR(VLOOKUP($F17,MatrizHDUniclass!$A:$AN,32,0),"NA") -> TRANSVERSAL | N17: =IFERROR(VLOOKUP($F17,MatrizHDUniclass!$A:$AN,33,0),"NA") -> NACIONAL | O17: =IFERROR(VLOOKUP($F17,MatrizHDUniclass!$A:$AN,26,0),"NA") -> TTTR | P17: =IFERROR(VLOOKUP($F17,MatrizHDUniclass!$A:$AN,34,0),"NA") -> TRANSV CTV | Q17: =IFERROR(VLOOKUP($F17,MatrizHDUniclass!$A:$AN,35,0),"NA") -> TRANSVER | R17: =IFERROR(VLOOKUP($F17,MatrizHDUniclass!$A:$AN,36,0),"NA") -> TRANSV UEN | S17: =IFERROR(VLOOKUP($F17,MatrizHDUniclass!$A:$AN,37,0),"NA") -> CSC | T17: =IFERROR(VLOOKUP($F17,MatrizHDUniclass!$A:$AN,38,0),"NA") -> CONECTAR TV | U17: =IFERROR(VLOOKUP($F17,MatrizHDUniclass!$A:$AN,39,0),"NA") -> ADMINISTRACION | V17: =IFERROR(VLOOKUP($F17,MatrizHDUniclass!$A:$AN,40,0),"NA") -> ADMINISTRATIVO | W17: Cambio de Licencia a Gestión de Permisos Admon | X17: 45981
A18: 18/06/2025 | B18: BOGOTA | C18: 11.3 | D18: (M) .CO | E18: Microsoft 365 Empresa Estándar | F18: 1013103168 | G18: nicolas.diaz@grupoconectar.co | H18: ERIKA JOHANA CASTELLANOS | I18: =IFERROR(VLOOKUP($F18,MatrizHDUniclass!$A:$AN,3,0),"NA") -> DIAZ DIAZ NICOLAS | J18: =IFERROR(VLOOKUP($F18,MatrizHDUniclass!$A:$AN,19,0),"NA") -> DISEÑADOR OPERACION | K18: =IFERROR(VLOOKUP($F18,MatrizHDUniclass!$A:$AN,24,0),"NA") -> IGCB | L18: =IFERROR(VLOOKUP($F18,MatrizHDUniclass!$A:$AN,31,0),"NA") -> INGENIERIA-GENERAL | M18: =IFERROR(VLOOKUP($F18,MatrizHDUniclass!$A:$AN,32,0),"NA") -> REG CENTRO | N18: =IFERROR(VLOOKUP($F18,MatrizHDUniclass!$A:$AN,33,0),"NA") -> BOGOTA | O18: =IFERROR(VLOOKUP($F18,MatrizHDUniclass!$A:$AN,26,0),"NA") -> BSCL | P18: =IFERROR(VLOOKUP($F18,MatrizHDUniclass!$A:$AN,34,0),"NA") -> ATP | Q18: =IFERROR(VLOOKUP($F18,MatrizHDUniclass!$A:$AN,35,0),"NA") -> SOLU FIJAS | R18: =IFERROR(VLOOKUP($F18,MatrizHDUniclass!$A:$AN,36,0),"NA") -> COLOS | S18: =IFERROR(VLOOKUP($F18,MatrizHDUniclass!$A:$AN,37,0),"NA") -> CLIENTES | T18: =IFERROR(VLOOKUP($F18,MatrizHDUniclass!$A:$AN,38,0),"NA") -> CONECTAR TV | U18: =IFERROR(VLOOKUP($F18,MatrizHDUniclass!$A:$AN,39,0),"NA") -> INGENIERIA | V18: =IFERROR(VLOOKUP($F18,MatrizHDUniclass!$A:$AN,40,0),"NA") -> PERSONAL APOYO | W18: Cambio de Licencia a Gestión de Infraestructura | X18: 45981
A19: 45222 | B19: BOGOTA | C19: 5.5 | D19: (M) .CO | E19: Microsoft 365 Empresa Básico | F19: 1000326505 | G19: nicolas.cubillos@grupoconectar.co | H19: NICOLAS CUBILLOS GUARNIZO(Harol Cardenas) | I19: =IFERROR(VLOOKUP($F19,MatrizHDUniclass!$A:$AN,3,0),"NA") -> NA | J19: =IFERROR(VLOOKUP($F19,MatrizHDUniclass!$A:$AN,19,0),"NA") -> NA | K19: =IFERROR(VLOOKUP($F19,MatrizHDUniclass!$A:$AN,24,0),"NA") -> NA | L19: =IFERROR(VLOOKUP($F19,MatrizHDUniclass!$A:$AN,31,0),"NA") -> NA | M19: =IFERROR(VLOOKUP($F19,MatrizHDUniclass!$A:$AN,32,0),"NA") -> NA | N19: =IFERROR(VLOOKUP($F19,MatrizHDUniclass!$A:$AN,33,0),"NA") -> NA | O19: =IFERROR(VLOOKUP($F19,MatrizHDUniclass!$A:$AN,26,0),"NA") -> NA | P19: =IFERROR(VLOOKUP($F19,MatrizHDUniclass!$A:$AN,34,0),"NA") -> NA | Q19: =IFERROR(VLOOKUP($F19,MatrizHDUniclass!$A:$AN,35,0),"NA") -> NA | R19: =IFERROR(VLOOKUP($F19,MatrizHDUniclass!$A:$AN,36,0),"NA") -> NA | S19: =IFERROR(VLOOKUP($F19,MatrizHDUniclass!$A:$AN,37,0),"NA") -> NA | T19: =IFERROR(VLOOKUP($F19,MatrizHDUniclass!$A:$AN,38,0),"NA") -> NA | U19: =IFERROR(VLOOKUP($F19,MatrizHDUniclass!$A:$AN,39,0),"NA") -> NA | V19: =IFERROR(VLOOKUP($F19,MatrizHDUniclass!$A:$AN,40,0),"NA") -> NA | W19: Cambio de Licencia a Gestión de Diseño | X19: 45981
A20: 45231 | B20: MEDELLIN | C20: 5.5 | D20: (M) .CO | E20: Microsoft 365 Empresa Básico | F20: 1036948710 | G20: camilo.gomez@grupoconectar.co | H20: coordinador fml | I20: =IFERROR(VLOOKUP($F20,MatrizHDUniclass!$A:$AN,3,0),"NA") -> GOMEZ ALCARAZ CAMILO ANDRES | J20: =IFERROR(VLOOKUP($F20,MatrizHDUniclass!$A:$AN,19,0),"NA") -> COORDINADOR OPERACION FLM | K20: =IFERROR(VLOOKUP($F20,MatrizHDUniclass!$A:$AN,24,0),"NA") -> IGAM | L20: =IFERROR(VLOOKUP($F20,MatrizHDUniclass!$A:$AN,31,0),"NA") -> INGENIERIA-GENERAL | M20: =IFERROR(VLOOKUP($F20,MatrizHDUniclass!$A:$AN,32,0),"NA") -> REG ANTIO | N20: =IFERROR(VLOOKUP($F20,MatrizHDUniclass!$A:$AN,33,0),"NA") -> MEDELLIN | O20: =IFERROR(VLOOKUP($F20,MatrizHDUniclass!$A:$AN,26,0),"NA") -> HNAL | P20: =IFERROR(VLOOKUP($F20,MatrizHDUniclass!$A:$AN,34,0),"NA") -> HUAWEI | Q20: =IFERROR(VLOOKUP($F20,MatrizHDUniclass!$A:$AN,35,0),"NA") -> NUEVOS NEG | R20: =IFERROR(VLOOKUP($F20,MatrizHDUniclass!$A:$AN,36,0),"NA") -> FLM ALL IN ONE | S20: =IFERROR(VLOOKUP($F20,MatrizHDUniclass!$A:$AN,37,0),"NA") -> CLIENTES | T20: =IFERROR(VLOOKUP($F20,MatrizHDUniclass!$A:$AN,38,0),"NA") -> CONECTAR TV | U20: =IFERROR(VLOOKUP($F20,MatrizHDUniclass!$A:$AN,39,0),"NA") -> INGENIERIA | V20: =IFERROR(VLOOKUP($F20,MatrizHDUniclass!$A:$AN,40,0),"NA") -> OPERATIVO | W20: Cambio de Licencia a Elton Cortés | X20: 45981
A21: 45041 | B21: MEDELLIN | C21: 5.5 | D21: (M) .CO | E21: Microsoft 365 Empresa Básico | F21: 1001145154 | G21: Auxiliarthtigo@grupoconectar.co | H21: MARÍA CAMILA PALACIO AGUILAR (Randy) | I21: =IFERROR(VLOOKUP($F21,MatrizHDUniclass!$A:$AN,3,0),"NA") -> NA | J21: =IFERROR(VLOOKUP($F21,MatrizHDUniclass!$A:$AN,19,0),"NA") -> NA | K21: =IFERROR(VLOOKUP($F21,MatrizHDUniclass!$A:$AN,24,0),"NA") -> NA | L21: =IFERROR(VLOOKUP($F21,MatrizHDUniclass!$A:$AN,31,0),"NA") -> NA | M21: =IFERROR(VLOOKUP($F21,MatrizHDUniclass!$A:$AN,32,0),"NA") -> NA | N21: =IFERROR(VLOOKUP($F21,MatrizHDUniclass!$A:$AN,33,0),"NA") -> NA | O21: =IFERROR(VLOOKUP($F21,MatrizHDUniclass!$A:$AN,26,0),"NA") -> NA | P21: =IFERROR(VLOOKUP($F21,MatrizHDUniclass!$A:$AN,34,0),"NA") -> NA | Q21: =IFERROR(VLOOKUP($F21,MatrizHDUniclass!$A:$AN,35,0),"NA") -> NA | R21: =IFERROR(VLOOKUP($F21,MatrizHDUniclass!$A:$AN,36,0),"NA") -> NA | S21: =IFERROR(VLOOKUP($F21,MatrizHDUniclass!$A:$AN,37,0),"NA") -> NA | T21: =IFERROR(VLOOKUP($F21,MatrizHDUniclass!$A:$AN,38,0),"NA") -> NA | U21: =IFERROR(VLOOKUP($F21,MatrizHDUniclass!$A:$AN,39,0),"NA") -> NA | V21: =IFERROR(VLOOKUP($F21,MatrizHDUniclass!$A:$AN,40,0),"NA") -> NA | W21: Cambio de Nombre a Camila Palacio | X21: 45982
A22: 44957 | B22: BOGOTA | C22: 11.3 | D22: (M) .CO | E22: Microsoft 365 Empresa Estándar | F22: 1014218476 | G22: liliana.casallas@grupoconectar.co | H22: LILIANA ROCIO CASALLAS MARTÍNEZ (Angélica Rivera) | I22: =IFERROR(VLOOKUP($F22,MatrizHDUniclass!$A:$AN,3,0),"NA") -> NA | J22: =IFERROR(VLOOKUP($F22,MatrizHDUniclass!$A:$AN,19,0),"NA") -> NA | K22: =IFERROR(VLOOKUP($F22,MatrizHDUniclass!$A:$AN,24,0),"NA") -> NA | L22: =IFERROR(VLOOKUP($F22,MatrizHDUniclass!$A:$AN,31,0),"NA") -> NA | M22: =IFERROR(VLOOKUP($F22,MatrizHDUniclass!$A:$AN,32,0),"NA") -> NA | N22: =IFERROR(VLOOKUP($F22,MatrizHDUniclass!$A:$AN,33,0),"NA") -> NA | O22: =IFERROR(VLOOKUP($F22,MatrizHDUniclass!$A:$AN,26,0),"NA") -> NA | P22: =IFERROR(VLOOKUP($F22,MatrizHDUniclass!$A:$AN,34,0),"NA") -> NA | Q22: =IFERROR(VLOOKUP($F22,MatrizHDUniclass!$A:$AN,35,0),"NA") -> NA | R22: =IFERROR(VLOOKUP($F22,MatrizHDUniclass!$A:$AN,36,0),"NA") -> NA | S22: =IFERROR(VLOOKUP($F22,MatrizHDUniclass!$A:$AN,37,0),"NA") -> NA | T22: =IFERROR(VLOOKUP($F22,MatrizHDUniclass!$A:$AN,38,0),"NA") -> NA | U22: =IFERROR(VLOOKUP($F22,MatrizHDUniclass!$A:$AN,39,0),"NA") -> NA | V22: =IFERROR(VLOOKUP($F22,MatrizHDUniclass!$A:$AN,40,0),"NA") -> NA | W22: Cambio de Nombre a Arelis Peña | X22: 45985
A23: 43909 | B23: BOGOTA | C23: 5.5 | D23: (M) .CO | E23: Microsoft 365 Empresa Básico | F23: 80028522 | G23: Leonel.Gonzalez@grupoconectar.co | I23: GONZALEZ GARZON LEONEL FERNANDO | J23: LIDER FORMACION | K23: TFTN | L23: TALENTO-FORMACION | M23: TRANSVERSAL | N23: NACIONAL | O23: TTTR | P23: TRANSV CTV | Q23: TRANSVER | R23: TRANSV UEN | S23: CSC | T23: CONECTAR TV | U23: TALENTO HUMANO | V23: ADMINISTRATIVO | W23: Cambio de Nombre a Jenny Bautista | X23: 45986
A24: 44834 | B24: BOGOTA | C24: 11.3 | D24: (M) .CO | E24: Microsoft 365 Empresa Estándar | F24: 1007556186 | G24: erika.castellanos@grupoconectar.co | H24: ERIKA JOHANNA CASTELLANOS CASTRO | I24: =IFERROR(VLOOKUP($F24,MatrizHDUniclass!$A:$AN,3,0),"NA") -> NA | J24: =IFERROR(VLOOKUP($F24,MatrizHDUniclass!$A:$AN,19,0),"NA") -> NA | K24: =IFERROR(VLOOKUP($F24,MatrizHDUniclass!$A:$AN,24,0),"NA") -> NA | L24: =IFERROR(VLOOKUP($F24,MatrizHDUniclass!$A:$AN,31,0),"NA") -> NA | M24: =IFERROR(VLOOKUP($F24,MatrizHDUniclass!$A:$AN,32,0),"NA") -> NA | N24: =IFERROR(VLOOKUP($F24,MatrizHDUniclass!$A:$AN,33,0),"NA") -> NA | O24: =IFERROR(VLOOKUP($F24,MatrizHDUniclass!$A:$AN,26,0),"NA") -> NA | P24: =IFERROR(VLOOKUP($F24,MatrizHDUniclass!$A:$AN,34,0),"NA") -> NA | Q24: =IFERROR(VLOOKUP($F24,MatrizHDUniclass!$A:$AN,35,0),"NA") -> NA | R24: =IFERROR(VLOOKUP($F24,MatrizHDUniclass!$A:$AN,36,0),"NA") -> NA | S24: =IFERROR(VLOOKUP($F24,MatrizHDUniclass!$A:$AN,37,0),"NA") -> NA | T24: =IFERROR(VLOOKUP($F24,MatrizHDUniclass!$A:$AN,38,0),"NA") -> NA | U24: =IFERROR(VLOOKUP($F24,MatrizHDUniclass!$A:$AN,39,0),"NA") -> NA | V24: =IFERROR(VLOOKUP($F24,MatrizHDUniclass!$A:$AN,40,0),"NA") -> NA | W24: Cambio de Nombre a Liliana Casallas | X24: 45986
A25: 44869 | B25: BOGOTA | C25: 5.5 | D25: (M) .CO | E25: Microsoft 365 Empresa Básico | F25: 80231431 | G25: mesadeayudaOyM@grupoconectar.co | H25: ATP (Álvaro Cruz) Gestión Baja | I25: =IFERROR(VLOOKUP($F25,MatrizHDUniclass!$A:$AN,3,0),"NA") -> NA | J25: =IFERROR(VLOOKUP($F25,MatrizHDUniclass!$A:$AN,19,0),"NA") -> NA | K25: =IFERROR(VLOOKUP($F25,MatrizHDUniclass!$A:$AN,24,0),"NA") -> NA | L25: =IFERROR(VLOOKUP($F25,MatrizHDUniclass!$A:$AN,31,0),"NA") -> NA | M25: =IFERROR(VLOOKUP($F25,MatrizHDUniclass!$A:$AN,32,0),"NA") -> NA | N25: =IFERROR(VLOOKUP($F25,MatrizHDUniclass!$A:$AN,33,0),"NA") -> NA | O25: =IFERROR(VLOOKUP($F25,MatrizHDUniclass!$A:$AN,26,0),"NA") -> NA | P25: =IFERROR(VLOOKUP($F25,MatrizHDUniclass!$A:$AN,34,0),"NA") -> NA | Q25: =IFERROR(VLOOKUP($F25,MatrizHDUniclass!$A:$AN,35,0),"NA") -> NA | R25: =IFERROR(VLOOKUP($F25,MatrizHDUniclass!$A:$AN,36,0),"NA") -> NA | S25: =IFERROR(VLOOKUP($F25,MatrizHDUniclass!$A:$AN,37,0),"NA") -> NA | T25: =IFERROR(VLOOKUP($F25,MatrizHDUniclass!$A:$AN,38,0),"NA") -> NA | U25: =IFERROR(VLOOKUP($F25,MatrizHDUniclass!$A:$AN,39,0),"NA") -> NA | V25: =IFERROR(VLOOKUP($F25,MatrizHDUniclass!$A:$AN,40,0),"NA") -> NA | W25: Cambio de Asignación a Harol Cardenas | X25: 45987
A26: 45552 | B26: BOGOTA | C26: 4.53 | D26: (M) .CO | E26: Exchange Online (Plan 1) | F26: 1007556186 | G26: tecnicos.azteca@grupoconectar.co | H26: TÉCNICOS(LILIANA CASALLAS) | I26: =IFERROR(VLOOKUP($F26,MatrizHDUniclass!$A:$AN,3,0),"NA") -> NA | J26: =IFERROR(VLOOKUP($F26,MatrizHDUniclass!$A:$AN,19,0),"NA") -> NA | K26: =IFERROR(VLOOKUP($F26,MatrizHDUniclass!$A:$AN,24,0),"NA") -> NA | L26: =IFERROR(VLOOKUP($F26,MatrizHDUniclass!$A:$AN,31,0),"NA") -> NA | M26: =IFERROR(VLOOKUP($F26,MatrizHDUniclass!$A:$AN,32,0),"NA") -> NA | N26: =IFERROR(VLOOKUP($F26,MatrizHDUniclass!$A:$AN,33,0),"NA") -> NA | O26: =IFERROR(VLOOKUP($F26,MatrizHDUniclass!$A:$AN,26,0),"NA") -> NA | P26: =IFERROR(VLOOKUP($F26,MatrizHDUniclass!$A:$AN,34,0),"NA") -> NA | Q26: =IFERROR(VLOOKUP($F26,MatrizHDUniclass!$A:$AN,35,0),"NA") -> NA | R26: =IFERROR(VLOOKUP($F26,MatrizHDUniclass!$A:$AN,36,0),"NA") -> NA | S26: =IFERROR(VLOOKUP($F26,MatrizHDUniclass!$A:$AN,37,0),"NA") -> NA | T26: =IFERROR(VLOOKUP($F26,MatrizHDUniclass!$A:$AN,38,0),"NA") -> NA | U26: =IFERROR(VLOOKUP($F26,MatrizHDUniclass!$A:$AN,39,0),"NA") -> NA | V26: =IFERROR(VLOOKUP($F26,MatrizHDUniclass!$A:$AN,40,0),"NA") -> NA | W26: Cambio de Asignación a Liliana Casallas | X26: 45987
A27: 45260 | B27: MEDELLIN | C27: 5.5 | D27: (M) .CO | E27: Microsoft 365 Empresa Básico | F27: 1036655332 | G27: supervisoresredexatpmedellin@grupoconectar.co | H27: supervisores ATP Medellín | I27: =IFERROR(VLOOKUP($F27,MatrizHDUniclass!$A:$AN,3,0),"NA") -> NA | J27: =IFERROR(VLOOKUP($F27,MatrizHDUniclass!$A:$AN,19,0),"NA") -> NA | K27: =IFERROR(VLOOKUP($F27,MatrizHDUniclass!$A:$AN,24,0),"NA") -> NA | L27: =IFERROR(VLOOKUP($F27,MatrizHDUniclass!$A:$AN,31,0),"NA") -> NA | M27: =IFERROR(VLOOKUP($F27,MatrizHDUniclass!$A:$AN,32,0),"NA") -> NA | N27: =IFERROR(VLOOKUP($F27,MatrizHDUniclass!$A:$AN,33,0),"NA") -> NA | O27: =IFERROR(VLOOKUP($F27,MatrizHDUniclass!$A:$AN,26,0),"NA") -> NA | P27: =IFERROR(VLOOKUP($F27,MatrizHDUniclass!$A:$AN,34,0),"NA") -> NA | Q27: =IFERROR(VLOOKUP($F27,MatrizHDUniclass!$A:$AN,35,0),"NA") -> NA | R27: =IFERROR(VLOOKUP($F27,MatrizHDUniclass!$A:$AN,36,0),"NA") -> NA | S27: =IFERROR(VLOOKUP($F27,MatrizHDUniclass!$A:$AN,37,0),"NA") -> NA | T27: =IFERROR(VLOOKUP($F27,MatrizHDUniclass!$A:$AN,38,0),"NA") -> NA | U27: =IFERROR(VLOOKUP($F27,MatrizHDUniclass!$A:$AN,39,0),"NA") -> NA | V27: =IFERROR(VLOOKUP($F27,MatrizHDUniclass!$A:$AN,40,0),"NA") -> NA | W27: Cambio de Asignación a Ruben Dario Gomez | X27: 45987
A28: 45315 | B28: BOGOTA | C28: 11.3 | D28: (M) .CO | E28: Microsoft 365 Empresa Estándar | F28: 1010013785 | G28: sofia.hernandez@grupoconectar.co | H28: Sofia Hernández Rodriguez (Angélica Rivera) "Baja" | I28: =IFERROR(VLOOKUP($F28,MatrizHDUniclass!$A:$AN,3,0),"NA") -> NA | J28: =IFERROR(VLOOKUP($F28,MatrizHDUniclass!$A:$AN,19,0),"NA") -> NA | K28: =IFERROR(VLOOKUP($F28,MatrizHDUniclass!$A:$AN,24,0),"NA") -> NA | L28: =IFERROR(VLOOKUP($F28,MatrizHDUniclass!$A:$AN,31,0),"NA") -> NA | M28: =IFERROR(VLOOKUP($F28,MatrizHDUniclass!$A:$AN,32,0),"NA") -> NA | N28: =IFERROR(VLOOKUP($F28,MatrizHDUniclass!$A:$AN,33,0),"NA") -> NA | O28: =IFERROR(VLOOKUP($F28,MatrizHDUniclass!$A:$AN,26,0),"NA") -> NA | P28: =IFERROR(VLOOKUP($F28,MatrizHDUniclass!$A:$AN,34,0),"NA") -> NA | Q28: =IFERROR(VLOOKUP($F28,MatrizHDUniclass!$A:$AN,35,0),"NA") -> NA | R28: =IFERROR(VLOOKUP($F28,MatrizHDUniclass!$A:$AN,36,0),"NA") -> NA | S28: =IFERROR(VLOOKUP($F28,MatrizHDUniclass!$A:$AN,37,0),"NA") -> NA | T28: =IFERROR(VLOOKUP($F28,MatrizHDUniclass!$A:$AN,38,0),"NA") -> NA | U28: =IFERROR(VLOOKUP($F28,MatrizHDUniclass!$A:$AN,39,0),"NA") -> NA | V28: =IFERROR(VLOOKUP($F28,MatrizHDUniclass!$A:$AN,40,0),"NA") -> NA | W28: Eliminado con Backup | X28: 45992
A29: 44889 | B29: BOGOTA | C29: 5.5 | D29: (M) .CO | E29: Microsoft 365 Empresa Básico | F29: 1014248901 | G29: liliana.casallas@grupoconectar.co | I29: =IFERROR(VLOOKUP($F29,MatrizHDUniclass!$A:$AN,3,0),"NA") -> CASALLAS FAJARDO LINA MARIA | J29: =IFERROR(VLOOKUP($F29,MatrizHDUniclass!$A:$AN,19,0),"NA") -> BACKOFFICE OPERACION | K29: =IFERROR(VLOOKUP($F29,MatrizHDUniclass!$A:$AN,24,0),"NA") -> IGCB | L29: =IFERROR(VLOOKUP($F29,MatrizHDUniclass!$A:$AN,31,0),"NA") -> INGENIERIA-GENERAL | M29: =IFERROR(VLOOKUP($F29,MatrizHDUniclass!$A:$AN,32,0),"NA") -> REG CENTRO | N29: =IFERROR(VLOOKUP($F29,MatrizHDUniclass!$A:$AN,33,0),"NA") -> BOGOTA | O29: =IFERROR(VLOOKUP($F29,MatrizHDUniclass!$A:$AN,26,0),"NA") -> USIM | P29: =IFERROR(VLOOKUP($F29,MatrizHDUniclass!$A:$AN,34,0),"NA") -> CLARO R4 | Q29: =IFERROR(VLOOKUP($F29,MatrizHDUniclass!$A:$AN,35,0),"NA") -> SOLU FIJAS | R29: =IFERROR(VLOOKUP($F29,MatrizHDUniclass!$A:$AN,36,0),"NA") -> IMM | S29: =IFERROR(VLOOKUP($F29,MatrizHDUniclass!$A:$AN,37,0),"NA") -> CLIENTES | T29: =IFERROR(VLOOKUP($F29,MatrizHDUniclass!$A:$AN,38,0),"NA") -> CONECTAR TV | U29: =IFERROR(VLOOKUP($F29,MatrizHDUniclass!$A:$AN,39,0),"NA") -> INGENIERIA | V29: =IFERROR(VLOOKUP($F29,MatrizHDUniclass!$A:$AN,40,0),"NA") -> PERSONAL APOYO | W29: Cambio de Asignación a Arelis Pena | X29: 45985
A30: 44533 | B30: BOGOTA | C30: 11.3 | D30: (M) .CO | E30: Microsoft 365 Empresa Estándar | F30: 1061219779 | G30: arelis.pena@grupoconectar.co | H30: ARELIS PENA CAMAYO (Angélica Rivera)(Ana Adq Mov) | I30: =IFERROR(VLOOKUP($F30,MatrizHDUniclass!$A:$AN,3,0),"NA") -> NA | J30: =IFERROR(VLOOKUP($F30,MatrizHDUniclass!$A:$AN,19,0),"NA") -> NA | K30: =IFERROR(VLOOKUP($F30,MatrizHDUniclass!$A:$AN,24,0),"NA") -> NA | L30: =IFERROR(VLOOKUP($F30,MatrizHDUniclass!$A:$AN,31,0),"NA") -> NA | M30: =IFERROR(VLOOKUP($F30,MatrizHDUniclass!$A:$AN,32,0),"NA") -> NA | N30: =IFERROR(VLOOKUP($F30,MatrizHDUniclass!$A:$AN,33,0),"NA") -> NA | O30: =IFERROR(VLOOKUP($F30,MatrizHDUniclass!$A:$AN,26,0),"NA") -> NA | P30: =IFERROR(VLOOKUP($F30,MatrizHDUniclass!$A:$AN,34,0),"NA") -> NA | Q30: =IFERROR(VLOOKUP($F30,MatrizHDUniclass!$A:$AN,35,0),"NA") -> NA | R30: =IFERROR(VLOOKUP($F30,MatrizHDUniclass!$A:$AN,36,0),"NA") -> NA | S30: =IFERROR(VLOOKUP($F30,MatrizHDUniclass!$A:$AN,37,0),"NA") -> NA | T30: =IFERROR(VLOOKUP($F30,MatrizHDUniclass!$A:$AN,38,0),"NA") -> NA | U30: =IFERROR(VLOOKUP($F30,MatrizHDUniclass!$A:$AN,39,0),"NA") -> NA | V30: =IFERROR(VLOOKUP($F30,MatrizHDUniclass!$A:$AN,40,0),"NA") -> NA | W30: Eliminado con Backup | X30: 45992
A31: 44697 | B31: BOGOTA | C31: 5.5 | D31: (M) .CO | E31: Microsoft 365 Empresa Básico | F31: 9922207 | G31: oscar.arias@grupoconectar.co | H31: "BAJA" | I31: =IFERROR(VLOOKUP($F31,MatrizHDUniclass!$A:$AN,3,0),"NA") -> NA | J31: =IFERROR(VLOOKUP($F31,MatrizHDUniclass!$A:$AN,19,0),"NA") -> NA | K31: =IFERROR(VLOOKUP($F31,MatrizHDUniclass!$A:$AN,24,0),"NA") -> NA | L31: =IFERROR(VLOOKUP($F31,MatrizHDUniclass!$A:$AN,31,0),"NA") -> NA | M31: =IFERROR(VLOOKUP($F31,MatrizHDUniclass!$A:$AN,32,0),"NA") -> NA | N31: =IFERROR(VLOOKUP($F31,MatrizHDUniclass!$A:$AN,33,0),"NA") -> NA | O31: =IFERROR(VLOOKUP($F31,MatrizHDUniclass!$A:$AN,26,0),"NA") -> NA | P31: =IFERROR(VLOOKUP($F31,MatrizHDUniclass!$A:$AN,34,0),"NA") -> NA | Q31: =IFERROR(VLOOKUP($F31,MatrizHDUniclass!$A:$AN,35,0),"NA") -> NA | R31: =IFERROR(VLOOKUP($F31,MatrizHDUniclass!$A:$AN,36,0),"NA") -> NA | S31: =IFERROR(VLOOKUP($F31,MatrizHDUniclass!$A:$AN,37,0),"NA") -> NA | T31: =IFERROR(VLOOKUP($F31,MatrizHDUniclass!$A:$AN,38,0),"NA") -> NA | U31: =IFERROR(VLOOKUP($F31,MatrizHDUniclass!$A:$AN,39,0),"NA") -> NA | V31: =IFERROR(VLOOKUP($F31,MatrizHDUniclass!$A:$AN,40,0),"NA") -> NA | W31: Eliminado con Backup | X31: 45992
A32: 45019 | B32: BOGOTA | C32: 5.5 | D32: (M) .CO | E32: Microsoft 365 Empresa Básico | F32: 53161472 | G32: daly.becerra@grupoconectar.co | H32: DALY ALEXANDRA BECERRA TORRES (Luz Jaramillo) "BAJA" | I32: =IFERROR(VLOOKUP($F32,MatrizHDUniclass!$A:$AN,3,0),"NA") -> BECERRA TORRES DALY ALEXANDRA | J32: =IFERROR(VLOOKUP($F32,MatrizHDUniclass!$A:$AN,19,0),"NA") -> BACKOFFICE OPERACION | K32: =IFERROR(VLOOKUP($F32,MatrizHDUniclass!$A:$AN,24,0),"NA") -> IGCB | L32: =IFERROR(VLOOKUP($F32,MatrizHDUniclass!$A:$AN,31,0),"NA") -> INGENIERIA-GENERAL | M32: =IFERROR(VLOOKUP($F32,MatrizHDUniclass!$A:$AN,32,0),"NA") -> REG CENTRO | N32: =IFERROR(VLOOKUP($F32,MatrizHDUniclass!$A:$AN,33,0),"NA") -> BOGOTA | O32: =IFERROR(VLOOKUP($F32,MatrizHDUniclass!$A:$AN,26,0),"NA") -> YSAF | P32: =IFERROR(VLOOKUP($F32,MatrizHDUniclass!$A:$AN,34,0),"NA") -> ZTE | Q32: =IFERROR(VLOOKUP($F32,MatrizHDUniclass!$A:$AN,35,0),"NA") -> SOLU FIJAS | R32: =IFERROR(VLOOKUP($F32,MatrizHDUniclass!$A:$AN,36,0),"NA") -> APROV FIBRA | S32: =IFERROR(VLOOKUP($F32,MatrizHDUniclass!$A:$AN,37,0),"NA") -> CLIENTES | T32: =IFERROR(VLOOKUP($F32,MatrizHDUniclass!$A:$AN,38,0),"NA") -> CONECTAR TV | U32: =IFERROR(VLOOKUP($F32,MatrizHDUniclass!$A:$AN,39,0),"NA") -> INGENIERIA | V32: =IFERROR(VLOOKUP($F32,MatrizHDUniclass!$A:$AN,40,0),"NA") -> PERSONAL APOYO | W32: Eliminado con Backup | X32: 45993
A33: 45254 | B33: IBAGUE | C33: 11.3 | D33: (M) .CO | E33: Microsoft 365 Empresa Estándar | F33: 1110536612 | G33: leonel.acosta@grupoconectar.co | H33: Leonel Alexander Acosta Mosquera "Baja" | I33: =IFERROR(VLOOKUP($F33,MatrizHDUniclass!$A:$AN,3,0),"NA") -> NA | J33: =IFERROR(VLOOKUP($F33,MatrizHDUniclass!$A:$AN,19,0),"NA") -> NA | K33: =IFERROR(VLOOKUP($F33,MatrizHDUniclass!$A:$AN,24,0),"NA") -> NA | L33: =IFERROR(VLOOKUP($F33,MatrizHDUniclass!$A:$AN,31,0),"NA") -> NA | M33: =IFERROR(VLOOKUP($F33,MatrizHDUniclass!$A:$AN,32,0),"NA") -> NA | N33: =IFERROR(VLOOKUP($F33,MatrizHDUniclass!$A:$AN,33,0),"NA") -> NA | O33: =IFERROR(VLOOKUP($F33,MatrizHDUniclass!$A:$AN,26,0),"NA") -> NA | P33: =IFERROR(VLOOKUP($F33,MatrizHDUniclass!$A:$AN,34,0),"NA") -> NA | Q33: =IFERROR(VLOOKUP($F33,MatrizHDUniclass!$A:$AN,35,0),"NA") -> NA | R33: =IFERROR(VLOOKUP($F33,MatrizHDUniclass!$A:$AN,36,0),"NA") -> NA | S33: =IFERROR(VLOOKUP($F33,MatrizHDUniclass!$A:$AN,37,0),"NA") -> NA | T33: =IFERROR(VLOOKUP($F33,MatrizHDUniclass!$A:$AN,38,0),"NA") -> NA | U33: =IFERROR(VLOOKUP($F33,MatrizHDUniclass!$A:$AN,39,0),"NA") -> NA | V33: =IFERROR(VLOOKUP($F33,MatrizHDUniclass!$A:$AN,40,0),"NA") -> NA | W33: Eliminado con Backup | X33: 45993
A34: 45391 | B34: IBAGUE | C34: 5.5 | D34: (M) .CO | E34: Microsoft 365 Empresa Básico | F34: 93180454 | G34: elkin.celis@grupoconectar.co | H34: (Leonel González)"BAJA" | I34: =IFERROR(VLOOKUP($F34,MatrizHDUniclass!$A:$AN,3,0),"NA") -> NA | J34: =IFERROR(VLOOKUP($F34,MatrizHDUniclass!$A:$AN,19,0),"NA") -> NA | K34: =IFERROR(VLOOKUP($F34,MatrizHDUniclass!$A:$AN,24,0),"NA") -> NA | L34: =IFERROR(VLOOKUP($F34,MatrizHDUniclass!$A:$AN,31,0),"NA") -> NA | M34: =IFERROR(VLOOKUP($F34,MatrizHDUniclass!$A:$AN,32,0),"NA") -> NA | N34: =IFERROR(VLOOKUP($F34,MatrizHDUniclass!$A:$AN,33,0),"NA") -> NA | O34: =IFERROR(VLOOKUP($F34,MatrizHDUniclass!$A:$AN,26,0),"NA") -> NA | P34: =IFERROR(VLOOKUP($F34,MatrizHDUniclass!$A:$AN,34,0),"NA") -> NA | Q34: =IFERROR(VLOOKUP($F34,MatrizHDUniclass!$A:$AN,35,0),"NA") -> NA | R34: =IFERROR(VLOOKUP($F34,MatrizHDUniclass!$A:$AN,36,0),"NA") -> NA | S34: =IFERROR(VLOOKUP($F34,MatrizHDUniclass!$A:$AN,37,0),"NA") -> NA | T34: =IFERROR(VLOOKUP($F34,MatrizHDUniclass!$A:$AN,38,0),"NA") -> NA | U34: =IFERROR(VLOOKUP($F34,MatrizHDUniclass!$A:$AN,39,0),"NA") -> NA | V34: =IFERROR(VLOOKUP($F34,MatrizHDUniclass!$A:$AN,40,0),"NA") -> NA | W34: Eliminado con Backup | X34: 45994
A35: 45324 | B35: MEDELLIN | C35: 5.5 | D35: (M) .CO | E35: Microsoft 365 Empresa Básico | F35: 1000323344 | G35: karen.tovar@grupoconectar.co | H35: KAREN TATIANA TOVAR BEJARANO (ATP)(Jhonatan Rodrig) "BAJA" | I35: =IFERROR(VLOOKUP($F35,MatrizHDUniclass!$A:$AN,3,0),"NA") -> NA | J35: =IFERROR(VLOOKUP($F35,MatrizHDUniclass!$A:$AN,19,0),"NA") -> NA | K35: =IFERROR(VLOOKUP($F35,MatrizHDUniclass!$A:$AN,24,0),"NA") -> NA | L35: =IFERROR(VLOOKUP($F35,MatrizHDUniclass!$A:$AN,31,0),"NA") -> NA | M35: =IFERROR(VLOOKUP($F35,MatrizHDUniclass!$A:$AN,32,0),"NA") -> NA | N35: =IFERROR(VLOOKUP($F35,MatrizHDUniclass!$A:$AN,33,0),"NA") -> NA | O35: =IFERROR(VLOOKUP($F35,MatrizHDUniclass!$A:$AN,26,0),"NA") -> NA | P35: =IFERROR(VLOOKUP($F35,MatrizHDUniclass!$A:$AN,34,0),"NA") -> NA | Q35: =IFERROR(VLOOKUP($F35,MatrizHDUniclass!$A:$AN,35,0),"NA") -> NA | R35: =IFERROR(VLOOKUP($F35,MatrizHDUniclass!$A:$AN,36,0),"NA") -> NA | S35: =IFERROR(VLOOKUP($F35,MatrizHDUniclass!$A:$AN,37,0),"NA") -> NA | T35: =IFERROR(VLOOKUP($F35,MatrizHDUniclass!$A:$AN,38,0),"NA") -> NA | U35: =IFERROR(VLOOKUP($F35,MatrizHDUniclass!$A:$AN,39,0),"NA") -> NA | V35: =IFERROR(VLOOKUP($F35,MatrizHDUniclass!$A:$AN,40,0),"NA") -> NA | W35: Eliminado con Backup | X35: 45995
A36: 44715 | B36: BOGOTA | C36: 5.5 | D36: (M) .CO | E36: Microsoft 365 Empresa Básico | F36: 51932789 | G36: auxiliar.control@grupoconectar.co | H36: (Edward Galvis) "Baja" | I36: =IFERROR(VLOOKUP($F36,MatrizHDUniclass!$A:$AN,3,0),"NA") -> NA | J36: =IFERROR(VLOOKUP($F36,MatrizHDUniclass!$A:$AN,19,0),"NA") -> NA | K36: =IFERROR(VLOOKUP($F36,MatrizHDUniclass!$A:$AN,24,0),"NA") -> NA | L36: =IFERROR(VLOOKUP($F36,MatrizHDUniclass!$A:$AN,31,0),"NA") -> NA | M36: =IFERROR(VLOOKUP($F36,MatrizHDUniclass!$A:$AN,32,0),"NA") -> NA | N36: =IFERROR(VLOOKUP($F36,MatrizHDUniclass!$A:$AN,33,0),"NA") -> NA | O36: =IFERROR(VLOOKUP($F36,MatrizHDUniclass!$A:$AN,26,0),"NA") -> NA | P36: =IFERROR(VLOOKUP($F36,MatrizHDUniclass!$A:$AN,34,0),"NA") -> NA | Q36: =IFERROR(VLOOKUP($F36,MatrizHDUniclass!$A:$AN,35,0),"NA") -> NA | R36: =IFERROR(VLOOKUP($F36,MatrizHDUniclass!$A:$AN,36,0),"NA") -> NA | S36: =IFERROR(VLOOKUP($F36,MatrizHDUniclass!$A:$AN,37,0),"NA") -> NA | T36: =IFERROR(VLOOKUP($F36,MatrizHDUniclass!$A:$AN,38,0),"NA") -> NA | U36: =IFERROR(VLOOKUP($F36,MatrizHDUniclass!$A:$AN,39,0),"NA") -> NA | V36: =IFERROR(VLOOKUP($F36,MatrizHDUniclass!$A:$AN,40,0),"NA") -> NA | W36: Eliminado con Backup | X36: 45995
A37: 44393 | B37: CALI | C37: 5.5 | D37: (M) .CO | E37: Microsoft 365 Empresa Básico | F37: 94532031 | G37: jeinson.montenegro@grupoconectar.co | H37: ATP CALI "BAJA" | I37: =IFERROR(VLOOKUP($F37,MatrizHDUniclass!$A:$AN,3,0),"NA") -> NA | J37: =IFERROR(VLOOKUP($F37,MatrizHDUniclass!$A:$AN,19,0),"NA") -> NA | K37: =IFERROR(VLOOKUP($F37,MatrizHDUniclass!$A:$AN,24,0),"NA") -> NA | L37: =IFERROR(VLOOKUP($F37,MatrizHDUniclass!$A:$AN,31,0),"NA") -> NA | M37: =IFERROR(VLOOKUP($F37,MatrizHDUniclass!$A:$AN,32,0),"NA") -> NA | N37: =IFERROR(VLOOKUP($F37,MatrizHDUniclass!$A:$AN,33,0),"NA") -> NA | O37: =IFERROR(VLOOKUP($F37,MatrizHDUniclass!$A:$AN,26,0),"NA") -> NA | P37: =IFERROR(VLOOKUP($F37,MatrizHDUniclass!$A:$AN,34,0),"NA") -> NA | Q37: =IFERROR(VLOOKUP($F37,MatrizHDUniclass!$A:$AN,35,0),"NA") -> NA | R37: =IFERROR(VLOOKUP($F37,MatrizHDUniclass!$A:$AN,36,0),"NA") -> NA | S37: =IFERROR(VLOOKUP($F37,MatrizHDUniclass!$A:$AN,37,0),"NA") -> NA | T37: =IFERROR(VLOOKUP($F37,MatrizHDUniclass!$A:$AN,38,0),"NA") -> NA | U37: =IFERROR(VLOOKUP($F37,MatrizHDUniclass!$A:$AN,39,0),"NA") -> NA | V37: =IFERROR(VLOOKUP($F37,MatrizHDUniclass!$A:$AN,40,0),"NA") -> NA | W37: Eliminado con Backup | X37: 45996
A38: 45247 | B38: CALI | C38: 11.3 | D38: (M) .CO | E38: Microsoft 365 Empresa Estándar | F38: 1130593293 | G38: jeferson.bedoya@grupoconectar.co | H38: FORMADOR TH R3 (Leonel González) "Baja" | I38: =IFERROR(VLOOKUP($F38,MatrizHDUniclass!$A:$AN,3,0),"NA") -> NA | J38: =IFERROR(VLOOKUP($F38,MatrizHDUniclass!$A:$AN,19,0),"NA") -> NA | K38: =IFERROR(VLOOKUP($F38,MatrizHDUniclass!$A:$AN,24,0),"NA") -> NA | L38: =IFERROR(VLOOKUP($F38,MatrizHDUniclass!$A:$AN,31,0),"NA") -> NA | M38: =IFERROR(VLOOKUP($F38,MatrizHDUniclass!$A:$AN,32,0),"NA") -> NA | N38: =IFERROR(VLOOKUP($F38,MatrizHDUniclass!$A:$AN,33,0),"NA") -> NA | O38: =IFERROR(VLOOKUP($F38,MatrizHDUniclass!$A:$AN,26,0),"NA") -> NA | P38: =IFERROR(VLOOKUP($F38,MatrizHDUniclass!$A:$AN,34,0),"NA") -> NA | Q38: =IFERROR(VLOOKUP($F38,MatrizHDUniclass!$A:$AN,35,0),"NA") -> NA | R38: =IFERROR(VLOOKUP($F38,MatrizHDUniclass!$A:$AN,36,0),"NA") -> NA | S38: =IFERROR(VLOOKUP($F38,MatrizHDUniclass!$A:$AN,37,0),"NA") -> NA | T38: =IFERROR(VLOOKUP($F38,MatrizHDUniclass!$A:$AN,38,0),"NA") -> NA | U38: =IFERROR(VLOOKUP($F38,MatrizHDUniclass!$A:$AN,39,0),"NA") -> NA | V38: =IFERROR(VLOOKUP($F38,MatrizHDUniclass!$A:$AN,40,0),"NA") -> NA | W38: Eliminado con Backup | X38: 45996
A39: 45994 | B39: BOGOTA | C39: 5.5 | D39: (M) .CO | E39: Microsoft 365 Empresa Básico | F39: 1015437159 | G39: diana.diaz.c@grupoconectar.co | H39: DIANA DIAZ (Christofer Garcia) | I39: =IFERROR(VLOOKUP($F39,MatrizHDUniclass!$A:$AN,3,0),"NA") -> DIAZ CARDENAS DIANA MILENA | J39: =IFERROR(VLOOKUP($F39,MatrizHDUniclass!$A:$AN,19,0),"NA") -> ANALISTA OPERACION | K39: =IFERROR(VLOOKUP($F39,MatrizHDUniclass!$A:$AN,24,0),"NA") -> IGCB | L39: =IFERROR(VLOOKUP($F39,MatrizHDUniclass!$A:$AN,31,0),"NA") -> INGENIERIA-GENERAL | M39: =IFERROR(VLOOKUP($F39,MatrizHDUniclass!$A:$AN,32,0),"NA") -> REG CENTRO | N39: =IFERROR(VLOOKUP($F39,MatrizHDUniclass!$A:$AN,33,0),"NA") -> BOGOTA | O39: =IFERROR(VLOOKUP($F39,MatrizHDUniclass!$A:$AN,26,0),"NA") -> HNTR | P39: =IFERROR(VLOOKUP($F39,MatrizHDUniclass!$A:$AN,34,0),"NA") -> HUAWEI | Q39: =IFERROR(VLOOKUP($F39,MatrizHDUniclass!$A:$AN,35,0),"NA") -> NUEVOS NEG | R39: =IFERROR(VLOOKUP($F39,MatrizHDUniclass!$A:$AN,36,0),"NA") -> TRANSV UEN | S39: =IFERROR(VLOOKUP($F39,MatrizHDUniclass!$A:$AN,37,0),"NA") -> CLIENTES | T39: =IFERROR(VLOOKUP($F39,MatrizHDUniclass!$A:$AN,38,0),"NA") -> CONECTAR TV | U39: =IFERROR(VLOOKUP($F39,MatrizHDUniclass!$A:$AN,39,0),"NA") -> INGENIERIA | V39: =IFERROR(VLOOKUP($F39,MatrizHDUniclass!$A:$AN,40,0),"NA") -> OPERATIVO | W39: Modificacion de Licencia a Standard | X39: 45996
A40: 45378 | B40: BOGOTA | C40: 5.5 | D40: (M) .CO | E40: Microsoft 365 Empresa Básico | F40: 1000255177 | G40: laura.rocha@grupoconectar.co | H40: LAURA XIMENA ROCHA DUQUE (Lina Bocanegra) | I40: =IFERROR(VLOOKUP($F40,MatrizHDUniclass!$A:$AN,3,0),"NA") -> NA | J40: =IFERROR(VLOOKUP($F40,MatrizHDUniclass!$A:$AN,19,0),"NA") -> NA | K40: =IFERROR(VLOOKUP($F40,MatrizHDUniclass!$A:$AN,24,0),"NA") -> NA | L40: =IFERROR(VLOOKUP($F40,MatrizHDUniclass!$A:$AN,31,0),"NA") -> NA | M40: =IFERROR(VLOOKUP($F40,MatrizHDUniclass!$A:$AN,32,0),"NA") -> NA | N40: =IFERROR(VLOOKUP($F40,MatrizHDUniclass!$A:$AN,33,0),"NA") -> NA | O40: =IFERROR(VLOOKUP($F40,MatrizHDUniclass!$A:$AN,26,0),"NA") -> NA | P40: =IFERROR(VLOOKUP($F40,MatrizHDUniclass!$A:$AN,34,0),"NA") -> NA | Q40: =IFERROR(VLOOKUP($F40,MatrizHDUniclass!$A:$AN,35,0),"NA") -> NA | R40: =IFERROR(VLOOKUP($F40,MatrizHDUniclass!$A:$AN,36,0),"NA") -> NA | S40: =IFERROR(VLOOKUP($F40,MatrizHDUniclass!$A:$AN,37,0),"NA") -> NA | T40: =IFERROR(VLOOKUP($F40,MatrizHDUniclass!$A:$AN,38,0),"NA") -> NA | U40: =IFERROR(VLOOKUP($F40,MatrizHDUniclass!$A:$AN,39,0),"NA") -> NA | V40: =IFERROR(VLOOKUP($F40,MatrizHDUniclass!$A:$AN,40,0),"NA") -> NA | W40: Cambio de Asignación a Juan Sebastian Barrantes | X40: 45996
A41: 45293 | B41: CALI | C41: 11.3 | D41: (M) .CO | E41: Microsoft 365 Empresa Estándar | F41: 66933425 | G41: paula.marulanda@grupoconectar.co | H41: PAULA ANDREA MARULANDA VIVEROS (Analis Admin) R3 (Eliesid G.) "Baja" | I41: =IFERROR(VLOOKUP($F41,MatrizHDUniclass!$A:$AN,3,0),"NA") -> NA | J41: =IFERROR(VLOOKUP($F41,MatrizHDUniclass!$A:$AN,19,0),"NA") -> NA | K41: =IFERROR(VLOOKUP($F41,MatrizHDUniclass!$A:$AN,24,0),"NA") -> NA | L41: =IFERROR(VLOOKUP($F41,MatrizHDUniclass!$A:$AN,31,0),"NA") -> NA | M41: =IFERROR(VLOOKUP($F41,MatrizHDUniclass!$A:$AN,32,0),"NA") -> NA | N41: =IFERROR(VLOOKUP($F41,MatrizHDUniclass!$A:$AN,33,0),"NA") -> NA | O41: =IFERROR(VLOOKUP($F41,MatrizHDUniclass!$A:$AN,26,0),"NA") -> NA | P41: =IFERROR(VLOOKUP($F41,MatrizHDUniclass!$A:$AN,34,0),"NA") -> NA | Q41: =IFERROR(VLOOKUP($F41,MatrizHDUniclass!$A:$AN,35,0),"NA") -> NA | R41: =IFERROR(VLOOKUP($F41,MatrizHDUniclass!$A:$AN,36,0),"NA") -> NA | S41: =IFERROR(VLOOKUP($F41,MatrizHDUniclass!$A:$AN,37,0),"NA") -> NA | T41: =IFERROR(VLOOKUP($F41,MatrizHDUniclass!$A:$AN,38,0),"NA") -> NA | U41: =IFERROR(VLOOKUP($F41,MatrizHDUniclass!$A:$AN,39,0),"NA") -> NA | V41: =IFERROR(VLOOKUP($F41,MatrizHDUniclass!$A:$AN,40,0),"NA") -> NA | W41: Eliminado con Backup | X41: 45996
A42: 45231 | B42: MEDELLIN | C42: 5.5 | D42: (M) .CO | E42: Microsoft 365 Empresa Básico | F42: 1214719554 | G42: elton.cortes@grupoconectar.co | H42: CORTES TIRADO ELTON (Crhistofer) | I42: =IFERROR(VLOOKUP($F42,MatrizHDUniclass!$A:$AN,3,0),"NA") -> NA | J42: =IFERROR(VLOOKUP($F42,MatrizHDUniclass!$A:$AN,19,0),"NA") -> NA | K42: =IFERROR(VLOOKUP($F42,MatrizHDUniclass!$A:$AN,24,0),"NA") -> NA | L42: =IFERROR(VLOOKUP($F42,MatrizHDUniclass!$A:$AN,31,0),"NA") -> NA | M42: =IFERROR(VLOOKUP($F42,MatrizHDUniclass!$A:$AN,32,0),"NA") -> NA | N42: =IFERROR(VLOOKUP($F42,MatrizHDUniclass!$A:$AN,33,0),"NA") -> NA | O42: =IFERROR(VLOOKUP($F42,MatrizHDUniclass!$A:$AN,26,0),"NA") -> NA | P42: =IFERROR(VLOOKUP($F42,MatrizHDUniclass!$A:$AN,34,0),"NA") -> NA | Q42: =IFERROR(VLOOKUP($F42,MatrizHDUniclass!$A:$AN,35,0),"NA") -> NA | R42: =IFERROR(VLOOKUP($F42,MatrizHDUniclass!$A:$AN,36,0),"NA") -> NA | S42: =IFERROR(VLOOKUP($F42,MatrizHDUniclass!$A:$AN,37,0),"NA") -> NA | T42: =IFERROR(VLOOKUP($F42,MatrizHDUniclass!$A:$AN,38,0),"NA") -> NA | U42: =IFERROR(VLOOKUP($F42,MatrizHDUniclass!$A:$AN,39,0),"NA") -> NA | V42: =IFERROR(VLOOKUP($F42,MatrizHDUniclass!$A:$AN,40,0),"NA") -> NA | W42: Cambio de Asignación a Julián Atehortúa V | X42: 46001
A43: 45537 | B43: MEDELLIN | C43: 5.5 | D43: (M) .CO | E43: Microsoft 365 Empresa Básico | F43: 1017210041 | G43: julian.atehortua@grupoconectar.co | H43: BAJA | I43: ATEHORTUA VANEGAS JULIAN ALEXANDER | J43: TECNICO CONDUCTOR HUAWEI FLM | K43: IGAM | L43: INGENIERIA-GENERAL | M43: NA | N43: NA | O43: NA | P43: NA | Q43: NA | R43: NA | S43: NA | T43: NA | U43: NA | V43: NA | W43: Eliminado con Backup | X43: 46002
A44: 45499 | B44: IBAGUE | C44: 5.5 | D44: (M) .CO | E44: Microsoft 365 Empresa Básico | F44: 1104700436 | G44: jimmy.ballen@grupoconectar.co | H44: JIMMY ALEXANDER BALLEN QUINTERO IMPECOM "Baja" | I44: NA | J44: NA | K44: NA | L44: NA | M44: NA | N44: NA | O44: NA | P44: NA | Q44: NA | R44: NA | S44: NA | T44: NA | U44: NA | V44: NA | W44: Eliminado con Backup | X44: 46002
A45: 45730 | B45: MEDELLIN | C45: 5.5 | D45: (M) .CO | E45: Microsoft 365 Empresa Básico | F45: 1128433706 | G45: jaksson.mosquera@grupoconectar.co | H45: MOSQUERA ROBLEDO JAKSSON (Randy Pérez) | I45: ROBLEDO MOSQUERA JAKSSON HERMELY | J45: DISEÑADOR OPERACION | K45: IGAM | L45: INGENIERIA-GENERAL | M45: REG ANTIO | N45: MEDELLIN | O45: ISST | P45: TIGO | Q45: SOLU FIJAS | R45: STRONG | S45: CLIENTES | T45: CONECTAR TV | U45: INGENIERIA | V45: OPERATIVO | W45: Modificacion de Licencia a Standard | X45: 46003
A46: 45254 | B46: IBAGUE | C46: 11.3 | D46: (M) .CO | E46: Microsoft 365 Empresa Estándar | F46: 1005711291 | G46: eric.orjuela@grupoconectar.co | H46: Eric Santiago Orjuela Fierro "Baja" | I46: NA | J46: NA | K46: NA | L46: NA | M46: NA | N46: NA | O46: NA | P46: NA | Q46: NA | R46: NA | S46: NA | T46: NA | U46: NA | V46: NA | W46: Eliminado con Backup | X46: 46003
A47: 45574 | B47: MEDELLIN | C47: 5.5 | D47: (M) .CO | E47: Microsoft 365 Empresa Básico | F47: 80231431 | G47: sandro.zabaleta@grupoconectar.co | H47: SANDRO ZABALETA "BAJA" | I47: NA | J47: NA | K47: NA | L47: NA | M47: NA | N47: NA | O47: NA | P47: NA | Q47: NA | R47: NA | S47: NA | T47: NA | U47: NA | V47: NA | W47: Eliminado con Backup | X47: 46003
A48: 45730 | B48: MEDELLIN | C48: 4.53 | D48: (M) .CO | E48: Exchange Online (Plan 1) | F48: 1048018219 | G48: diego.montoya@grupoconectar.co | H48: DIEGO ALEJANDRO MONTOYA DURANGO (Randy Pérez) | I48: MONTOYA DURANGO DIEGO ALEJANDRO | J48: DISEÑADOR OPERACION | K48: IGAM | L48: INGENIERIA-GENERAL | M48: REG ANTIO | N48: MEDELLIN | O48: ISST | P48: TIGO | Q48: SOLU FIJAS | R48: STRONG | S48: CLIENTES | T48: CONECTAR TV | U48: INGENIERIA | V48: OPERATIVO | W48: Modificacion de Licencia a Standard | X48: 46003
A49: 45244 | B49: FLORENCIA | C49: 11.3 | D49: (M) .CO | E49: Microsoft 365 Empresa Estándar | F49: 1083882842 | G49: walter.burbano@grupoconectar.co | H49: Walter Burbano "BAJA" | I49: NA | J49: NA | K49: NA | L49: NA | M49: NA | N49: NA | O49: NA | P49: NA | Q49: NA | R49: NA | S49: NA | T49: NA | U49: NA | V49: NA | W49: Modificacion de Licencia a Básico | X49: 46003
A50: 45250 | B50: FLORENCIA | C50: 11.3 | D50: (M) .CO | E50: Microsoft 365 Empresa Estándar | F50: 1117492191 | G50: derly.quintero@grupoconectar.co | H50: DERLY YANETH QUINTERO OMET th Florencia "Baja" | I50: NA | J50: NA | K50: NA | L50: NA | M50: NA | N50: NA | O50: NA | P50: NA | Q50: NA | R50: NA | S50: NA | T50: NA | U50: NA | V50: NA | W50: Modificacion de Licencia a Básico | X50: 46003
A51: 45250 | B51: ESPINAL | C51: 11.3 | D51: (M) .CO | E51: Microsoft 365 Empresa Estándar | F51: 1105692415 | G51: jhoan.ortiz@grupoconectar.co | H51: JHOAN SEBASTIAN ORTIZ QUIMBAYO th Espinal "Baja" | I51: NA | J51: NA | K51: NA | L51: NA | M51: NA | N51: NA | O51: NA | P51: NA | Q51: NA | R51: NA | S51: NA | T51: NA | U51: NA | V51: NA | W51: Modificacion de Licencia a Básico | X51: 46003
A52: 45259 | B52: CALI | C52: 11.3 | D52: (M) .CO | E52: Microsoft 365 Empresa Estándar | F52: 94526617 | G52: jonierth.velasquez@grupoconectar.co | H52: Jonierth Alberto Velásquez Landino (Iván Arias) CLARO R3 | I52: NA | J52: NA | K52: NA | L52: NA | M52: NA | N52: NA | O52: NA | P52: NA | Q52: NA | R52: NA | S52: NA | T52: NA | U52: NA | V52: NA | W52: Modificacion de Licencia a Básico | X52: 46003
A53: 45730 | B53: MEDELLIN | C53: 4.53 | D53: (M) .CO | E53: Exchange Online (Plan 1) | F53: 1020407640 | G53: jorge.ospina@grupoconectar.co | H53: JORGE LUIS OSPINA CANO (Randy Pérez) | I53: OSPINA CANO JORGE LUIS | J53: DISEÑADOR OPERACION | K53: IGAM | L53: INGENIERIA-GENERAL | M53: REG ANTIO | N53: MEDELLIN | O53: ISST | P53: TIGO | Q53: SOLU FIJAS | R53: STRONG | S53: CLIENTES | T53: CONECTAR TV | U53: INGENIERIA | V53: OPERATIVO | W53: Modificacion de Licencia a Standard | X53: 46006
A54: 45168 | B54: MEDELLIN | C54: 5.5 | D54: (M) .CO | E54: Microsoft 365 Empresa Básico | F54: 1152200424 | G54: jennifer.velasquez@grupoconectar.co | H54: (randy perez) TIGO | I54: VELASQUEZ MUNOZ JENNIFER ALEXANDRA | J54: ANALISTA OPERACION | K54: IGAM | L54: INGENIERIA-GENERAL | M54: REG ANTIO | N54: MEDELLIN | O54: ISST | P54: TIGO | Q54: SOLU FIJAS | R54: STRONG | S54: CLIENTES | T54: CONECTAR TV | U54: INGENIERIA | V54: OPERATIVO | W54: Modificacion de Licencia a Standard | X54: 46006
... A63: 45254 | B63: CALI | C63: 11.3 | D63: (M) .CO | E63: Microsoft 365 Empresa Estándar | F63: 14468277 | G63: jonathan.correa@grupoconectar.co | H63: Jonathan Correa "Baja" | I63: NA | J63: NA | K63: NA | L63: NA | M63: NA | N63: NA | O63: NA | P63: NA | Q63: NA | R63: NA | S63: NA | T63: NA | U63: NA | V63: NA | W63: Modificacion de Licencia a Básico | X63: 46007
A64: 44427 | B64: BOGOTA | C64: 5.5 | D64: (M) .CO | E64: Microsoft 365 Empresa Básico | F64: 80231431 | G64: jairo.munoz@grupoconectar.co | H64: OK "Milher" "BAJA" | I64: =IFERROR(VLOOKUP(F64,MatrizHDUniclass!$A:$AN,3,0),"NA") -> NA | J64: =IFERROR(VLOOKUP(F64,MatrizHDUniclass!$A:$AN,19,0),"NA") -> NA | K64: =IFERROR(VLOOKUP(F64,MatrizHDUniclass!$A:$AN,24,0),"NA") -> NA | L64: =IFERROR(VLOOKUP(F64,MatrizHDUniclass!$A:$AN,31,0),"NA") -> NA | M64: =IFERROR(VLOOKUP(F64,MatrizHDUniclass!$A:$AN,32,0),"NA") -> NA | N64: =IFERROR(VLOOKUP(F64,MatrizHDUniclass!$A:$AN,33,0),"NA") -> NA | O64: =IFERROR(VLOOKUP(F64,MatrizHDUniclass!$A:$AN,26,0),"NA") -> NA | P64: =IFERROR(VLOOKUP(F64,MatrizHDUniclass!$A:$AN,34,0),"NA") -> NA | Q64: =IFERROR(VLOOKUP(F64,MatrizHDUniclass!$A:$AN,35,0),"NA") -> NA | R64: =IFERROR(VLOOKUP(F64,MatrizHDUniclass!$A:$AN,36,0),"NA") -> NA | S64: =IFERROR(VLOOKUP(F64,MatrizHDUniclass!$A:$AN,37,0),"NA") -> NA | T64: =IFERROR(VLOOKUP(F64,MatrizHDUniclass!$A:$AN,38,0),"NA") -> NA | U64: =IFERROR(VLOOKUP(F64,MatrizHDUniclass!$A:$AN,39,0),"NA") -> NA | V64: =IFERROR(VLOOKUP(F64,MatrizHDUniclass!$A:$AN,40,0),"NA") -> NA | W64: Eliminado con Backup | X64: 46007
A65: 45351 | B65: BOGOTA | C65: 11.3 | D65: (M) .CO | E65: Microsoft 365 Empresa Estándar | F65: 1012357471 | G65: carlos.londono@grupoconectar.co | H65: "Baja" | I65: =IFERROR(VLOOKUP(F65,MatrizHDUniclass!$A:$AN,3,0),"NA") -> NA | J65: =IFERROR(VLOOKUP(F65,MatrizHDUniclass!$A:$AN,19,0),"NA") -> NA | K65: =IFERROR(VLOOKUP(F65,MatrizHDUniclass!$A:$AN,24,0),"NA") -> NA | L65: =IFERROR(VLOOKUP(F65,MatrizHDUniclass!$A:$AN,31,0),"NA") -> NA | M65: =IFERROR(VLOOKUP(F65,MatrizHDUniclass!$A:$AN,32,0),"NA") -> NA | N65: =IFERROR(VLOOKUP(F65,MatrizHDUniclass!$A:$AN,33,0),"NA") -> NA | O65: =IFERROR(VLOOKUP(F65,MatrizHDUniclass!$A:$AN,26,0),"NA") -> NA | P65: =IFERROR(VLOOKUP(F65,MatrizHDUniclass!$A:$AN,34,0),"NA") -> NA | Q65: =IFERROR(VLOOKUP(F65,MatrizHDUniclass!$A:$AN,35,0),"NA") -> NA | R65: =IFERROR(VLOOKUP(F65,MatrizHDUniclass!$A:$AN,36,0),"NA") -> NA | S65: =IFERROR(VLOOKUP(F65,MatrizHDUniclass!$A:$AN,37,0),"NA") -> NA | T65: =IFERROR(VLOOKUP(F65,MatrizHDUniclass!$A:$AN,38,0),"NA") -> NA | U65: =IFERROR(VLOOKUP(F65,MatrizHDUniclass!$A:$AN,39,0),"NA") -> NA | V65: =IFERROR(VLOOKUP(F65,MatrizHDUniclass!$A:$AN,40,0),"NA") -> NA | W65: Modificacion de Licencia a Básico | X65: 46008
A66: 45916 | B66: MEDELLIN | C66: 5.5 | D66: (M) .CO | E66: Microsoft 365 Empresa Básico | F66: 1037646737 | G66: helmer.blandon@grupoconectar.co | H66: Helmer Alejandro Blandon Castaneda (Juan Guarin) | I66: =IFERROR(VLOOKUP(F66,MatrizHDUniclass!$A:$AN,3,0),"NA") -> NA | J66: =IFERROR(VLOOKUP(F66,MatrizHDUniclass!$A:$AN,19,0),"NA") -> NA | K66: =IFERROR(VLOOKUP(F66,MatrizHDUniclass!$A:$AN,24,0),"NA") -> NA | L66: =IFERROR(VLOOKUP(F66,MatrizHDUniclass!$A:$AN,31,0),"NA") -> NA | M66: =IFERROR(VLOOKUP(F66,MatrizHDUniclass!$A:$AN,32,0),"NA") -> NA | N66: =IFERROR(VLOOKUP(F66,MatrizHDUniclass!$A:$AN,33,0),"NA") -> NA | O66: =IFERROR(VLOOKUP(F66,MatrizHDUniclass!$A:$AN,26,0),"NA") -> NA | P66: =IFERROR(VLOOKUP(F66,MatrizHDUniclass!$A:$AN,34,0),"NA") -> NA | Q66: =IFERROR(VLOOKUP(F66,MatrizHDUniclass!$A:$AN,35,0),"NA") -> NA | R66: =IFERROR(VLOOKUP(F66,MatrizHDUniclass!$A:$AN,36,0),"NA") -> NA | S66: =IFERROR(VLOOKUP(F66,MatrizHDUniclass!$A:$AN,37,0),"NA") -> NA | T66: =IFERROR(VLOOKUP(F66,MatrizHDUniclass!$A:$AN,38,0),"NA") -> NA | U66: =IFERROR(VLOOKUP(F66,MatrizHDUniclass!$A:$AN,39,0),"NA") -> NA | V66: =IFERROR(VLOOKUP(F66,MatrizHDUniclass!$A:$AN,40,0),"NA") -> NA | W66: Modificacion de Licencia a Standard | X66: 46008
A67: 45456 | B67: MEDELLIN | C67: 4.53 | D67: (M) .CO | E67: Exchange Online (Plan 1) | F67: 1152693318 | G67: laura.ortiz@grupoconectar.co | H67: TIGO (Melissa Mejía) | I67: =IFERROR(VLOOKUP(F67,MatrizHDUniclass!$A:$AN,3,0),"NA") -> ORTIZ PINEDA LAURA MARCELA | J67: =IFERROR(VLOOKUP(F67,MatrizHDUniclass!$A:$AN,19,0),"NA") -> ANALISTA OPERACION | K67: =IFERROR(VLOOKUP(F67,MatrizHDUniclass!$A:$AN,24,0),"NA") -> IGAM | L67: =IFERROR(VLOOKUP(F67,MatrizHDUniclass!$A:$AN,31,0),"NA") -> INGENIERIA-GENERAL | M67: =IFERROR(VLOOKUP(F67,MatrizHDUniclass!$A:$AN,32,0),"NA") -> REG ANTIO | N67: =IFERROR(VLOOKUP(F67,MatrizHDUniclass!$A:$AN,33,0),"NA") -> MEDELLIN | O67: =IFERROR(VLOOKUP(F67,MatrizHDUniclass!$A:$AN,26,0),"NA") -> ISCA | P67: =IFERROR(VLOOKUP(F67,MatrizHDUniclass!$A:$AN,34,0),"NA") -> TIGO | Q67: =IFERROR(VLOOKUP(F67,MatrizHDUniclass!$A:$AN,35,0),"NA") -> SOLU FIJAS | R67: =IFERROR(VLOOKUP(F67,MatrizHDUniclass!$A:$AN,36,0),"NA") -> CAPACITY | S67: =IFERROR(VLOOKUP(F67,MatrizHDUniclass!$A:$AN,37,0),"NA") -> CLIENTES | T67: =IFERROR(VLOOKUP(F67,MatrizHDUniclass!$A:$AN,38,0),"NA") -> CONECTAR TV | U67: =IFERROR(VLOOKUP(F67,MatrizHDUniclass!$A:$AN,39,0),"NA") -> INGENIERIA | V67: =IFERROR(VLOOKUP(F67,MatrizHDUniclass!$A:$AN,40,0),"NA") -> OPERATIVO | W67: Modificacion de Licencia a Standard | X67: 46008
A68: 43984 | B68: CALI | C68: 5.5 | D68: (M) .CO | E68: Microsoft 365 Empresa Básico | F68: 1104700436 | G68: andrea.corredor@grupoconectar.co | H68: OK "Milher" "BAJA" | I68: =IFERROR(VLOOKUP(F68,MatrizHDUniclass!$A:$AN,3,0),"NA") -> NA | J68: =IFERROR(VLOOKUP(F68,MatrizHDUniclass!$A:$AN,19,0),"NA") -> NA | K68: =IFERROR(VLOOKUP(F68,MatrizHDUniclass!$A:$AN,24,0),"NA") -> NA | L68: =IFERROR(VLOOKUP(F68,MatrizHDUniclass!$A:$AN,31,0),"NA") -> NA | M68: =IFERROR(VLOOKUP(F68,MatrizHDUniclass!$A:$AN,32,0),"NA") -> NA | N68: =IFERROR(VLOOKUP(F68,MatrizHDUniclass!$A:$AN,33,0),"NA") -> NA | O68: =IFERROR(VLOOKUP(F68,MatrizHDUniclass!$A:$AN,26,0),"NA") -> NA | P68: =IFERROR(VLOOKUP(F68,MatrizHDUniclass!$A:$AN,34,0),"NA") -> NA | Q68: =IFERROR(VLOOKUP(F68,MatrizHDUniclass!$A:$AN,35,0),"NA") -> NA | R68: =IFERROR(VLOOKUP(F68,MatrizHDUniclass!$A:$AN,36,0),"NA") -> NA | S68: =IFERROR(VLOOKUP(F68,MatrizHDUniclass!$A:$AN,37,0),"NA") -> NA | T68: =IFERROR(VLOOKUP(F68,MatrizHDUniclass!$A:$AN,38,0),"NA") -> NA | U68: =IFERROR(VLOOKUP(F68,MatrizHDUniclass!$A:$AN,39,0),"NA") -> NA | V68: =IFERROR(VLOOKUP(F68,MatrizHDUniclass!$A:$AN,40,0),"NA") -> NA | W68: Eliminado con Backup | X68: 46008
A69: 45295 | B69: CALI | C69: 11.3 | D69: (M) .CO | E69: Microsoft 365 Empresa Estándar | F69: 6343651 | G69: ruben.solano@grupoconectar.co | H69: SOLANO RUBEN DARIO (Jhoan Gil)"Baja" | I69: NA | J69: NA | K69: NA | L69: NA | M69: NA | N69: NA | O69: NA | P69: NA | Q69: NA | R69: NA | S69: NA | T69: NA | U69: NA | V69: NA | W69: Eliminado con Backup | X69: 46008
A70: 45345 | B70: IBAGUE | C70: 4.53 | D70: (M) .CO | E70: Exchange Online (Plan 1) | F70: 1104700436 | G70: diego.rozo@grupoconectar.co | H70: (Miguel Alfonso) GESTOR IMPECOM "Baja" | I70: =IFERROR(VLOOKUP(F70,MatrizHDUniclass!$A:$AN,3,0),"NA") -> NA | J70: =IFERROR(VLOOKUP(F70,MatrizHDUniclass!$A:$AN,19,0),"NA") -> NA | K70: =IFERROR(VLOOKUP(F70,MatrizHDUniclass!$A:$AN,24,0),"NA") -> NA | L70: =IFERROR(VLOOKUP(F70,MatrizHDUniclass!$A:$AN,31,0),"NA") -> NA | M70: =IFERROR(VLOOKUP(F70,MatrizHDUniclass!$A:$AN,32,0),"NA") -> NA | N70: =IFERROR(VLOOKUP(F70,MatrizHDUniclass!$A:$AN,33,0),"NA") -> NA | O70: =IFERROR(VLOOKUP(F70,MatrizHDUniclass!$A:$AN,26,0),"NA") -> NA | P70: =IFERROR(VLOOKUP(F70,MatrizHDUniclass!$A:$AN,34,0),"NA") -> NA | Q70: =IFERROR(VLOOKUP(F70,MatrizHDUniclass!$A:$AN,35,0),"NA") -> NA | R70: =IFERROR(VLOOKUP(F70,MatrizHDUniclass!$A:$AN,36,0),"NA") -> NA | S70: =IFERROR(VLOOKUP(F70,MatrizHDUniclass!$A:$AN,37,0),"NA") -> NA | T70: =IFERROR(VLOOKUP(F70,MatrizHDUniclass!$A:$AN,38,0),"NA") -> NA | U70: =IFERROR(VLOOKUP(F70,MatrizHDUniclass!$A:$AN,39,0),"NA") -> NA | V70: =IFERROR(VLOOKUP(F70,MatrizHDUniclass!$A:$AN,40,0),"NA") -> NA | W70: Eliminado con Backup | X70: 46009
A71: 45351 | B71: BOGOTA | C71: 5.5 | D71: (M) .CO | E71: Microsoft 365 Empresa Básico | F71: 1012357471 | G71: carlos.londono@grupoconectar.co | H71: "Baja" | I71: =IFERROR(VLOOKUP(F71,MatrizHDUniclass!$A:$AN,3,0),"NA") -> NA | J71: =IFERROR(VLOOKUP(F71,MatrizHDUniclass!$A:$AN,19,0),"NA") -> NA | K71: =IFERROR(VLOOKUP(F71,MatrizHDUniclass!$A:$AN,24,0),"NA") -> NA | L71: =IFERROR(VLOOKUP(F71,MatrizHDUniclass!$A:$AN,31,0),"NA") -> NA | M71: =IFERROR(VLOOKUP(F71,MatrizHDUniclass!$A:$AN,32,0),"NA") -> NA | N71: =IFERROR(VLOOKUP(F71,MatrizHDUniclass!$A:$AN,33,0),"NA") -> NA | O71: =IFERROR(VLOOKUP(F71,MatrizHDUniclass!$A:$AN,26,0),"NA") -> NA | P71: =IFERROR(VLOOKUP(F71,MatrizHDUniclass!$A:$AN,34,0),"NA") -> NA | Q71: =IFERROR(VLOOKUP(F71,MatrizHDUniclass!$A:$AN,35,0),"NA") -> NA | R71: =IFERROR(VLOOKUP(F71,MatrizHDUniclass!$A:$AN,36,0),"NA") -> NA | S71: =IFERROR(VLOOKUP(F71,MatrizHDUniclass!$A:$AN,37,0),"NA") -> NA | T71: =IFERROR(VLOOKUP(F71,MatrizHDUniclass!$A:$AN,38,0),"NA") -> NA | U71: =IFERROR(VLOOKUP(F71,MatrizHDUniclass!$A:$AN,39,0),"NA") -> NA | V71: =IFERROR(VLOOKUP(F71,MatrizHDUniclass!$A:$AN,40,0),"NA") -> NA | W71: Eliminado con Backup | X71: 46009
A72: 45894 | B72: BOGOTA | C72: 11.3 | D72: (M) .CO | E72: Microsoft 365 Empresa Estándar | F72: 1023362874 | G72: nicoll.trujillo@grupoconectar.co | H72: Nicoll Dayana Trujillo Alcantar (Angie Millán) | I72: =IFERROR(VLOOKUP(F72,MatrizHDUniclass!$A:$AN,3,0),"NA") -> NA | J72: =IFERROR(VLOOKUP(F72,MatrizHDUniclass!$A:$AN,19,0),"NA") -> NA | K72: =IFERROR(VLOOKUP(F72,MatrizHDUniclass!$A:$AN,24,0),"NA") -> NA | L72: =IFERROR(VLOOKUP(F72,MatrizHDUniclass!$A:$AN,31,0),"NA") -> NA | M72: =IFERROR(VLOOKUP(F72,MatrizHDUniclass!$A:$AN,32,0),"NA") -> NA | N72: =IFERROR(VLOOKUP(F72,MatrizHDUniclass!$A:$AN,33,0),"NA") -> NA | O72: =IFERROR(VLOOKUP(F72,MatrizHDUniclass!$A:$AN,26,0),"NA") -> NA | P72: =IFERROR(VLOOKUP(F72,MatrizHDUniclass!$A:$AN,34,0),"NA") -> NA | Q72: =IFERROR(VLOOKUP(F72,MatrizHDUniclass!$A:$AN,35,0),"NA") -> NA | R72: =IFERROR(VLOOKUP(F72,MatrizHDUniclass!$A:$AN,36,0),"NA") -> NA | S72: =IFERROR(VLOOKUP(F72,MatrizHDUniclass!$A:$AN,37,0),"NA") -> NA | T72: =IFERROR(VLOOKUP(F72,MatrizHDUniclass!$A:$AN,38,0),"NA") -> NA | U72: =IFERROR(VLOOKUP(F72,MatrizHDUniclass!$A:$AN,39,0),"NA") -> NA | V72: =IFERROR(VLOOKUP(F72,MatrizHDUniclass!$A:$AN,40,0),"NA") -> NA | W72: Cambio de Asignación a Anderson Garcia | X72: 46010
A73: 45254 | B73: PALMIRA | C73: 5.5 | D73: (M) .CO | E73: Microsoft 365 Empresa Básico | F73: 1113674885 | G73: steven.cedano@grupoconectar.co | H73: Steven Alfonso Cedano Mendez "Baja" | I73: =IFERROR(VLOOKUP(F73,MatrizHDUniclass!$A:$AN,3,0),"NA") -> NA | J73: =IFERROR(VLOOKUP(F73,MatrizHDUniclass!$A:$AN,19,0),"NA") -> NA | K73: =IFERROR(VLOOKUP(F73,MatrizHDUniclass!$A:$AN,24,0),"NA") -> NA | L73: =IFERROR(VLOOKUP(F73,MatrizHDUniclass!$A:$AN,31,0),"NA") -> NA | M73: =IFERROR(VLOOKUP(F73,MatrizHDUniclass!$A:$AN,32,0),"NA") -> NA | N73: =IFERROR(VLOOKUP(F73,MatrizHDUniclass!$A:$AN,33,0),"NA") -> NA | O73: =IFERROR(VLOOKUP(F73,MatrizHDUniclass!$A:$AN,26,0),"NA") -> NA | P73: =IFERROR(VLOOKUP(F73,MatrizHDUniclass!$A:$AN,34,0),"NA") -> NA | Q73: =IFERROR(VLOOKUP(F73,MatrizHDUniclass!$A:$AN,35,0),"NA") -> NA | R73: =IFERROR(VLOOKUP(F73,MatrizHDUniclass!$A:$AN,36,0),"NA") -> NA | S73: =IFERROR(VLOOKUP(F73,MatrizHDUniclass!$A:$AN,37,0),"NA") -> NA | T73: =IFERROR(VLOOKUP(F73,MatrizHDUniclass!$A:$AN,38,0),"NA") -> NA | U73: =IFERROR(VLOOKUP(F73,MatrizHDUniclass!$A:$AN,39,0),"NA") -> NA | V73: =IFERROR(VLOOKUP(F73,MatrizHDUniclass!$A:$AN,40,0),"NA") -> NA | W73: Eliminado con Backup | X73: 46010
A74: 45610 | B74: IBAGUE | C74: 5.5 | D74: (M) .CO | E74: Microsoft 365 Empresa Básico | F74: 1010037648 | G74: ana.infante@grupoconectar.co | H74: Ana Milena Infante Maldonado (Linda Sierra)"Baja" | I74: =IFERROR(VLOOKUP(F74,MatrizHDUniclass!$A:$AN,3,0),"NA") -> NA | J74: =IFERROR(VLOOKUP(F74,MatrizHDUniclass!$A:$AN,19,0),"NA") -> NA | K74: =IFERROR(VLOOKUP(F74,MatrizHDUniclass!$A:$AN,24,0),"NA") -> NA | L74: =IFERROR(VLOOKUP(F74,MatrizHDUniclass!$A:$AN,31,0),"NA") -> NA | M74: =IFERROR(VLOOKUP(F74,MatrizHDUniclass!$A:$AN,32,0),"NA") -> NA | N74: =IFERROR(VLOOKUP(F74,MatrizHDUniclass!$A:$AN,33,0),"NA") -> NA | O74: =IFERROR(VLOOKUP(F74,MatrizHDUniclass!$A:$AN,26,0),"NA") -> NA | P74: =IFERROR(VLOOKUP(F74,MatrizHDUniclass!$A:$AN,34,0),"NA") -> NA | Q74: =IFERROR(VLOOKUP(F74,MatrizHDUniclass!$A:$AN,35,0),"NA") -> NA | R74: =IFERROR(VLOOKUP(F74,MatrizHDUniclass!$A:$AN,36,0),"NA") -> NA | S74: =IFERROR(VLOOKUP(F74,MatrizHDUniclass!$A:$AN,37,0),"NA") -> NA | T74: =IFERROR(VLOOKUP(F74,MatrizHDUniclass!$A:$AN,38,0),"NA") -> NA | U74: =IFERROR(VLOOKUP(F74,MatrizHDUniclass!$A:$AN,39,0),"NA") -> NA | V74: =IFERROR(VLOOKUP(F74,MatrizHDUniclass!$A:$AN,40,0),"NA") -> NA | W74: Eliminado con Backup | X74: 46010
A75: 44742 | B75: MEDELLIN | C75: 5.5 | D75: (M) .CO | E75: Microsoft 365 Empresa Básico | F75: 71753073 | G75: wilton.avedano@grupoconectar.co | H75: (Crhistofer García) | I75: AVEDANO DIAZ WILTON CESAR | J75: COORDINADOR OPERACION FLM | K75: IGAM | L75: INGENIERIA-GENERAL | M75: REG ANTIO | N75: MEDELLIN | O75: HNAL | P75: HUAWEI | Q75: NUEVOS NEG | R75: FLM ALL IN ONE | S75: CLIENTES | T75: CONECTAR TV | U75: INGENIERIA | V75: OPERATIVO | W75: Cambio de Asignación a Camilo Gómez | X75: 46013
A76: 45245 | B76: CALI | C76: 4.53 | D76: (M) .CO | E76: Exchange Online (Plan 1) | F76: 25390028 | G76: angelica.ramirez@grupoconectar.co | H76: ANGELICA RAMIREZ DIAZ "Baja" | I76: =IFERROR(VLOOKUP(F76,MatrizHDUniclass!$A:$AN,3,0),"NA") -> NA | J76: =IFERROR(VLOOKUP(F76,MatrizHDUniclass!$A:$AN,19,0),"NA") -> NA | K76: =IFERROR(VLOOKUP(F76,MatrizHDUniclass!$A:$AN,24,0),"NA") -> NA | L76: =IFERROR(VLOOKUP(F76,MatrizHDUniclass!$A:$AN,31,0),"NA") -> NA | M76: =IFERROR(VLOOKUP(F76,MatrizHDUniclass!$A:$AN,32,0),"NA") -> NA | N76: =IFERROR(VLOOKUP(F76,MatrizHDUniclass!$A:$AN,33,0),"NA") -> NA | O76: =IFERROR(VLOOKUP(F76,MatrizHDUniclass!$A:$AN,26,0),"NA") -> NA | P76: =IFERROR(VLOOKUP(F76,MatrizHDUniclass!$A:$AN,34,0),"NA") -> NA | Q76: =IFERROR(VLOOKUP(F76,MatrizHDUniclass!$A:$AN,35,0),"NA") -> NA | R76: =IFERROR(VLOOKUP(F76,MatrizHDUniclass!$A:$AN,36,0),"NA") -> NA | S76: =IFERROR(VLOOKUP(F76,MatrizHDUniclass!$A:$AN,37,0),"NA") -> NA | T76: =IFERROR(VLOOKUP(F76,MatrizHDUniclass!$A:$AN,38,0),"NA") -> NA | U76: =IFERROR(VLOOKUP(F76,MatrizHDUniclass!$A:$AN,39,0),"NA") -> NA | V76: =IFERROR(VLOOKUP(F76,MatrizHDUniclass!$A:$AN,40,0),"NA") -> NA | W76: Eliminado con Backup | X76: 46013
A77: 44642 | B77: CALI | C77: 5.5 | D77: (M) .CO | E77: Microsoft 365 Empresa Básico | F77: 1104700436 | G77: miguel.alonso@grupoconectar.co | H77: "BAJA" | I77: =IFERROR(VLOOKUP(F77,MatrizHDUniclass!$A:$AN,3,0),"NA") -> NA | J77: =IFERROR(VLOOKUP(F77,MatrizHDUniclass!$A:$AN,19,0),"NA") -> NA | K77: =IFERROR(VLOOKUP(F77,MatrizHDUniclass!$A:$AN,24,0),"NA") -> NA | L77: =IFERROR(VLOOKUP(F77,MatrizHDUniclass!$A:$AN,31,0),"NA") -> NA | M77: =IFERROR(VLOOKUP(F77,MatrizHDUniclass!$A:$AN,32,0),"NA") -> NA | N77: =IFERROR(VLOOKUP(F77,MatrizHDUniclass!$A:$AN,33,0),"NA") -> NA | O77: =IFERROR(VLOOKUP(F77,MatrizHDUniclass!$A:$AN,26,0),"NA") -> NA | P77: =IFERROR(VLOOKUP(F77,MatrizHDUniclass!$A:$AN,34,0),"NA") -> NA | Q77: =IFERROR(VLOOKUP(F77,MatrizHDUniclass!$A:$AN,35,0),"NA") -> NA | R77: =IFERROR(VLOOKUP(F77,MatrizHDUniclass!$A:$AN,36,0),"NA") -> NA | S77: =IFERROR(VLOOKUP(F77,MatrizHDUniclass!$A:$AN,37,0),"NA") -> NA | T77: =IFERROR(VLOOKUP(F77,MatrizHDUniclass!$A:$AN,38,0),"NA") -> NA | U77: =IFERROR(VLOOKUP(F77,MatrizHDUniclass!$A:$AN,39,0),"NA") -> NA | V77: =IFERROR(VLOOKUP(F77,MatrizHDUniclass!$A:$AN,40,0),"NA") -> NA | W77: Eliminado con Backup | X77: 46014
A78: 45244 | B78: FLORENCIA | C78: 5.5 | D78: (M) .CO | E78: Microsoft 365 Empresa Básico | F78: 1083882842 | G78: walter.burbano@grupoconectar.co | H78: Walter Burbano "BAJA" | I78: =IFERROR(VLOOKUP(F78,MatrizHDUniclass!$A:$AN,3,0),"NA") -> NA | J78: =IFERROR(VLOOKUP(F78,MatrizHDUniclass!$A:$AN,19,0),"NA") -> NA | K78: =IFERROR(VLOOKUP(F78,MatrizHDUniclass!$A:$AN,24,0),"NA") -> NA | L78: =IFERROR(VLOOKUP(F78,MatrizHDUniclass!$A:$AN,31,0),"NA") -> NA | M78: =IFERROR(VLOOKUP(F78,MatrizHDUniclass!$A:$AN,32,0),"NA") -> NA | N78: =IFERROR(VLOOKUP(F78,MatrizHDUniclass!$A:$AN,33,0),"NA") -> NA | O78: =IFERROR(VLOOKUP(F78,MatrizHDUniclass!$A:$AN,26,0),"NA") -> NA | P78: =IFERROR(VLOOKUP(F78,MatrizHDUniclass!$A:$AN,34,0),"NA") -> NA | Q78: =IFERROR(VLOOKUP(F78,MatrizHDUniclass!$A:$AN,35,0),"NA") -> NA | R78: =IFERROR(VLOOKUP(F78,MatrizHDUniclass!$A:$AN,36,0),"NA") -> NA | S78: =IFERROR(VLOOKUP(F78,MatrizHDUniclass!$A:$AN,37,0),"NA") -> NA | T78: =IFERROR(VLOOKUP(F78,MatrizHDUniclass!$A:$AN,38,0),"NA") -> NA | U78: =IFERROR(VLOOKUP(F78,MatrizHDUniclass!$A:$AN,39,0),"NA") -> NA | V78: =IFERROR(VLOOKUP(F78,MatrizHDUniclass!$A:$AN,40,0),"NA") -> NA | W78: Eliminado con Backup | X78: 46015
A79: 18/06/2025 | B79: BOGOTA | C79: 5.5 | D79: (M) .CO | E79: Microsoft 365 Empresa Básico | F79: 1022400006 | G79: jhonatan.rodriguez@grupoconectar.co | H79: ERIKA JOHANA CASTELLANOS "Baja" | I79: =IFERROR(VLOOKUP(F79,MatrizHDUniclass!$A:$AN,3,0),"NA") -> NA | J79: =IFERROR(VLOOKUP(F79,MatrizHDUniclass!$A:$AN,19,0),"NA") -> NA | K79: =IFERROR(VLOOKUP(F79,MatrizHDUniclass!$A:$AN,24,0),"NA") -> NA | L79: =IFERROR(VLOOKUP(F79,MatrizHDUniclass!$A:$AN,31,0),"NA") -> NA | M79: =IFERROR(VLOOKUP(F79,MatrizHDUniclass!$A:$AN,32,0),"NA") -> NA | N79: =IFERROR(VLOOKUP(F79,MatrizHDUniclass!$A:$AN,33,0),"NA") -> NA | O79: =IFERROR(VLOOKUP(F79,MatrizHDUniclass!$A:$AN,26,0),"NA") -> NA | P79: =IFERROR(VLOOKUP(F79,MatrizHDUniclass!$A:$AN,34,0),"NA") -> NA | Q79: =IFERROR(VLOOKUP(F79,MatrizHDUniclass!$A:$AN,35,0),"NA") -> NA | R79: =IFERROR(VLOOKUP(F79,MatrizHDUniclass!$A:$AN,36,0),"NA") -> NA | S79: =IFERROR(VLOOKUP(F79,MatrizHDUniclass!$A:$AN,37,0),"NA") -> NA | T79: =IFERROR(VLOOKUP(F79,MatrizHDUniclass!$A:$AN,38,0),"NA") -> NA | U79: =IFERROR(VLOOKUP(F79,MatrizHDUniclass!$A:$AN,39,0),"NA") -> NA | V79: =IFERROR(VLOOKUP(F79,MatrizHDUniclass!$A:$AN,40,0),"NA") -> NA | W79: Eliminado con Backup | X79: 46015
A80: 45019 | B80: BOGOTA | C80: 5.5 | D80: (M) .CO | E80: Microsoft 365 Empresa Básico | F80: 1023003268 | G80: mychel.apache@grupoconectar.co | H80: "BAJA" | I80: =IFERROR(VLOOKUP(F80,MatrizHDUniclass!$A:$AN,3,0),"NA") -> NA | J80: =IFERROR(VLOOKUP(F80,MatrizHDUniclass!$A:$AN,19,0),"NA") -> NA | K80: =IFERROR(VLOOKUP(F80,MatrizHDUniclass!$A:$AN,24,0),"NA") -> NA | L80: =IFERROR(VLOOKUP(F80,MatrizHDUniclass!$A:$AN,31,0),"NA") -> NA | M80: =IFERROR(VLOOKUP(F80,MatrizHDUniclass!$A:$AN,32,0),"NA") -> NA | N80: =IFERROR(VLOOKUP(F80,MatrizHDUniclass!$A:$AN,33,0),"NA") -> NA | O80: =IFERROR(VLOOKUP(F80,MatrizHDUniclass!$A:$AN,26,0),"NA") -> NA | P80: =IFERROR(VLOOKUP(F80,MatrizHDUniclass!$A:$AN,34,0),"NA") -> NA | Q80: =IFERROR(VLOOKUP(F80,MatrizHDUniclass!$A:$AN,35,0),"NA") -> NA | R80: =IFERROR(VLOOKUP(F80,MatrizHDUniclass!$A:$AN,36,0),"NA") -> NA | S80: =IFERROR(VLOOKUP(F80,MatrizHDUniclass!$A:$AN,37,0),"NA") -> NA | T80: =IFERROR(VLOOKUP(F80,MatrizHDUniclass!$A:$AN,38,0),"NA") -> NA | U80: =IFERROR(VLOOKUP(F80,MatrizHDUniclass!$A:$AN,39,0),"NA") -> NA | V80: =IFERROR(VLOOKUP(F80,MatrizHDUniclass!$A:$AN,40,0),"NA") -> NA | W80: Eliminado con Backup | X80: 46020
A81: 44652 | B81: CALI | C81: 5.5 | D81: (M) .CO | E81: Microsoft 365 Empresa Básico | F81: 1019020725 | G81: german.molano@grupoconectar.co | H81: "Baja" | I81: =IFERROR(VLOOKUP(F81,MatrizHDUniclass!$A:$AN,3,0),"NA") -> NA | J81: =IFERROR(VLOOKUP(F81,MatrizHDUniclass!$A:$AN,19,0),"NA") -> NA | K81: =IFERROR(VLOOKUP(F81,MatrizHDUniclass!$A:$AN,24,0),"NA") -> NA | L81: =IFERROR(VLOOKUP(F81,MatrizHDUniclass!$A:$AN,31,0),"NA") -> NA | M81: =IFERROR(VLOOKUP(F81,MatrizHDUniclass!$A:$AN,32,0),"NA") -> NA | N81: =IFERROR(VLOOKUP(F81,MatrizHDUniclass!$A:$AN,33,0),"NA") -> NA | O81: =IFERROR(VLOOKUP(F81,MatrizHDUniclass!$A:$AN,26,0),"NA") -> NA | P81: =IFERROR(VLOOKUP(F81,MatrizHDUniclass!$A:$AN,34,0),"NA") -> NA | Q81: =IFERROR(VLOOKUP(F81,MatrizHDUniclass!$A:$AN,35,0),"NA") -> NA | R81: =IFERROR(VLOOKUP(F81,MatrizHDUniclass!$A:$AN,36,0),"NA") -> NA | S81: =IFERROR(VLOOKUP(F81,MatrizHDUniclass!$A:$AN,37,0),"NA") -> NA | T81: =IFERROR(VLOOKUP(F81,MatrizHDUniclass!$A:$AN,38,0),"NA") -> NA | U81: =IFERROR(VLOOKUP(F81,MatrizHDUniclass!$A:$AN,39,0),"NA") -> NA | V81: =IFERROR(VLOOKUP(F81,MatrizHDUniclass!$A:$AN,40,0),"NA") -> NA | W81: Eliminado con Backup | X81: 46017
A82: 44575 | B82: BOGOTA | C82: 5.5 | D82: (M) .CO | E82: Microsoft 365 Empresa Básico | F82: 1005460931 | G82: miyer.mosquera@grupoconectar.co | I82: =IFERROR(VLOOKUP(F82,MatrizHDUniclass!$A:$AN,3,0),"NA") -> MOSQUERA MOSQUERA MIYER ANDRES | J82: =IFERROR(VLOOKUP(F82,MatrizHDUniclass!$A:$AN,19,0),"NA") -> COORDINADOR OPERACION | K82: =IFERROR(VLOOKUP(F82,MatrizHDUniclass!$A:$AN,24,0),"NA") -> IGCB | L82: =IFERROR(VLOOKUP(F82,MatrizHDUniclass!$A:$AN,31,0),"NA") -> INGENIERIA-GENERAL | M82: =IFERROR(VLOOKUP(F82,MatrizHDUniclass!$A:$AN,32,0),"NA") -> REG CENTRO | N82: =IFERROR(VLOOKUP(F82,MatrizHDUniclass!$A:$AN,33,0),"NA") -> BOGOTA | O82: =IFERROR(VLOOKUP(F82,MatrizHDUniclass!$A:$AN,26,0),"NA") -> YSAF | P82: =IFERROR(VLOOKUP(F82,MatrizHDUniclass!$A:$AN,34,0),"NA") -> ZTE | Q82: =IFERROR(VLOOKUP(F82,MatrizHDUniclass!$A:$AN,35,0),"NA") -> SOLU FIJAS | R82: =IFERROR(VLOOKUP(F82,MatrizHDUniclass!$A:$AN,36,0),"NA") -> APROV FIBRA | S82: =IFERROR(VLOOKUP(F82,MatrizHDUniclass!$A:$AN,37,0),"NA") -> CLIENTES | T82: =IFERROR(VLOOKUP(F82,MatrizHDUniclass!$A:$AN,38,0),"NA") -> CONECTAR TV | U82: =IFERROR(VLOOKUP(F82,MatrizHDUniclass!$A:$AN,39,0),"NA") -> INGENIERIA | V82: =IFERROR(VLOOKUP(F82,MatrizHDUniclass!$A:$AN,40,0),"NA") -> ADMINISTRATIVO | W82: Modificacion de Licencia a Standard | X82: 46020
A83: 45222 | B83: BOGOTA | C83: 11.3 | D83: (M) .CO | E83: Microsoft 365 Empresa Estándar | F83: 79638719 | G83: gestiondepermisos@grupoconectar.co | H83: (Jose Gómez) | I83: =IFERROR(VLOOKUP(F83,MatrizHDUniclass!$A:$AN,3,0),"NA") -> GOMEZ FRANCO JOSE ALIRIO | J83: =IFERROR(VLOOKUP(F83,MatrizHDUniclass!$A:$AN,19,0),"NA") -> JEFE OPERACIONES | K83: =IFERROR(VLOOKUP(F83,MatrizHDUniclass!$A:$AN,24,0),"NA") -> IGTN | L83: =IFERROR(VLOOKUP(F83,MatrizHDUniclass!$A:$AN,31,0),"NA") -> INGENIERIA-GENERAL | M83: =IFERROR(VLOOKUP(F83,MatrizHDUniclass!$A:$AN,32,0),"NA") -> TRANSVERSAL | N83: =IFERROR(VLOOKUP(F83,MatrizHDUniclass!$A:$AN,33,0),"NA") -> NACIONAL | O83: =IFERROR(VLOOKUP(F83,MatrizHDUniclass!$A:$AN,26,0),"NA") -> BSCL | P83: =IFERROR(VLOOKUP(F83,MatrizHDUniclass!$A:$AN,34,0),"NA") -> ATP | Q83: =IFERROR(VLOOKUP(F83,MatrizHDUniclass!$A:$AN,35,0),"NA") -> SOLU FIJAS | R83: =IFERROR(VLOOKUP(F83,MatrizHDUniclass!$A:$AN,36,0),"NA") -> COLOS | S83: =IFERROR(VLOOKUP(F83,MatrizHDUniclass!$A:$AN,37,0),"NA") -> CLIENTES | T83: =IFERROR(VLOOKUP(F83,MatrizHDUniclass!$A:$AN,38,0),"NA") -> CONECTAR TV | U83: =IFERROR(VLOOKUP(F83,MatrizHDUniclass!$A:$AN,39,0),"NA") -> INGENIERIA | V83: =IFERROR(VLOOKUP(F83,MatrizHDUniclass!$A:$AN,40,0),"NA") -> ADMINISTRATIVO | W83: Modificación Nombre a gestiondeproyectos | X83: 46021
A84: 44503 | B84: CALI | C84: 5.5 | D84: (M) .CO | E84: Microsoft 365 Empresa Básico | F84: 1110482789 | G84: johan.velasquez@grupoconectar.co | H84: "Baja" | I84: =IFERROR(VLOOKUP(F84,MatrizHDUniclass!$A:$AN,3,0),"NA") -> NA | J84: =IFERROR(VLOOKUP(F84,MatrizHDUniclass!$A:$AN,19,0),"NA") -> NA | K84: =IFERROR(VLOOKUP(F84,MatrizHDUniclass!$A:$AN,24,0),"NA") -> NA | L84: =IFERROR(VLOOKUP(F84,MatrizHDUniclass!$A:$AN,31,0),"NA") -> NA | M84: =IFERROR(VLOOKUP(F84,MatrizHDUniclass!$A:$AN,32,0),"NA") -> NA | N84: =IFERROR(VLOOKUP(F84,MatrizHDUniclass!$A:$AN,33,0),"NA") -> NA | O84: =IFERROR(VLOOKUP(F84,MatrizHDUniclass!$A:$AN,26,0),"NA") -> NA | P84: =IFERROR(VLOOKUP(F84,MatrizHDUniclass!$A:$AN,34,0),"NA") -> NA | Q84: =IFERROR(VLOOKUP(F84,MatrizHDUniclass!$A:$AN,35,0),"NA") -> NA | R84: =IFERROR(VLOOKUP(F84,MatrizHDUniclass!$A:$AN,36,0),"NA") -> NA | S84: =IFERROR(VLOOKUP(F84,MatrizHDUniclass!$A:$AN,37,0),"NA") -> NA | T84: =IFERROR(VLOOKUP(F84,MatrizHDUniclass!$A:$AN,38,0),"NA") -> NA | U84: =IFERROR(VLOOKUP(F84,MatrizHDUniclass!$A:$AN,39,0),"NA") -> NA | V84: =IFERROR(VLOOKUP(F84,MatrizHDUniclass!$A:$AN,40,0),"NA") -> NA | W84: Eliminado con Backup | X84: 46021
